Workbook

Sheet Instructions
A1: 24-Month Cash Flow Forecast Model – Aurelia Developments LLC
A3: Purpose | B3: Institutional-quality monthly cash flow forecast for a Dubai luxury real estate developer, built for FP&A, private equity diligence, treasury planning, and project finance review.
A5: Color coding | B5: Blue font = hard-coded inputs; Black font = formulas; Green font = links from other sheets; Grey fill = headers/static labels; Light yellow fill = scenario toggle inputs.
A7: Model structure | B7: 1) Scenario Toggle 2) Assumptions 3) Project Database 4) Operating Schedules 5) Financing Schedules 6) Consolidated Cash Flow 7) Liquidity 8) Sensitivity 9) Dashboard
A9: How to use | B9: Select Base Case / Downside Case / Upside Case on the Scenario Toggle sheet. Update only blue-font assumption cells. All monthly schedules and outputs will update automatically.
A11: Output horizon | B11: Monthly forecast covering Apr-26 to Mar-28 (24 months).
A13: Checks | B13: The model contains schedule links, debt roll-forward logic, cash roll-forward logic, escrow mechanics, and liquidity outputs intended to mimic a PE / lender review model.

Sheet Scenario Toggle
A1: Scenario Control Panel
A3: Active Scenario | B3: Base Case
A4: Description | B4: Select scenario from dropdown. All key drivers below flow into Assumptions.
A6: Scenario Multipliers
A7: Driver | B7: Base Case | C7: Downside Case | D7: Upside Case | E7: Selected Value | F7: Unit
A8: Sales velocity multiplier | B8: 1 | C8: 0.8 | D8: 1.15 | E8: =IF($B$3="Base Case",B8,IF($B$3="Downside Case",C8,D8)) -> 1 | F8: x
A9: Sales price growth p.m. | B9: 0.004 | C9: 0.001 | D9: 0.006 | E9: =IF($B$3="Base Case",B9,IF($B$3="Downside Case",C9,D9)) -> 0.004 | F9: %
A10: Cancellation rate | B10: 0.02 | C10: 0.05 | D10: 0.01 | E10: =IF($B$3="Base Case",B10,IF($B$3="Downside Case",C10,D10)) -> 0.02 | F10: %
A11: Construction cost overrun | B11: 0 | C11: 0.08 | D11: -0.01 | E11: =IF($B$3="Base Case",B11,IF($B$3="Downside Case",C11,D11)) -> 0 | F11: %
A12: Construction delay (months) | B12: 0 | C12: 3 | D12: 0 | E12: =IF($B$3="Base Case",B12,IF($B$3="Downside Case",C12,D12)) -> 0 | F12: months
A13: Interest rate premium | B13: 0 | C13: 0.01 | D13: -0.005 | E13: =IF($B$3="Base Case",B13,IF($B$3="Downside Case",C13,D13)) -> 0 | F13: %
A14: Rent / hospitality multiplier | B14: 1 | C14: 0.9 | D14: 1.08 | E14: =IF($B$3="Base Case",B14,IF($B$3="Downside Case",C14,D14)) -> 1 | F14: x

Sheet Assumptions
A1: Assumptions
A3: Macro Assumptions
A4: Assumption | B4: Base | C4: Downside | D4: Upside | E4: Selected | F4: Unit | G4: Source / Note
A5: Inflation p.a. | B5: 0.025 | C5: 0.035 | D5: 0.02 | E5: =IF('Scenario Toggle'!$B$3="Base Case",B5,IF('Scenario Toggle'!$B$3="Downside Case",C5,D5)) -> 0.025 | F5: % | G5: Illustrative management planning assumption
A6: Construction cost escalation p.a. | B6: 0.03 | C6: 0.07 | D6: 0.02 | E6: =IF('Scenario Toggle'!$B$3="Base Case",B6,IF('Scenario Toggle'!$B$3="Downside Case",C6,D6)) -> 0.03 | F6: % | G6: Illustrative
A7: Base borrowing rate p.a. | B7: 0.065 | C7: 0.065 | D7: 0.065 | E7: =IF('Scenario Toggle'!$B$3="Base Case",B7,IF('Scenario Toggle'!$B$3="Downside Case",C7,D7)) -> 0.065 | F7: % | G7: Illustrative
A8: FX AED/USD | B8: 3.6725 | C8: 3.6725 | D8: 3.6725 | E8: =IF('Scenario Toggle'!$B$3="Base Case",B8,IF('Scenario Toggle'!$B$3="Downside Case",C8,D8)) -> 3.6725 | F8: x | G8: AED peg
A9: Minimum cash threshold | B9: 75000000 | C9: 100000000 | D9: 75000000 | E9: =IF('Scenario Toggle'!$B$3="Base Case",B9,IF('Scenario Toggle'!$B$3="Downside Case",C9,D9)) -> 75000000 | F9: AED | G9: Treasury policy
A10: Undrawn corporate revolver | B10: 250000000 | C10: 200000000 | D10: 300000000 | E10: =IF('Scenario Toggle'!$B$3="Base Case",B10,IF('Scenario Toggle'!$B$3="Downside Case",C10,D10)) -> 250000000 | F10: AED | G10: Available liquidity support
A12: Sales Assumptions
A13: Assumption | B13: Base | C13: Downside | D13: Upside | E13: Selected | F13: Unit | G13: Source / Note
A14: Booking payment | B14: 0.2 | C14: 0.2 | D14: 0.2 | E14: =IF('Scenario Toggle'!$B$3="Base Case",B14,IF('Scenario Toggle'!$B$3="Downside Case",C14,D14)) -> 0.2 | F14: % | G14: Dubai off-plan
A15: Milestone 1 payment | B15: 0.2 | C15: 0.2 | D15: 0.2 | E15: =IF('Scenario Toggle'!$B$3="Base Case",B15,IF('Scenario Toggle'!$B$3="Downside Case",C15,D15)) -> 0.2 | F15: % | G15: 6 months after sale
A16: Milestone 2 payment | B16: 0.2 | C16: 0.2 | D16: 0.2 | E16: =IF('Scenario Toggle'!$B$3="Base Case",B16,IF('Scenario Toggle'!$B$3="Downside Case",C16,D16)) -> 0.2 | F16: % | G16: 12 months after sale
A17: Milestone 3 payment | B17: 0.2 | C17: 0.2 | D17: 0.2 | E17: =IF('Scenario Toggle'!$B$3="Base Case",B17,IF('Scenario Toggle'!$B$3="Downside Case",C17,D17)) -> 0.2 | F17: % | G17: 18 months after sale
A18: Handover payment | B18: 0.2 | C18: 0.2 | D18: 0.2 | E18: =IF('Scenario Toggle'!$B$3="Base Case",B18,IF('Scenario Toggle'!$B$3="Downside Case",C18,D18)) -> 0.2 | F18: % | G18: At completion / handover
A19: Monthly sales commission | B19: 0.03 | C19: 0.035 | D19: 0.028 | E19: =IF('Scenario Toggle'!$B$3="Base Case",B19,IF('Scenario Toggle'!$B$3="Downside Case",C19,D19)) -> 0.03 | F19: % | G19: As % of sales value
A20: Monthly rental growth p.a. | B20: 0.03 | C20: 0.01 | D20: 0.04 | E20: =IF('Scenario Toggle'!$B$3="Base Case",B20,IF('Scenario Toggle'!$B$3="Downside Case",C20,D20)) -> 0.03 | F20: % | G20: Portfolio rental growth
A21: Monthly hospitality growth p.a. | B21: 0.04 | C21: 0.015 | D21: 0.05 | E21: =IF('Scenario Toggle'!$B$3="Base Case",B21,IF('Scenario Toggle'!$B$3="Downside Case",C21,D21)) -> 0.04 | F21: % | G21: Hospitality revenue growth
A23: Corporate Assumptions
A24: Assumption | B24: Base | C24: Downside | D24: Upside | E24: Selected | F24: Unit | G24: Source / Note
A25: Executive salaries (monthly) | B25: 2800000 | C25: 2800000 | D25: 2800000 | E25: =IF('Scenario Toggle'!$B$3="Base Case",B25,IF('Scenario Toggle'!$B$3="Downside Case",C25,D25)) -> 2800000 | F25: AED | G25: Illustrative
A26: Employee payroll (monthly) | B26: 5200000 | C26: 5200000 | D26: 5200000 | E26: =IF('Scenario Toggle'!$B$3="Base Case",B26,IF('Scenario Toggle'!$B$3="Downside Case",C26,D26)) -> 5200000 | F26: AED | G26: Illustrative
A27: Office rent (monthly) | B27: 650000 | C27: 650000 | D27: 650000 | E27: =IF('Scenario Toggle'!$B$3="Base Case",B27,IF('Scenario Toggle'!$B$3="Downside Case",C27,D27)) -> 650000 | F27: AED | G27: Illustrative
A28: Insurance (monthly) | B28: 350000 | C28: 350000 | D28: 350000 | E28: =IF('Scenario Toggle'!$B$3="Base Case",B28,IF('Scenario Toggle'!$B$3="Downside Case",C28,D28)) -> 350000 | F28: AED | G28: Illustrative
A29: Legal & professional fees (monthly) | B29: 900000 | C29: 1100000 | D29: 850000 | E29: =IF('Scenario Toggle'!$B$3="Base Case",B29,IF('Scenario Toggle'!$B$3="Downside Case",C29,D29)) -> 900000 | F29: AED | G29: Illustrative
A30: IT costs (monthly) | B30: 450000 | C30: 500000 | D30: 450000 | E30: =IF('Scenario Toggle'!$B$3="Base Case",B30,IF('Scenario Toggle'!$B$3="Downside Case",C30,D30)) -> 450000 | F30: AED | G30: Illustrative
A31: General admin (monthly) | B31: 750000 | C31: 800000 | D31: 700000 | E31: =IF('Scenario Toggle'!$B$3="Base Case",B31,IF('Scenario Toggle'!$B$3="Downside Case",C31,D31)) -> 750000 | F31: AED | G31: Illustrative
A32: Payroll growth p.a. | B32: 0.05 | C32: 0.06 | D32: 0.045 | E32: =IF('Scenario Toggle'!$B$3="Base Case",B32,IF('Scenario Toggle'!$B$3="Downside Case",C32,D32)) -> 0.05 | F32: % | G32: Escalation
A33: Admin cost growth p.a. | B33: 0.03 | C33: 0.05 | D33: 0.025 | E33: =IF('Scenario Toggle'!$B$3="Base Case",B33,IF('Scenario Toggle'!$B$3="Downside Case",C33,D33)) -> 0.03 | F33: % | G33: Escalation

Sheet Project Database
A1: Development Project Database
A3: Project Name | B3: Location | C3: Units | D3: Launch Date | E3: Completion Date | F3: Project Budget | G3: Avg Saleable Sqft / Unit | H3: Initial ASP / Sqft | I3: Gross Margin Target | J3: Opening Escrow | K3: Opening Debt | L3: Land / Predev Spend To Date
A4: Marina Residences Tower | B4: Dubai Marina | C4: 180 | D4: 46113 | E4: 46631 | F4: 900000000 | G4: 5000 | H4: 3200 | I4: 0.15 | J4: 120000000 | K4: 220000000 | L4: 180000000
A5: Palm Waterfront Villas | B5: Palm Jumeirah | C5: 60 | D5: 46143 | E5: 46722 | F5: 650000000 | G5: 7800 | H5: 4500 | I5: 0.18 | J5: 80000000 | K5: 140000000 | L5: 160000000
A6: Downtown Branded Residences | B6: Downtown Dubai | C6: 220 | D6: 46204 | E6: 46813 | F6: 1100000000 | G6: 4200 | H6: 2900 | I6: 0.14 | J6: 150000000 | K6: 260000000 | L6: 220000000
A7: Jumeirah Mixed-Use Development | B7: Jumeirah | C7: 140 | D7: 46174 | E7: 46784 | F7: 850000000 | G7: 3900 | H7: 2600 | I7: 0.12 | J7: 100000000 | K7: 180000000 | L7: 200000000
A9: Total / Average | C9: =SUM(C4:C8) -> 600 | F9: =SUM(F4:F8) -> 3500000000 | G9: =SUM(G4:G8) -> 20900 | H9: =SUM(H4:H8) -> 13200 | I9: =AVERAGE(I4:I8) -> 0.1475 | J9: =SUM(J4:J8) -> 450000000 | K9: =SUM(K4:K8) -> 800000000 | L9: =SUM(L4:L8) -> 760000000

Sheet Sales Forecast
A1: Monthly Sales Forecast Model
A3: Project | B3: Metric | C3: 46113 | D3: 46143 | E3: 46174 | F3: 46204 | G3: 46235 | H3: 46266 | I3: 46296 | J3: 46327 | K3: 46357 | L3: 46388 | M3: 46419 | N3: 46447 | O3: 46478 | P3: 46508 | Q3: 46539 | R3: 46569 | S3: 46600 | T3: 46631 | U3: 46661 | V3: 46692 | W3: 46722 | X3: 46753 | Y3: 46784 | Z3: 46813
A4: Marina Residences Tower | B4: Units Available BOY | C4: ='Project Database'!$C$4 -> 180 | D4: =C4-C7 -> 170.2 | E4: =D4-D7 -> 160.4 | F4: =E4-E7 -> 150.6 | G4: =F4-F7 -> 140.8 | H4: =G4-G7 -> 131 | I4: =H4-H7 -> 121.2 | J4: =I4-I7 -> 111.4 | K4: =J4-J7 -> 101.6 | ... Z4: =Y4-Y7 -> 3.6
B5: Units Sold | C5: =IF(AND(C$3>='Project Database'!$D$4,C$3<=EDATE('Project Database'!$E$4,ROUND('Scenario Toggle'!$E$12,0))),MIN(ROUND('Project Database'!$C$4/MAX(1,DATEDIF('Project Database'!$D$4,EDATE('Project Database'!$E$4,ROUND('Scenario Toggle'!$E$12,0)),"m")+1)*'Scenario Toggle'!$E$8,0),C4),0) -> 10 | D5: =IF(AND(D$3>='Project Database'!$D$4,D$3<=EDATE('Project Database'!$E$4,ROUND('Scenario Toggle'!$E$12,0))),MIN(ROUND('Project Database'!$C$4/MAX(1,DATEDIF('Project Database'!$D$4,EDATE('Project Database'!$E$4,ROUND('Scenario Toggle'!$E$12,0)),"m")+1)*'Scenario Toggle'!$E$8,0),D4),0) -> 10 | E5: =IF(AND(E$3>='Project Database'!$D$4,E$3<=EDATE('Project Database'!$E$4,ROUND('Scenario Toggle'!$E$12,0))),MIN(ROUND('Project Database'!$C$4/MAX(1,DATEDIF('Project Database'!$D$4,EDATE('Project Database'!$E$4,ROUND('Scenario Toggle'!$E$12,0)),"m")+1)*'Scenario Toggle'!$E$8,0),E4),0) -> 10 | F5: =IF(AND(F$3>='Project Database'!$D$4,F$3<=EDATE('Project Database'!$E$4,ROUND('Scenario Toggle'!$E$12,0))),MIN(ROUND('Project Database'!$C$4/MAX(1,DATEDIF('Project Database'!$D$4,EDATE('Project Database'!$E$4,ROUND('Scenario Toggle'!$E$12,0)),"m")+1)*'Scenario Toggle'!$E$8,0),F4),0) -> 10 | G5: =IF(AND(G$3>='Project Database'!$D$4,G$3<=EDATE('Project Database'!$E$4,ROUND('Scenario Toggle'!$E$12,0))),MIN(ROUND('Project Database'!$C$4/MAX(1,DATEDIF('Project Database'!$D$4,EDATE('Project Database'!$E$4,ROUND('Scenario Toggle'!$E$12,0)),"m")+1)*'Scenario Toggle'!$E$8,0),G4),0) -> 10 | H5: =IF(AND(H$3>='Project Database'!$D$4,H$3<=EDATE('Project Database'!$E$4,ROUND('Scenario Toggle'!$E$12,0))),MIN(ROUND('Project Database'!$C$4/MAX(1,DATEDIF('Project Database'!$D$4,EDATE('Project Database'!$E$4,ROUND('Scenario Toggle'!$E$12,0)),"m")+1)*'Scenario Toggle'!$E$8,0),H4),0) -> 10 | I5: =IF(AND(I$3>='Project Database'!$D$4,I$3<=EDATE('Project Database'!$E$4,ROUND('Scenario Toggle'!$E$12,0))),MIN(ROUND('Project Database'!$C$4/MAX(1,DATEDIF('Project Database'!$D$4,EDATE('Project Database'!$E$4,ROUND('Scenario Toggle'!$E$12,0)),"m")+1)*'Scenario Toggle'!$E$8,0),I4),0) -> 10 | J5: =IF(AND(J$3>='Project Database'!$D$4,J$3<=EDATE('Project Database'!$E$4,ROUND('Scenario Toggle'!$E$12,0))),MIN(ROUND('Project Database'!$C$4/MAX(1,DATEDIF('Project Database'!$D$4,EDATE('Project Database'!$E$4,ROUND('Scenario Toggle'!$E$12,0)),"m")+1)*'Scenario Toggle'!$E$8,0),J4),0) -> 10 | ... Z5: =IF(AND(Z$3>='Project Database'!$D$4,Z$3<=EDATE('Project Database'!$E$4,ROUND('Scenario Toggle'!$E$12,0))),MIN(ROUND('Project Database'!$C$4/MAX(1,DATEDIF('Project Database'!$D$4,EDATE('Project Database'!$E$4,ROUND('Scenario Toggle'!$E$12,0)),"m")+1)*'Scenario Toggle'!$E$8,0),Z4),0) -> 0
B6: Cancellations | C6: =C5*'Scenario Toggle'!$E$10 -> 0.2 | D6: =D5*'Scenario Toggle'!$E$10 -> 0.2 | E6: =E5*'Scenario Toggle'!$E$10 -> 0.2 | F6: =F5*'Scenario Toggle'!$E$10 -> 0.2 | G6: =G5*'Scenario Toggle'!$E$10 -> 0.2 | H6: =H5*'Scenario Toggle'!$E$10 -> 0.2 | I6: =I5*'Scenario Toggle'!$E$10 -> 0.2 | J6: =J5*'Scenario Toggle'!$E$10 -> 0.2 | ... Z6: =Z5*'Scenario Toggle'!$E$10 -> 0
B7: Net Units Sold | C7: =MAX(0,C5-C6) -> 9.8 | D7: =MAX(0,D5-D6) -> 9.8 | E7: =MAX(0,E5-E6) -> 9.8 | F7: =MAX(0,F5-F6) -> 9.8 | G7: =MAX(0,G5-G6) -> 9.8 | H7: =MAX(0,H5-H6) -> 9.8 | I7: =MAX(0,I5-I6) -> 9.8 | J7: =MAX(0,J5-J6) -> 9.8 | ... Z7: =MAX(0,Z5-Z6) -> 0
B8: Avg Selling Price / Unit | C8: =IF(C$3<'Project Database'!$D$4,0,'Project Database'!$G$4*'Project Database'!$H$4*(1+'Scenario Toggle'!$E$9)^DATEDIF('Project Database'!$D$4,C$3,"m")) -> 16000000 | D8: =IF(D$3<'Project Database'!$D$4,0,'Project Database'!$G$4*'Project Database'!$H$4*(1+'Scenario Toggle'!$E$9)^DATEDIF('Project Database'!$D$4,D$3,"m")) -> 16064000 | E8: =IF(E$3<'Project Database'!$D$4,0,'Project Database'!$G$4*'Project Database'!$H$4*(1+'Scenario Toggle'!$E$9)^DATEDIF('Project Database'!$D$4,E$3,"m")) -> 16128256 | F8: =IF(F$3<'Project Database'!$D$4,0,'Project Database'!$G$4*'Project Database'!$H$4*(1+'Scenario Toggle'!$E$9)^DATEDIF('Project Database'!$D$4,F$3,"m")) -> 16192769 | G8: =IF(G$3<'Project Database'!$D$4,0,'Project Database'!$G$4*'Project Database'!$H$4*(1+'Scenario Toggle'!$E$9)^DATEDIF('Project Database'!$D$4,G$3,"m")) -> 16257540 | H8: =IF(H$3<'Project Database'!$D$4,0,'Project Database'!$G$4*'Project Database'!$H$4*(1+'Scenario Toggle'!$E$9)^DATEDIF('Project Database'!$D$4,H$3,"m")) -> 16322570 | I8: =IF(I$3<'Project Database'!$D$4,0,'Project Database'!$G$4*'Project Database'!$H$4*(1+'Scenario Toggle'!$E$9)^DATEDIF('Project Database'!$D$4,I$3,"m")) -> 16387861 | J8: =IF(J$3<'Project Database'!$D$4,0,'Project Database'!$G$4*'Project Database'!$H$4*(1+'Scenario Toggle'!$E$9)^DATEDIF('Project Database'!$D$4,J$3,"m")) -> 16453412 | ... Z8: =IF(Z$3<'Project Database'!$D$4,0,'Project Database'!$G$4*'Project Database'!$H$4*(1+'Scenario Toggle'!$E$9)^DATEDIF('Project Database'!$D$4,Z$3,"m")) -> 17538618
B9: Sales Value | C9: =C7*C8 -> 156800000 | D9: =D7*D8 -> 157427200 | E9: =E7*E8 -> 1.5805691e+08 | F9: =F7*F8 -> 1.5868914e+08 | G9: =G7*G8 -> 1.5932389e+08 | H9: =H7*H8 -> 1.5996119e+08 | I9: =I7*I8 -> 1.6060103e+08 | J9: =J7*J8 -> 1.6124344e+08 | ... Z9: =Z7*Z8 -> 0
A10: Palm Waterfront Villas | B10: Units Available BOY | C10: ='Project Database'!$C$5 -> 60 | D10: =C10-C13 -> 60 | E10: =D10-D13 -> 57.06 | F10: =E10-E13 -> 54.12 | G10: =F10-F13 -> 51.18 | H10: =G10-G13 -> 48.24 | I10: =H10-H13 -> 45.3 | J10: =I10-I13 -> 42.36 | K10: =J10-J13 -> 39.42 | ... Z10: =Y10-Y13 -> 1.2
B11: Units Sold | C11: =IF(AND(C$3>='Project Database'!$D$5,C$3<=EDATE('Project Database'!$E$5,ROUND('Scenario Toggle'!$E$12,0))),MIN(ROUND('Project Database'!$C$5/MAX(1,DATEDIF('Project Database'!$D$5,EDATE('Project Database'!$E$5,ROUND('Scenario Toggle'!$E$12,0)),"m")+1)*'Scenario Toggle'!$E$8,0),C10),0) -> 0 | D11: =IF(AND(D$3>='Project Database'!$D$5,D$3<=EDATE('Project Database'!$E$5,ROUND('Scenario Toggle'!$E$12,0))),MIN(ROUND('Project Database'!$C$5/MAX(1,DATEDIF('Project Database'!$D$5,EDATE('Project Database'!$E$5,ROUND('Scenario Toggle'!$E$12,0)),"m")+1)*'Scenario Toggle'!$E$8,0),D10),0) -> 3 | E11: =IF(AND(E$3>='Project Database'!$D$5,E$3<=EDATE('Project Database'!$E$5,ROUND('Scenario Toggle'!$E$12,0))),MIN(ROUND('Project Database'!$C$5/MAX(1,DATEDIF('Project Database'!$D$5,EDATE('Project Database'!$E$5,ROUND('Scenario Toggle'!$E$12,0)),"m")+1)*'Scenario Toggle'!$E$8,0),E10),0) -> 3 | F11: =IF(AND(F$3>='Project Database'!$D$5,F$3<=EDATE('Project Database'!$E$5,ROUND('Scenario Toggle'!$E$12,0))),MIN(ROUND('Project Database'!$C$5/MAX(1,DATEDIF('Project Database'!$D$5,EDATE('Project Database'!$E$5,ROUND('Scenario Toggle'!$E$12,0)),"m")+1)*'Scenario Toggle'!$E$8,0),F10),0) -> 3 | G11: =IF(AND(G$3>='Project Database'!$D$5,G$3<=EDATE('Project Database'!$E$5,ROUND('Scenario Toggle'!$E$12,0))),MIN(ROUND('Project Database'!$C$5/MAX(1,DATEDIF('Project Database'!$D$5,EDATE('Project Database'!$E$5,ROUND('Scenario Toggle'!$E$12,0)),"m")+1)*'Scenario Toggle'!$E$8,0),G10),0) -> 3 | H11: =IF(AND(H$3>='Project Database'!$D$5,H$3<=EDATE('Project Database'!$E$5,ROUND('Scenario Toggle'!$E$12,0))),MIN(ROUND('Project Database'!$C$5/MAX(1,DATEDIF('Project Database'!$D$5,EDATE('Project Database'!$E$5,ROUND('Scenario Toggle'!$E$12,0)),"m")+1)*'Scenario Toggle'!$E$8,0),H10),0) -> 3 | I11: =IF(AND(I$3>='Project Database'!$D$5,I$3<=EDATE('Project Database'!$E$5,ROUND('Scenario Toggle'!$E$12,0))),MIN(ROUND('Project Database'!$C$5/MAX(1,DATEDIF('Project Database'!$D$5,EDATE('Project Database'!$E$5,ROUND('Scenario Toggle'!$E$12,0)),"m")+1)*'Scenario Toggle'!$E$8,0),I10),0) -> 3 | J11: =IF(AND(J$3>='Project Database'!$D$5,J$3<=EDATE('Project Database'!$E$5,ROUND('Scenario Toggle'!$E$12,0))),MIN(ROUND('Project Database'!$C$5/MAX(1,DATEDIF('Project Database'!$D$5,EDATE('Project Database'!$E$5,ROUND('Scenario Toggle'!$E$12,0)),"m")+1)*'Scenario Toggle'!$E$8,0),J10),0) -> 3 | ... Z11: =IF(AND(Z$3>='Project Database'!$D$5,Z$3<=EDATE('Project Database'!$E$5,ROUND('Scenario Toggle'!$E$12,0))),MIN(ROUND('Project Database'!$C$5/MAX(1,DATEDIF('Project Database'!$D$5,EDATE('Project Database'!$E$5,ROUND('Scenario Toggle'!$E$12,0)),"m")+1)*'Scenario Toggle'!$E$8,0),Z10),0) -> 0
B12: Cancellations | C12: =C11*'Scenario Toggle'!$E$10 -> 0 | D12: =D11*'Scenario Toggle'!$E$10 -> 0.06 | E12: =E11*'Scenario Toggle'!$E$10 -> 0.06 | F12: =F11*'Scenario Toggle'!$E$10 -> 0.06 | G12: =G11*'Scenario Toggle'!$E$10 -> 0.06 | H12: =H11*'Scenario Toggle'!$E$10 -> 0.06 | I12: =I11*'Scenario Toggle'!$E$10 -> 0.06 | J12: =J11*'Scenario Toggle'!$E$10 -> 0.06 | ... Z12: =Z11*'Scenario Toggle'!$E$10 -> 0
B13: Net Units Sold | C13: =MAX(0,C11-C12) -> 0 | D13: =MAX(0,D11-D12) -> 2.94 | E13: =MAX(0,E11-E12) -> 2.94 | F13: =MAX(0,F11-F12) -> 2.94 | G13: =MAX(0,G11-G12) -> 2.94 | H13: =MAX(0,H11-H12) -> 2.94 | I13: =MAX(0,I11-I12) -> 2.94 | J13: =MAX(0,J11-J12) -> 2.94 | ... Z13: =MAX(0,Z11-Z12) -> 0
B14: Avg Selling Price / Unit | C14: =IF(C$3<'Project Database'!$D$5,0,'Project Database'!$G$5*'Project Database'!$H$5*(1+'Scenario Toggle'!$E$9)^DATEDIF('Project Database'!$D$5,C$3,"m")) -> 0 | D14: =IF(D$3<'Project Database'!$D$5,0,'Project Database'!$G$5*'Project Database'!$H$5*(1+'Scenario Toggle'!$E$9)^DATEDIF('Project Database'!$D$5,D$3,"m")) -> 35100000 | E14: =IF(E$3<'Project Database'!$D$5,0,'Project Database'!$G$5*'Project Database'!$H$5*(1+'Scenario Toggle'!$E$9)^DATEDIF('Project Database'!$D$5,E$3,"m")) -> 35240400 | F14: =IF(F$3<'Project Database'!$D$5,0,'Project Database'!$G$5*'Project Database'!$H$5*(1+'Scenario Toggle'!$E$9)^DATEDIF('Project Database'!$D$5,F$3,"m")) -> 35381362 | G14: =IF(G$3<'Project Database'!$D$5,0,'Project Database'!$G$5*'Project Database'!$H$5*(1+'Scenario Toggle'!$E$9)^DATEDIF('Project Database'!$D$5,G$3,"m")) -> 35522887 | H14: =IF(H$3<'Project Database'!$D$5,0,'Project Database'!$G$5*'Project Database'!$H$5*(1+'Scenario Toggle'!$E$9)^DATEDIF('Project Database'!$D$5,H$3,"m")) -> 35664979 | I14: =IF(I$3<'Project Database'!$D$5,0,'Project Database'!$G$5*'Project Database'!$H$5*(1+'Scenario Toggle'!$E$9)^DATEDIF('Project Database'!$D$5,I$3,"m")) -> 35807639 | J14: =IF(J$3<'Project Database'!$D$5,0,'Project Database'!$G$5*'Project Database'!$H$5*(1+'Scenario Toggle'!$E$9)^DATEDIF('Project Database'!$D$5,J$3,"m")) -> 35950869 | ... Z14: =IF(Z$3<'Project Database'!$D$5,0,'Project Database'!$G$5*'Project Database'!$H$5*(1+'Scenario Toggle'!$E$9)^DATEDIF('Project Database'!$D$5,Z$3,"m")) -> 38322056
B15: Sales Value | C15: =C13*C14 -> 0 | D15: =D13*D14 -> 103194000 | E15: =E13*E14 -> 103606776 | F15: =F13*F14 -> 1.040212e+08 | G15: =G13*G14 -> 1.0443729e+08 | H15: =H13*H14 -> 1.0485504e+08 | I15: =I13*I14 -> 1.0527446e+08 | J15: =J13*J14 -> 1.0569556e+08 | ... Z15: =Z13*Z14 -> 0
A16: Downtown Branded Residences | B16: Units Available BOY | C16: ='Project Database'!$C$6 -> 220 | D16: =C16-C19 -> 220 | E16: =D16-D19 -> 220 | F16: =E16-E19 -> 220 | G16: =F16-F19 -> 210.2 | H16: =G16-G19 -> 200.4 | I16: =H16-H19 -> 190.6 | J16: =I16-I19 -> 180.8 | K16: =J16-J19 -> 171 | ... Z16: =Y16-Y19 -> 24
B17: Units Sold | C17: =IF(AND(C$3>='Project Database'!$D$6,C$3<=EDATE('Project Database'!$E$6,ROUND('Scenario Toggle'!$E$12,0))),MIN(ROUND('Project Database'!$C$6/MAX(1,DATEDIF('Project Database'!$D$6,EDATE('Project Database'!$E$6,ROUND('Scenario Toggle'!$E$12,0)),"m")+1)*'Scenario Toggle'!$E$8,0),C16),0) -> 0 | D17: =IF(AND(D$3>='Project Database'!$D$6,D$3<=EDATE('Project Database'!$E$6,ROUND('Scenario Toggle'!$E$12,0))),MIN(ROUND('Project Database'!$C$6/MAX(1,DATEDIF('Project Database'!$D$6,EDATE('Project Database'!$E$6,ROUND('Scenario Toggle'!$E$12,0)),"m")+1)*'Scenario Toggle'!$E$8,0),D16),0) -> 0 | E17: =IF(AND(E$3>='Project Database'!$D$6,E$3<=EDATE('Project Database'!$E$6,ROUND('Scenario Toggle'!$E$12,0))),MIN(ROUND('Project Database'!$C$6/MAX(1,DATEDIF('Project Database'!$D$6,EDATE('Project Database'!$E$6,ROUND('Scenario Toggle'!$E$12,0)),"m")+1)*'Scenario Toggle'!$E$8,0),E16),0) -> 0 | F17: =IF(AND(F$3>='Project Database'!$D$6,F$3<=EDATE('Project Database'!$E$6,ROUND('Scenario Toggle'!$E$12,0))),MIN(ROUND('Project Database'!$C$6/MAX(1,DATEDIF('Project Database'!$D$6,EDATE('Project Database'!$E$6,ROUND('Scenario Toggle'!$E$12,0)),"m")+1)*'Scenario Toggle'!$E$8,0),F16),0) -> 10 | G17: =IF(AND(G$3>='Project Database'!$D$6,G$3<=EDATE('Project Database'!$E$6,ROUND('Scenario Toggle'!$E$12,0))),MIN(ROUND('Project Database'!$C$6/MAX(1,DATEDIF('Project Database'!$D$6,EDATE('Project Database'!$E$6,ROUND('Scenario Toggle'!$E$12,0)),"m")+1)*'Scenario Toggle'!$E$8,0),G16),0) -> 10 | H17: =IF(AND(H$3>='Project Database'!$D$6,H$3<=EDATE('Project Database'!$E$6,ROUND('Scenario Toggle'!$E$12,0))),MIN(ROUND('Project Database'!$C$6/MAX(1,DATEDIF('Project Database'!$D$6,EDATE('Project Database'!$E$6,ROUND('Scenario Toggle'!$E$12,0)),"m")+1)*'Scenario Toggle'!$E$8,0),H16),0) -> 10 | I17: =IF(AND(I$3>='Project Database'!$D$6,I$3<=EDATE('Project Database'!$E$6,ROUND('Scenario Toggle'!$E$12,0))),MIN(ROUND('Project Database'!$C$6/MAX(1,DATEDIF('Project Database'!$D$6,EDATE('Project Database'!$E$6,ROUND('Scenario Toggle'!$E$12,0)),"m")+1)*'Scenario Toggle'!$E$8,0),I16),0) -> 10 | J17: =IF(AND(J$3>='Project Database'!$D$6,J$3<=EDATE('Project Database'!$E$6,ROUND('Scenario Toggle'!$E$12,0))),MIN(ROUND('Project Database'!$C$6/MAX(1,DATEDIF('Project Database'!$D$6,EDATE('Project Database'!$E$6,ROUND('Scenario Toggle'!$E$12,0)),"m")+1)*'Scenario Toggle'!$E$8,0),J16),0) -> 10 | ... Z17: =IF(AND(Z$3>='Project Database'!$D$6,Z$3<=EDATE('Project Database'!$E$6,ROUND('Scenario Toggle'!$E$12,0))),MIN(ROUND('Project Database'!$C$6/MAX(1,DATEDIF('Project Database'!$D$6,EDATE('Project Database'!$E$6,ROUND('Scenario Toggle'!$E$12,0)),"m")+1)*'Scenario Toggle'!$E$8,0),Z16),0) -> 10
B18: Cancellations | C18: =C17*'Scenario Toggle'!$E$10 -> 0 | D18: =D17*'Scenario Toggle'!$E$10 -> 0 | E18: =E17*'Scenario Toggle'!$E$10 -> 0 | F18: =F17*'Scenario Toggle'!$E$10 -> 0.2 | G18: =G17*'Scenario Toggle'!$E$10 -> 0.2 | H18: =H17*'Scenario Toggle'!$E$10 -> 0.2 | I18: =I17*'Scenario Toggle'!$E$10 -> 0.2 | J18: =J17*'Scenario Toggle'!$E$10 -> 0.2 | ... Z18: =Z17*'Scenario Toggle'!$E$10 -> 0.2
B19: Net Units Sold | C19: =MAX(0,C17-C18) -> 0 | D19: =MAX(0,D17-D18) -> 0 | E19: =MAX(0,E17-E18) -> 0 | F19: =MAX(0,F17-F18) -> 9.8 | G19: =MAX(0,G17-G18) -> 9.8 | H19: =MAX(0,H17-H18) -> 9.8 | I19: =MAX(0,I17-I18) -> 9.8 | J19: =MAX(0,J17-J18) -> 9.8 | ... Z19: =MAX(0,Z17-Z18) -> 9.8
B20: Avg Selling Price / Unit | C20: =IF(C$3<'Project Database'!$D$6,0,'Project Database'!$G$6*'Project Database'!$H$6*(1+'Scenario Toggle'!$E$9)^DATEDIF('Project Database'!$D$6,C$3,"m")) -> 0 | D20: =IF(D$3<'Project Database'!$D$6,0,'Project Database'!$G$6*'Project Database'!$H$6*(1+'Scenario Toggle'!$E$9)^DATEDIF('Project Database'!$D$6,D$3,"m")) -> 0 | E20: =IF(E$3<'Project Database'!$D$6,0,'Project Database'!$G$6*'Project Database'!$H$6*(1+'Scenario Toggle'!$E$9)^DATEDIF('Project Database'!$D$6,E$3,"m")) -> 0 | F20: =IF(F$3<'Project Database'!$D$6,0,'Project Database'!$G$6*'Project Database'!$H$6*(1+'Scenario Toggle'!$E$9)^DATEDIF('Project Database'!$D$6,F$3,"m")) -> 12180000 | G20: =IF(G$3<'Project Database'!$D$6,0,'Project Database'!$G$6*'Project Database'!$H$6*(1+'Scenario Toggle'!$E$9)^DATEDIF('Project Database'!$D$6,G$3,"m")) -> 12228720 | H20: =IF(H$3<'Project Database'!$D$6,0,'Project Database'!$G$6*'Project Database'!$H$6*(1+'Scenario Toggle'!$E$9)^DATEDIF('Project Database'!$D$6,H$3,"m")) -> 12277635 | I20: =IF(I$3<'Project Database'!$D$6,0,'Project Database'!$G$6*'Project Database'!$H$6*(1+'Scenario Toggle'!$E$9)^DATEDIF('Project Database'!$D$6,I$3,"m")) -> 12326745 | J20: =IF(J$3<'Project Database'!$D$6,0,'Project Database'!$G$6*'Project Database'!$H$6*(1+'Scenario Toggle'!$E$9)^DATEDIF('Project Database'!$D$6,J$3,"m")) -> 12376052 | ... Z20: =IF(Z$3<'Project Database'!$D$6,0,'Project Database'!$G$6*'Project Database'!$H$6*(1+'Scenario Toggle'!$E$9)^DATEDIF('Project Database'!$D$6,Z$3,"m")) -> 13192331
B21: Sales Value | C21: =C19*C20 -> 0 | D21: =D19*D20 -> 0 | E21: =E19*E20 -> 0 | F21: =F19*F20 -> 1.19364e+08 | G21: =G19*G20 -> 1.1984146e+08 | H21: =H19*H20 -> 1.2032082e+08 | I21: =I19*I20 -> 1.2080211e+08 | J21: =J19*J20 -> 1.2128531e+08 | ... Z21: =Z19*Z20 -> 1.2928485e+08
A22: Jumeirah Mixed-Use Development | B22: Units Available BOY | C22: ='Project Database'!$C$7 -> 140 | D22: =C22-C25 -> 140 | E22: =D22-D25 -> 140 | F22: =E22-E25 -> 133.14 | G22: =F22-F25 -> 126.28 | H22: =G22-G25 -> 119.42 | I22: =H22-H25 -> 112.56 | J22: =I22-I25 -> 105.7 | K22: =J22-J25 -> 98.84 | ... Z22: =Y22-Y25 -> 0.056
B23: Units Sold | C23: =IF(AND(C$3>='Project Database'!$D$7,C$3<=EDATE('Project Database'!$E$7,ROUND('Scenario Toggle'!$E$12,0))),MIN(ROUND('Project Database'!$C$7/MAX(1,DATEDIF('Project Database'!$D$7,EDATE('Project Database'!$E$7,ROUND('Scenario Toggle'!$E$12,0)),"m")+1)*'Scenario Toggle'!$E$8,0),C22),0) -> 0 | D23: =IF(AND(D$3>='Project Database'!$D$7,D$3<=EDATE('Project Database'!$E$7,ROUND('Scenario Toggle'!$E$12,0))),MIN(ROUND('Project Database'!$C$7/MAX(1,DATEDIF('Project Database'!$D$7,EDATE('Project Database'!$E$7,ROUND('Scenario Toggle'!$E$12,0)),"m")+1)*'Scenario Toggle'!$E$8,0),D22),0) -> 0 | E23: =IF(AND(E$3>='Project Database'!$D$7,E$3<=EDATE('Project Database'!$E$7,ROUND('Scenario Toggle'!$E$12,0))),MIN(ROUND('Project Database'!$C$7/MAX(1,DATEDIF('Project Database'!$D$7,EDATE('Project Database'!$E$7,ROUND('Scenario Toggle'!$E$12,0)),"m")+1)*'Scenario Toggle'!$E$8,0),E22),0) -> 7 | F23: =IF(AND(F$3>='Project Database'!$D$7,F$3<=EDATE('Project Database'!$E$7,ROUND('Scenario Toggle'!$E$12,0))),MIN(ROUND('Project Database'!$C$7/MAX(1,DATEDIF('Project Database'!$D$7,EDATE('Project Database'!$E$7,ROUND('Scenario Toggle'!$E$12,0)),"m")+1)*'Scenario Toggle'!$E$8,0),F22),0) -> 7 | G23: =IF(AND(G$3>='Project Database'!$D$7,G$3<=EDATE('Project Database'!$E$7,ROUND('Scenario Toggle'!$E$12,0))),MIN(ROUND('Project Database'!$C$7/MAX(1,DATEDIF('Project Database'!$D$7,EDATE('Project Database'!$E$7,ROUND('Scenario Toggle'!$E$12,0)),"m")+1)*'Scenario Toggle'!$E$8,0),G22),0) -> 7 | H23: =IF(AND(H$3>='Project Database'!$D$7,H$3<=EDATE('Project Database'!$E$7,ROUND('Scenario Toggle'!$E$12,0))),MIN(ROUND('Project Database'!$C$7/MAX(1,DATEDIF('Project Database'!$D$7,EDATE('Project Database'!$E$7,ROUND('Scenario Toggle'!$E$12,0)),"m")+1)*'Scenario Toggle'!$E$8,0),H22),0) -> 7 | I23: =IF(AND(I$3>='Project Database'!$D$7,I$3<=EDATE('Project Database'!$E$7,ROUND('Scenario Toggle'!$E$12,0))),MIN(ROUND('Project Database'!$C$7/MAX(1,DATEDIF('Project Database'!$D$7,EDATE('Project Database'!$E$7,ROUND('Scenario Toggle'!$E$12,0)),"m")+1)*'Scenario Toggle'!$E$8,0),I22),0) -> 7 | J23: =IF(AND(J$3>='Project Database'!$D$7,J$3<=EDATE('Project Database'!$E$7,ROUND('Scenario Toggle'!$E$12,0))),MIN(ROUND('Project Database'!$C$7/MAX(1,DATEDIF('Project Database'!$D$7,EDATE('Project Database'!$E$7,ROUND('Scenario Toggle'!$E$12,0)),"m")+1)*'Scenario Toggle'!$E$8,0),J22),0) -> 7 | ... Z23: =IF(AND(Z$3>='Project Database'!$D$7,Z$3<=EDATE('Project Database'!$E$7,ROUND('Scenario Toggle'!$E$12,0))),MIN(ROUND('Project Database'!$C$7/MAX(1,DATEDIF('Project Database'!$D$7,EDATE('Project Database'!$E$7,ROUND('Scenario Toggle'!$E$12,0)),"m")+1)*'Scenario Toggle'!$E$8,0),Z22),0) -> 0
B24: Cancellations | C24: =C23*'Scenario Toggle'!$E$10 -> 0 | D24: =D23*'Scenario Toggle'!$E$10 -> 0 | E24: =E23*'Scenario Toggle'!$E$10 -> 0.14 | F24: =F23*'Scenario Toggle'!$E$10 -> 0.14 | G24: =G23*'Scenario Toggle'!$E$10 -> 0.14 | H24: =H23*'Scenario Toggle'!$E$10 -> 0.14 | I24: =I23*'Scenario Toggle'!$E$10 -> 0.14 | J24: =J23*'Scenario Toggle'!$E$10 -> 0.14 | ... Z24: =Z23*'Scenario Toggle'!$E$10 -> 0
B25: Net Units Sold | C25: =MAX(0,C23-C24) -> 0 | D25: =MAX(0,D23-D24) -> 0 | E25: =MAX(0,E23-E24) -> 6.86 | F25: =MAX(0,F23-F24) -> 6.86 | G25: =MAX(0,G23-G24) -> 6.86 | H25: =MAX(0,H23-H24) -> 6.86 | I25: =MAX(0,I23-I24) -> 6.86 | J25: =MAX(0,J23-J24) -> 6.86 | ... Z25: =MAX(0,Z23-Z24) -> 0
B26: Avg Selling Price / Unit | C26: =IF(C$3<'Project Database'!$D$7,0,'Project Database'!$G$7*'Project Database'!$H$7*(1+'Scenario Toggle'!$E$9)^DATEDIF('Project Database'!$D$7,C$3,"m")) -> 0 | D26: =IF(D$3<'Project Database'!$D$7,0,'Project Database'!$G$7*'Project Database'!$H$7*(1+'Scenario Toggle'!$E$9)^DATEDIF('Project Database'!$D$7,D$3,"m")) -> 0 | E26: =IF(E$3<'Project Database'!$D$7,0,'Project Database'!$G$7*'Project Database'!$H$7*(1+'Scenario Toggle'!$E$9)^DATEDIF('Project Database'!$D$7,E$3,"m")) -> 10140000 | F26: =IF(F$3<'Project Database'!$D$7,0,'Project Database'!$G$7*'Project Database'!$H$7*(1+'Scenario Toggle'!$E$9)^DATEDIF('Project Database'!$D$7,F$3,"m")) -> 10180560 | G26: =IF(G$3<'Project Database'!$D$7,0,'Project Database'!$G$7*'Project Database'!$H$7*(1+'Scenario Toggle'!$E$9)^DATEDIF('Project Database'!$D$7,G$3,"m")) -> 10221282 | H26: =IF(H$3<'Project Database'!$D$7,0,'Project Database'!$G$7*'Project Database'!$H$7*(1+'Scenario Toggle'!$E$9)^DATEDIF('Project Database'!$D$7,H$3,"m")) -> 10262167 | I26: =IF(I$3<'Project Database'!$D$7,0,'Project Database'!$G$7*'Project Database'!$H$7*(1+'Scenario Toggle'!$E$9)^DATEDIF('Project Database'!$D$7,I$3,"m")) -> 10303216 | J26: =IF(J$3<'Project Database'!$D$7,0,'Project Database'!$G$7*'Project Database'!$H$7*(1+'Scenario Toggle'!$E$9)^DATEDIF('Project Database'!$D$7,J$3,"m")) -> 10344429 | ... Z26: =IF(Z$3<'Project Database'!$D$7,0,'Project Database'!$G$7*'Project Database'!$H$7*(1+'Scenario Toggle'!$E$9)^DATEDIF('Project Database'!$D$7,Z$3,"m")) -> 11026709
B27: Sales Value | C27: =C25*C26 -> 0 | D27: =D25*D26 -> 0 | E27: =E25*E26 -> 69560400 | F27: =F25*F26 -> 69838642 | G27: =G25*G26 -> 70117996 | H27: =H25*H26 -> 70398468 | I27: =I25*I26 -> 70680062 | J27: =J25*J26 -> 70962782 | ... Z27: =Z25*Z26 -> 0
A29: Portfolio | B29: Total Net Units Sold | C29: =C7+C13+C19+C25 -> 9.8 | D29: =D7+D13+D19+D25 -> 12.74 | E29: =E7+E13+E19+E25 -> 19.6 | F29: =F7+F13+F19+F25 -> 29.4 | G29: =G7+G13+G19+G25 -> 29.4 | H29: =H7+H13+H19+H25 -> 29.4 | I29: =I7+I13+I19+I25 -> 29.4 | J29: =J7+J13+J19+J25 -> 29.4 | ... Z29: =Z7+Z13+Z19+Z25 -> 9.8
B30: Total Sales Value | C30: =C9+C15+C21+C27 -> 156800000 | D30: =D9+D15+D21+D27 -> 260621200 | E30: =E9+E15+E21+E27 -> 3.3122408e+08 | F30: =F9+F15+F21+F27 -> 4.5191298e+08 | G30: =G9+G15+G21+G27 -> 4.5372063e+08 | H30: =H9+H15+H21+H27 -> 4.5553552e+08 | I30: =I9+I15+I21+I27 -> 4.5735766e+08 | J30: =J9+J15+J21+J27 -> 4.5918709e+08 | ... Z30: =Z9+Z15+Z21+Z27 -> 1.2928485e+08

Sheet Collections
A1: Customer Collection Schedule
A3: Project | B3: Metric | C3: 46113 | D3: 46143 | E3: 46174 | F3: 46204 | G3: 46235 | H3: 46266 | I3: 46296 | J3: 46327 | K3: 46357 | L3: 46388 | M3: 46419 | N3: 46447 | O3: 46478 | P3: 46508 | Q3: 46539 | R3: 46569 | S3: 46600 | T3: 46631 | U3: 46661 | V3: 46692 | W3: 46722 | X3: 46753 | Y3: 46784 | Z3: 46813
A4: Marina Residences Tower | B4: Booking 20% | C4: ='Sales Forecast'!C9*Assumptions!$E$14 -> 31360000 | D4: ='Sales Forecast'!D9*Assumptions!$E$14 -> 31485440 | E4: ='Sales Forecast'!E9*Assumptions!$E$14 -> 31611382 | F4: ='Sales Forecast'!F9*Assumptions!$E$14 -> 31737827 | G4: ='Sales Forecast'!G9*Assumptions!$E$14 -> 31864779 | H4: ='Sales Forecast'!H9*Assumptions!$E$14 -> 31992238 | I4: ='Sales Forecast'!I9*Assumptions!$E$14 -> 32120207 | J4: ='Sales Forecast'!J9*Assumptions!$E$14 -> 32248687 | ... Z4: ='Sales Forecast'!Z9*Assumptions!$E$14 -> 0
B5: Milestone 1 20% | C5: 0 | D5: 0 | E5: 0 | F5: 0 | G5: 0 | H5: 0 | I5: ='Sales Forecast'!C9*Assumptions!$E$15 -> 31360000 | J5: ='Sales Forecast'!D9*Assumptions!$E$15 -> 31485440 | K5: ='Sales Forecast'!E9*Assumptions!$E$15 -> 31611382 | L5: ='Sales Forecast'!F9*Assumptions!$E$15 -> 31737827 | M5: ='Sales Forecast'!G9*Assumptions!$E$15 -> 31864779 | N5: ='Sales Forecast'!H9*Assumptions!$E$15 -> 31992238 | O5: ='Sales Forecast'!I9*Assumptions!$E$15 -> 32120207 | P5: ='Sales Forecast'!J9*Assumptions!$E$15 -> 32248687 | ... Z5: ='Sales Forecast'!T9*Assumptions!$E$15 -> 33562103
B6: Milestone 2 20% | C6: 0 | D6: 0 | E6: 0 | F6: 0 | G6: 0 | H6: 0 | I6: 0 | J6: 0 | K6: 0 | L6: 0 | M6: 0 | N6: 0 | O6: ='Sales Forecast'!C9*Assumptions!$E$16 -> 31360000 | P6: ='Sales Forecast'!D9*Assumptions!$E$16 -> 31485440 | Q6: ='Sales Forecast'!E9*Assumptions!$E$16 -> 31611382 | R6: ='Sales Forecast'!F9*Assumptions!$E$16 -> 31737827 | S6: ='Sales Forecast'!G9*Assumptions!$E$16 -> 31864779 | T6: ='Sales Forecast'!H9*Assumptions!$E$16 -> 31992238 | U6: ='Sales Forecast'!I9*Assumptions!$E$16 -> 32120207 | V6: ='Sales Forecast'!J9*Assumptions!$E$16 -> 32248687 | ... Z6: ='Sales Forecast'!N9*Assumptions!$E$16 -> 32767771
B7: Milestone 3 20% | C7: 0 | D7: 0 | E7: 0 | F7: 0 | G7: 0 | H7: 0 | I7: 0 | J7: 0 | K7: 0 | L7: 0 | M7: 0 | N7: 0 | O7: 0 | P7: 0 | Q7: 0 | R7: 0 | S7: 0 | T7: 0 | U7: ='Sales Forecast'!C9*Assumptions!$E$17 -> 31360000 | V7: ='Sales Forecast'!D9*Assumptions!$E$17 -> 31485440 | W7: ='Sales Forecast'!E9*Assumptions!$E$17 -> 31611382 | X7: ='Sales Forecast'!F9*Assumptions!$E$17 -> 31737827 | Y7: ='Sales Forecast'!G9*Assumptions!$E$17 -> 31864779 | Z7: ='Sales Forecast'!H9*Assumptions!$E$17 -> 31992238
B8: Handover 20% | C8: =IF(C$3>=EDATE('Project Database'!$E$4,ROUND('Scenario Toggle'!$E$12,0)),MAX(0,SUM('Sales Forecast'!$C$9:C9)*Assumptions!$E$18-0),0) -> 0 | D8: =IF(D$3>=EDATE('Project Database'!$E$4,ROUND('Scenario Toggle'!$E$12,0)),MAX(0,SUM('Sales Forecast'!$C$9:D9)*Assumptions!$E$18-SUM(C8)),0) -> 0 | E8: =IF(E$3>=EDATE('Project Database'!$E$4,ROUND('Scenario Toggle'!$E$12,0)),MAX(0,SUM('Sales Forecast'!$C$9:E9)*Assumptions!$E$18-SUM(C8:D8)),0) -> 0 | F8: =IF(F$3>=EDATE('Project Database'!$E$4,ROUND('Scenario Toggle'!$E$12,0)),MAX(0,SUM('Sales Forecast'!$C$9:F9)*Assumptions!$E$18-SUM(C8:E8)),0) -> 0 | G8: =IF(G$3>=EDATE('Project Database'!$E$4,ROUND('Scenario Toggle'!$E$12,0)),MAX(0,SUM('Sales Forecast'!$C$9:G9)*Assumptions!$E$18-SUM(C8:F8)),0) -> 0 | H8: =IF(H$3>=EDATE('Project Database'!$E$4,ROUND('Scenario Toggle'!$E$12,0)),MAX(0,SUM('Sales Forecast'!$C$9:H9)*Assumptions!$E$18-SUM(C8:G8)),0) -> 0 | I8: =IF(I$3>=EDATE('Project Database'!$E$4,ROUND('Scenario Toggle'!$E$12,0)),MAX(0,SUM('Sales Forecast'!$C$9:I9)*Assumptions!$E$18-SUM(C8:H8)),0) -> 0 | J8: =IF(J$3>=EDATE('Project Database'!$E$4,ROUND('Scenario Toggle'!$E$12,0)),MAX(0,SUM('Sales Forecast'!$C$9:J9)*Assumptions!$E$18-SUM(C8:I8)),0) -> 0 | K8: =IF(K$3>=EDATE('Project Database'!$E$4,ROUND('Scenario Toggle'!$E$12,0)),MAX(0,SUM('Sales Forecast'!$C$9:K9)*Assumptions!$E$18-SUM(C8:J8)),0) -> 0 | L8: =IF(L$3>=EDATE('Project Database'!$E$4,ROUND('Scenario Toggle'!$E$12,0)),MAX(0,SUM('Sales Forecast'!$C$9:L9)*Assumptions!$E$18-SUM(C8:K8)),0) -> 0 | M8: =IF(M$3>=EDATE('Project Database'!$E$4,ROUND('Scenario Toggle'!$E$12,0)),MAX(0,SUM('Sales Forecast'!$C$9:M9)*Assumptions!$E$18-SUM(C8:L8)),0) -> 0 | N8: =IF(N$3>=EDATE('Project Database'!$E$4,ROUND('Scenario Toggle'!$E$12,0)),MAX(0,SUM('Sales Forecast'!$C$9:N9)*Assumptions!$E$18-SUM(C8:M8)),0) -> 0 | O8: =IF(O$3>=EDATE('Project Database'!$E$4,ROUND('Scenario Toggle'!$E$12,0)),MAX(0,SUM('Sales Forecast'!$C$9:O9)*Assumptions!$E$18-SUM(C8:N8)),0) -> 0 | P8: =IF(P$3>=EDATE('Project Database'!$E$4,ROUND('Scenario Toggle'!$E$12,0)),MAX(0,SUM('Sales Forecast'!$C$9:P9)*Assumptions!$E$18-SUM(C8:O8)),0) -> 0 | Q8: =IF(Q$3>=EDATE('Project Database'!$E$4,ROUND('Scenario Toggle'!$E$12,0)),MAX(0,SUM('Sales Forecast'!$C$9:Q9)*Assumptions!$E$18-SUM(C8:P8)),0) -> 0 | R8: =IF(R$3>=EDATE('Project Database'!$E$4,ROUND('Scenario Toggle'!$E$12,0)),MAX(0,SUM('Sales Forecast'!$C$9:R9)*Assumptions!$E$18-SUM(C8:Q8)),0) -> 0 | S8: =IF(S$3>=EDATE('Project Database'!$E$4,ROUND('Scenario Toggle'!$E$12,0)),MAX(0,SUM('Sales Forecast'!$C$9:S9)*Assumptions!$E$18-SUM(C8:R8)),0) -> 0 | T8: =IF(T$3>=EDATE('Project Database'!$E$4,ROUND('Scenario Toggle'!$E$12,0)),MAX(0,SUM('Sales Forecast'!$C$9:T9)*Assumptions!$E$18-SUM(C8:S8)),0) -> 5.8408797e+08 | U8: =IF(U$3>=EDATE('Project Database'!$E$4,ROUND('Scenario Toggle'!$E$12,0)),MAX(0,SUM('Sales Forecast'!$C$9:U9)*Assumptions!$E$18-SUM(C8:T8)),0) -> 0 | V8: =IF(V$3>=EDATE('Project Database'!$E$4,ROUND('Scenario Toggle'!$E$12,0)),MAX(0,SUM('Sales Forecast'!$C$9:V9)*Assumptions!$E$18-SUM(C8:U8)),0) -> 0 | W8: =IF(W$3>=EDATE('Project Database'!$E$4,ROUND('Scenario Toggle'!$E$12,0)),MAX(0,SUM('Sales Forecast'!$C$9:W9)*Assumptions!$E$18-SUM(C8:V8)),0) -> 0 | X8: =IF(X$3>=EDATE('Project Database'!$E$4,ROUND('Scenario Toggle'!$E$12,0)),MAX(0,SUM('Sales Forecast'!$C$9:X9)*Assumptions!$E$18-SUM(C8:W8)),0) -> 0 | Y8: =IF(Y$3>=EDATE('Project Database'!$E$4,ROUND('Scenario Toggle'!$E$12,0)),MAX(0,SUM('Sales Forecast'!$C$9:Y9)*Assumptions!$E$18-SUM(C8:X8)),0) -> 0 | Z8: =IF(Z$3>=EDATE('Project Database'!$E$4,ROUND('Scenario Toggle'!$E$12,0)),MAX(0,SUM('Sales Forecast'!$C$9:Z9)*Assumptions!$E$18-SUM(C8:Y8)),0) -> 0
B9: Total Customer Collections | C9: =SUM(C4:C8) -> 31360000 | D9: =SUM(D4:D8) -> 31485440 | E9: =SUM(E4:E8) -> 31611382 | F9: =SUM(F4:F8) -> 31737827 | G9: =SUM(G4:G8) -> 31864779 | H9: =SUM(H4:H8) -> 31992238 | I9: =SUM(I4:I8) -> 63480207 | J9: =SUM(J4:J8) -> 63734127 | ... Z9: =SUM(Z4:Z8) -> 98322112
B10: Sales Commissions | C10: ='Sales Forecast'!C9*Assumptions!$E$19 -> 4704000 | D10: ='Sales Forecast'!D9*Assumptions!$E$19 -> 4722816 | E10: ='Sales Forecast'!E9*Assumptions!$E$19 -> 4741707.3 | F10: ='Sales Forecast'!F9*Assumptions!$E$19 -> 4760674.1 | G10: ='Sales Forecast'!G9*Assumptions!$E$19 -> 4779716.8 | H10: ='Sales Forecast'!H9*Assumptions!$E$19 -> 4798835.7 | I10: ='Sales Forecast'!I9*Assumptions!$E$19 -> 4818031 | J10: ='Sales Forecast'!J9*Assumptions!$E$19 -> 4837303.1 | ... Z10: ='Sales Forecast'!Z9*Assumptions!$E$19 -> 0
A11: Palm Waterfront Villas | B11: Booking 20% | C11: ='Sales Forecast'!C15*Assumptions!$E$14 -> 0 | D11: ='Sales Forecast'!D15*Assumptions!$E$14 -> 20638800 | E11: ='Sales Forecast'!E15*Assumptions!$E$14 -> 20721355 | F11: ='Sales Forecast'!F15*Assumptions!$E$14 -> 20804241 | G11: ='Sales Forecast'!G15*Assumptions!$E$14 -> 20887458 | H11: ='Sales Forecast'!H15*Assumptions!$E$14 -> 20971007 | I11: ='Sales Forecast'!I15*Assumptions!$E$14 -> 21054891 | J11: ='Sales Forecast'!J15*Assumptions!$E$14 -> 21139111 | ... Z11: ='Sales Forecast'!Z15*Assumptions!$E$14 -> 0
B12: Milestone 1 20% | C12: 0 | D12: 0 | E12: 0 | F12: 0 | G12: 0 | H12: 0 | I12: ='Sales Forecast'!C15*Assumptions!$E$15 -> 0 | J12: ='Sales Forecast'!D15*Assumptions!$E$15 -> 20638800 | K12: ='Sales Forecast'!E15*Assumptions!$E$15 -> 20721355 | L12: ='Sales Forecast'!F15*Assumptions!$E$15 -> 20804241 | M12: ='Sales Forecast'!G15*Assumptions!$E$15 -> 20887458 | N12: ='Sales Forecast'!H15*Assumptions!$E$15 -> 20971007 | O12: ='Sales Forecast'!I15*Assumptions!$E$15 -> 21054891 | P12: ='Sales Forecast'!J15*Assumptions!$E$15 -> 21139111 | ... Z12: ='Sales Forecast'!T15*Assumptions!$E$15 -> 22000059
B13: Milestone 2 20% | C13: 0 | D13: 0 | E13: 0 | F13: 0 | G13: 0 | H13: 0 | I13: 0 | J13: 0 | K13: 0 | L13: 0 | M13: 0 | N13: 0 | O13: ='Sales Forecast'!C15*Assumptions!$E$16 -> 0 | P13: ='Sales Forecast'!D15*Assumptions!$E$16 -> 20638800 | Q13: ='Sales Forecast'!E15*Assumptions!$E$16 -> 20721355 | R13: ='Sales Forecast'!F15*Assumptions!$E$16 -> 20804241 | S13: ='Sales Forecast'!G15*Assumptions!$E$16 -> 20887458 | T13: ='Sales Forecast'!H15*Assumptions!$E$16 -> 20971007 | U13: ='Sales Forecast'!I15*Assumptions!$E$16 -> 21054891 | V13: ='Sales Forecast'!J15*Assumptions!$E$16 -> 21139111 | ... Z13: ='Sales Forecast'!N15*Assumptions!$E$16 -> 21479372
B14: Milestone 3 20% | C14: 0 | D14: 0 | E14: 0 | F14: 0 | G14: 0 | H14: 0 | I14: 0 | J14: 0 | K14: 0 | L14: 0 | M14: 0 | N14: 0 | O14: 0 | P14: 0 | Q14: 0 | R14: 0 | S14: 0 | T14: 0 | U14: ='Sales Forecast'!C15*Assumptions!$E$17 -> 0 | V14: ='Sales Forecast'!D15*Assumptions!$E$17 -> 20638800 | W14: ='Sales Forecast'!E15*Assumptions!$E$17 -> 20721355 | X14: ='Sales Forecast'!F15*Assumptions!$E$17 -> 20804241 | Y14: ='Sales Forecast'!G15*Assumptions!$E$17 -> 20887458 | Z14: ='Sales Forecast'!H15*Assumptions!$E$17 -> 20971007
B15: Handover 20% | C15: =IF(C$3>=EDATE('Project Database'!$E$5,ROUND('Scenario Toggle'!$E$12,0)),MAX(0,SUM('Sales Forecast'!$C$15:C15)*Assumptions!$E$18-0),0) -> 0 | D15: =IF(D$3>=EDATE('Project Database'!$E$5,ROUND('Scenario Toggle'!$E$12,0)),MAX(0,SUM('Sales Forecast'!$C$15:D15)*Assumptions!$E$18-SUM(C15)),0) -> 0 | E15: =IF(E$3>=EDATE('Project Database'!$E$5,ROUND('Scenario Toggle'!$E$12,0)),MAX(0,SUM('Sales Forecast'!$C$15:E15)*Assumptions!$E$18-SUM(C15:D15)),0) -> 0 | F15: =IF(F$3>=EDATE('Project Database'!$E$5,ROUND('Scenario Toggle'!$E$12,0)),MAX(0,SUM('Sales Forecast'!$C$15:F15)*Assumptions!$E$18-SUM(C15:E15)),0) -> 0 | G15: =IF(G$3>=EDATE('Project Database'!$E$5,ROUND('Scenario Toggle'!$E$12,0)),MAX(0,SUM('Sales Forecast'!$C$15:G15)*Assumptions!$E$18-SUM(C15:F15)),0) -> 0 | H15: =IF(H$3>=EDATE('Project Database'!$E$5,ROUND('Scenario Toggle'!$E$12,0)),MAX(0,SUM('Sales Forecast'!$C$15:H15)*Assumptions!$E$18-SUM(C15:G15)),0) -> 0 | I15: =IF(I$3>=EDATE('Project Database'!$E$5,ROUND('Scenario Toggle'!$E$12,0)),MAX(0,SUM('Sales Forecast'!$C$15:I15)*Assumptions!$E$18-SUM(C15:H15)),0) -> 0 | J15: =IF(J$3>=EDATE('Project Database'!$E$5,ROUND('Scenario Toggle'!$E$12,0)),MAX(0,SUM('Sales Forecast'!$C$15:J15)*Assumptions!$E$18-SUM(C15:I15)),0) -> 0 | K15: =IF(K$3>=EDATE('Project Database'!$E$5,ROUND('Scenario Toggle'!$E$12,0)),MAX(0,SUM('Sales Forecast'!$C$15:K15)*Assumptions!$E$18-SUM(C15:J15)),0) -> 0 | L15: =IF(L$3>=EDATE('Project Database'!$E$5,ROUND('Scenario Toggle'!$E$12,0)),MAX(0,SUM('Sales Forecast'!$C$15:L15)*Assumptions!$E$18-SUM(C15:K15)),0) -> 0 | M15: =IF(M$3>=EDATE('Project Database'!$E$5,ROUND('Scenario Toggle'!$E$12,0)),MAX(0,SUM('Sales Forecast'!$C$15:M15)*Assumptions!$E$18-SUM(C15:L15)),0) -> 0 | N15: =IF(N$3>=EDATE('Project Database'!$E$5,ROUND('Scenario Toggle'!$E$12,0)),MAX(0,SUM('Sales Forecast'!$C$15:N15)*Assumptions!$E$18-SUM(C15:M15)),0) -> 0 | O15: =IF(O$3>=EDATE('Project Database'!$E$5,ROUND('Scenario Toggle'!$E$12,0)),MAX(0,SUM('Sales Forecast'!$C$15:O15)*Assumptions!$E$18-SUM(C15:N15)),0) -> 0 | P15: =IF(P$3>=EDATE('Project Database'!$E$5,ROUND('Scenario Toggle'!$E$12,0)),MAX(0,SUM('Sales Forecast'!$C$15:P15)*Assumptions!$E$18-SUM(C15:O15)),0) -> 0 | Q15: =IF(Q$3>=EDATE('Project Database'!$E$5,ROUND('Scenario Toggle'!$E$12,0)),MAX(0,SUM('Sales Forecast'!$C$15:Q15)*Assumptions!$E$18-SUM(C15:P15)),0) -> 0 | R15: =IF(R$3>=EDATE('Project Database'!$E$5,ROUND('Scenario Toggle'!$E$12,0)),MAX(0,SUM('Sales Forecast'!$C$15:R15)*Assumptions!$E$18-SUM(C15:Q15)),0) -> 0 | S15: =IF(S$3>=EDATE('Project Database'!$E$5,ROUND('Scenario Toggle'!$E$12,0)),MAX(0,SUM('Sales Forecast'!$C$15:S15)*Assumptions!$E$18-SUM(C15:R15)),0) -> 0 | T15: =IF(T$3>=EDATE('Project Database'!$E$5,ROUND('Scenario Toggle'!$E$12,0)),MAX(0,SUM('Sales Forecast'!$C$15:T15)*Assumptions!$E$18-SUM(C15:S15)),0) -> 0 | U15: =IF(U$3>=EDATE('Project Database'!$E$5,ROUND('Scenario Toggle'!$E$12,0)),MAX(0,SUM('Sales Forecast'!$C$15:U15)*Assumptions!$E$18-SUM(C15:T15)),0) -> 0 | V15: =IF(V$3>=EDATE('Project Database'!$E$5,ROUND('Scenario Toggle'!$E$12,0)),MAX(0,SUM('Sales Forecast'!$C$15:V15)*Assumptions!$E$18-SUM(C15:U15)),0) -> 0 | W15: =IF(W$3>=EDATE('Project Database'!$E$5,ROUND('Scenario Toggle'!$E$12,0)),MAX(0,SUM('Sales Forecast'!$C$15:W15)*Assumptions!$E$18-SUM(C15:V15)),0) -> 4.2884442e+08 | X15: =IF(X$3>=EDATE('Project Database'!$E$5,ROUND('Scenario Toggle'!$E$12,0)),MAX(0,SUM('Sales Forecast'!$C$15:X15)*Assumptions!$E$18-SUM(C15:W15)),0) -> 0 | Y15: =IF(Y$3>=EDATE('Project Database'!$E$5,ROUND('Scenario Toggle'!$E$12,0)),MAX(0,SUM('Sales Forecast'!$C$15:Y15)*Assumptions!$E$18-SUM(C15:X15)),0) -> 0 | Z15: =IF(Z$3>=EDATE('Project Database'!$E$5,ROUND('Scenario Toggle'!$E$12,0)),MAX(0,SUM('Sales Forecast'!$C$15:Z15)*Assumptions!$E$18-SUM(C15:Y15)),0) -> 0
B16: Total Customer Collections | C16: =SUM(C11:C15) -> 0 | D16: =SUM(D11:D15) -> 20638800 | E16: =SUM(E11:E15) -> 20721355 | F16: =SUM(F11:F15) -> 20804241 | G16: =SUM(G11:G15) -> 20887458 | H16: =SUM(H11:H15) -> 20971007 | I16: =SUM(I11:I15) -> 21054891 | J16: =SUM(J11:J15) -> 41777911 | ... Z16: =SUM(Z11:Z15) -> 64450438
B17: Sales Commissions | C17: ='Sales Forecast'!C15*Assumptions!$E$19 -> 0 | D17: ='Sales Forecast'!D15*Assumptions!$E$19 -> 3095820 | E17: ='Sales Forecast'!E15*Assumptions!$E$19 -> 3108203.3 | F17: ='Sales Forecast'!F15*Assumptions!$E$19 -> 3120636.1 | G17: ='Sales Forecast'!G15*Assumptions!$E$19 -> 3133118.6 | H17: ='Sales Forecast'!H15*Assumptions!$E$19 -> 3145651.1 | I17: ='Sales Forecast'!I15*Assumptions!$E$19 -> 3158233.7 | J17: ='Sales Forecast'!J15*Assumptions!$E$19 -> 3170866.7 | ... Z17: ='Sales Forecast'!Z15*Assumptions!$E$19 -> 0
A18: Downtown Branded Residences | B18: Booking 20% | C18: ='Sales Forecast'!C21*Assumptions!$E$14 -> 0 | D18: ='Sales Forecast'!D21*Assumptions!$E$14 -> 0 | E18: ='Sales Forecast'!E21*Assumptions!$E$14 -> 0 | F18: ='Sales Forecast'!F21*Assumptions!$E$14 -> 23872800 | G18: ='Sales Forecast'!G21*Assumptions!$E$14 -> 23968291 | H18: ='Sales Forecast'!H21*Assumptions!$E$14 -> 24064164 | I18: ='Sales Forecast'!I21*Assumptions!$E$14 -> 24160421 | J18: ='Sales Forecast'!J21*Assumptions!$E$14 -> 24257063 | ... Z18: ='Sales Forecast'!Z21*Assumptions!$E$14 -> 25856969
B19: Milestone 1 20% | C19: 0 | D19: 0 | E19: 0 | F19: 0 | G19: 0 | H19: 0 | I19: ='Sales Forecast'!C21*Assumptions!$E$15 -> 0 | J19: ='Sales Forecast'!D21*Assumptions!$E$15 -> 0 | K19: ='Sales Forecast'!E21*Assumptions!$E$15 -> 0 | L19: ='Sales Forecast'!F21*Assumptions!$E$15 -> 23872800 | M19: ='Sales Forecast'!G21*Assumptions!$E$15 -> 23968291 | N19: ='Sales Forecast'!H21*Assumptions!$E$15 -> 24064164 | O19: ='Sales Forecast'!I21*Assumptions!$E$15 -> 24160421 | P19: ='Sales Forecast'!J21*Assumptions!$E$15 -> 24257063 | ... Z19: ='Sales Forecast'!T21*Assumptions!$E$15 -> 25244998
B20: Milestone 2 20% | C20: 0 | D20: 0 | E20: 0 | F20: 0 | G20: 0 | H20: 0 | I20: 0 | J20: 0 | K20: 0 | L20: 0 | M20: 0 | N20: 0 | O20: ='Sales Forecast'!C21*Assumptions!$E$16 -> 0 | P20: ='Sales Forecast'!D21*Assumptions!$E$16 -> 0 | Q20: ='Sales Forecast'!E21*Assumptions!$E$16 -> 0 | R20: ='Sales Forecast'!F21*Assumptions!$E$16 -> 23872800 | S20: ='Sales Forecast'!G21*Assumptions!$E$16 -> 23968291 | T20: ='Sales Forecast'!H21*Assumptions!$E$16 -> 24064164 | U20: ='Sales Forecast'!I21*Assumptions!$E$16 -> 24160421 | V20: ='Sales Forecast'!J21*Assumptions!$E$16 -> 24257063 | ... Z20: ='Sales Forecast'!N21*Assumptions!$E$16 -> 24647511
B21: Milestone 3 20% | C21: 0 | D21: 0 | E21: 0 | F21: 0 | G21: 0 | H21: 0 | I21: 0 | J21: 0 | K21: 0 | L21: 0 | M21: 0 | N21: 0 | O21: 0 | P21: 0 | Q21: 0 | R21: 0 | S21: 0 | T21: 0 | U21: ='Sales Forecast'!C21*Assumptions!$E$17 -> 0 | V21: ='Sales Forecast'!D21*Assumptions!$E$17 -> 0 | W21: ='Sales Forecast'!E21*Assumptions!$E$17 -> 0 | X21: ='Sales Forecast'!F21*Assumptions!$E$17 -> 23872800 | Y21: ='Sales Forecast'!G21*Assumptions!$E$17 -> 23968291 | Z21: ='Sales Forecast'!H21*Assumptions!$E$17 -> 24064164
B22: Handover 20% | C22: =IF(C$3>=EDATE('Project Database'!$E$6,ROUND('Scenario Toggle'!$E$12,0)),MAX(0,SUM('Sales Forecast'!$C$21:C21)*Assumptions!$E$18-0),0) -> 0 | D22: =IF(D$3>=EDATE('Project Database'!$E$6,ROUND('Scenario Toggle'!$E$12,0)),MAX(0,SUM('Sales Forecast'!$C$21:D21)*Assumptions!$E$18-SUM(C22)),0) -> 0 | E22: =IF(E$3>=EDATE('Project Database'!$E$6,ROUND('Scenario Toggle'!$E$12,0)),MAX(0,SUM('Sales Forecast'!$C$21:E21)*Assumptions!$E$18-SUM(C22:D22)),0) -> 0 | F22: =IF(F$3>=EDATE('Project Database'!$E$6,ROUND('Scenario Toggle'!$E$12,0)),MAX(0,SUM('Sales Forecast'!$C$21:F21)*Assumptions!$E$18-SUM(C22:E22)),0) -> 0 | G22: =IF(G$3>=EDATE('Project Database'!$E$6,ROUND('Scenario Toggle'!$E$12,0)),MAX(0,SUM('Sales Forecast'!$C$21:G21)*Assumptions!$E$18-SUM(C22:F22)),0) -> 0 | H22: =IF(H$3>=EDATE('Project Database'!$E$6,ROUND('Scenario Toggle'!$E$12,0)),MAX(0,SUM('Sales Forecast'!$C$21:H21)*Assumptions!$E$18-SUM(C22:G22)),0) -> 0 | I22: =IF(I$3>=EDATE('Project Database'!$E$6,ROUND('Scenario Toggle'!$E$12,0)),MAX(0,SUM('Sales Forecast'!$C$21:I21)*Assumptions!$E$18-SUM(C22:H22)),0) -> 0 | J22: =IF(J$3>=EDATE('Project Database'!$E$6,ROUND('Scenario Toggle'!$E$12,0)),MAX(0,SUM('Sales Forecast'!$C$21:J21)*Assumptions!$E$18-SUM(C22:I22)),0) -> 0 | K22: =IF(K$3>=EDATE('Project Database'!$E$6,ROUND('Scenario Toggle'!$E$12,0)),MAX(0,SUM('Sales Forecast'!$C$21:K21)*Assumptions!$E$18-SUM(C22:J22)),0) -> 0 | L22: =IF(L$3>=EDATE('Project Database'!$E$6,ROUND('Scenario Toggle'!$E$12,0)),MAX(0,SUM('Sales Forecast'!$C$21:L21)*Assumptions!$E$18-SUM(C22:K22)),0) -> 0 | M22: =IF(M$3>=EDATE('Project Database'!$E$6,ROUND('Scenario Toggle'!$E$12,0)),MAX(0,SUM('Sales Forecast'!$C$21:M21)*Assumptions!$E$18-SUM(C22:L22)),0) -> 0 | N22: =IF(N$3>=EDATE('Project Database'!$E$6,ROUND('Scenario Toggle'!$E$12,0)),MAX(0,SUM('Sales Forecast'!$C$21:N21)*Assumptions!$E$18-SUM(C22:M22)),0) -> 0 | O22: =IF(O$3>=EDATE('Project Database'!$E$6,ROUND('Scenario Toggle'!$E$12,0)),MAX(0,SUM('Sales Forecast'!$C$21:O21)*Assumptions!$E$18-SUM(C22:N22)),0) -> 0 | P22: =IF(P$3>=EDATE('Project Database'!$E$6,ROUND('Scenario Toggle'!$E$12,0)),MAX(0,SUM('Sales Forecast'!$C$21:P21)*Assumptions!$E$18-SUM(C22:O22)),0) -> 0 | Q22: =IF(Q$3>=EDATE('Project Database'!$E$6,ROUND('Scenario Toggle'!$E$12,0)),MAX(0,SUM('Sales Forecast'!$C$21:Q21)*Assumptions!$E$18-SUM(C22:P22)),0) -> 0 | R22: =IF(R$3>=EDATE('Project Database'!$E$6,ROUND('Scenario Toggle'!$E$12,0)),MAX(0,SUM('Sales Forecast'!$C$21:R21)*Assumptions!$E$18-SUM(C22:Q22)),0) -> 0 | S22: =IF(S$3>=EDATE('Project Database'!$E$6,ROUND('Scenario Toggle'!$E$12,0)),MAX(0,SUM('Sales Forecast'!$C$21:S21)*Assumptions!$E$18-SUM(C22:R22)),0) -> 0 | T22: =IF(T$3>=EDATE('Project Database'!$E$6,ROUND('Scenario Toggle'!$E$12,0)),MAX(0,SUM('Sales Forecast'!$C$21:T21)*Assumptions!$E$18-SUM(C22:S22)),0) -> 0 | U22: =IF(U$3>=EDATE('Project Database'!$E$6,ROUND('Scenario Toggle'!$E$12,0)),MAX(0,SUM('Sales Forecast'!$C$21:U21)*Assumptions!$E$18-SUM(C22:T22)),0) -> 0 | V22: =IF(V$3>=EDATE('Project Database'!$E$6,ROUND('Scenario Toggle'!$E$12,0)),MAX(0,SUM('Sales Forecast'!$C$21:V21)*Assumptions!$E$18-SUM(C22:U22)),0) -> 0 | W22: =IF(W$3>=EDATE('Project Database'!$E$6,ROUND('Scenario Toggle'!$E$12,0)),MAX(0,SUM('Sales Forecast'!$C$21:W21)*Assumptions!$E$18-SUM(C22:V22)),0) -> 0 | X22: =IF(X$3>=EDATE('Project Database'!$E$6,ROUND('Scenario Toggle'!$E$12,0)),MAX(0,SUM('Sales Forecast'!$C$21:X21)*Assumptions!$E$18-SUM(C22:W22)),0) -> 0 | Y22: =IF(Y$3>=EDATE('Project Database'!$E$6,ROUND('Scenario Toggle'!$E$12,0)),MAX(0,SUM('Sales Forecast'!$C$21:Y21)*Assumptions!$E$18-SUM(C22:X22)),0) -> 0 | Z22: =IF(Z$3>=EDATE('Project Database'!$E$6,ROUND('Scenario Toggle'!$E$12,0)),MAX(0,SUM('Sales Forecast'!$C$21:Z21)*Assumptions!$E$18-SUM(C22:Y22)),0) -> 5.2189924e+08
B23: Total Customer Collections | C23: =SUM(C18:C22) -> 0 | D23: =SUM(D18:D22) -> 0 | E23: =SUM(E18:E22) -> 0 | F23: =SUM(F18:F22) -> 23872800 | G23: =SUM(G18:G22) -> 23968291 | H23: =SUM(H18:H22) -> 24064164 | I23: =SUM(I18:I22) -> 24160421 | J23: =SUM(J18:J22) -> 24257063 | ... Z23: =SUM(Z18:Z22) -> 6.2171288e+08
B24: Sales Commissions | C24: ='Sales Forecast'!C21*Assumptions!$E$19 -> 0 | D24: ='Sales Forecast'!D21*Assumptions!$E$19 -> 0 | E24: ='Sales Forecast'!E21*Assumptions!$E$19 -> 0 | F24: ='Sales Forecast'!F21*Assumptions!$E$19 -> 3580920 | G24: ='Sales Forecast'!G21*Assumptions!$E$19 -> 3595243.7 | H24: ='Sales Forecast'!H21*Assumptions!$E$19 -> 3609624.7 | I24: ='Sales Forecast'!I21*Assumptions!$E$19 -> 3624063.2 | J24: ='Sales Forecast'!J21*Assumptions!$E$19 -> 3638559.4 | ... Z24: ='Sales Forecast'!Z21*Assumptions!$E$19 -> 3878545.4
A25: Jumeirah Mixed-Use Development | B25: Booking 20% | C25: ='Sales Forecast'!C27*Assumptions!$E$14 -> 0 | D25: ='Sales Forecast'!D27*Assumptions!$E$14 -> 0 | E25: ='Sales Forecast'!E27*Assumptions!$E$14 -> 13912080 | F25: ='Sales Forecast'!F27*Assumptions!$E$14 -> 13967728 | G25: ='Sales Forecast'!G27*Assumptions!$E$14 -> 14023599 | H25: ='Sales Forecast'!H27*Assumptions!$E$14 -> 14079694 | I25: ='Sales Forecast'!I27*Assumptions!$E$14 -> 14136012 | J25: ='Sales Forecast'!J27*Assumptions!$E$14 -> 14192556 | ... Z25: ='Sales Forecast'!Z27*Assumptions!$E$14 -> 0
B26: Milestone 1 20% | C26: 0 | D26: 0 | E26: 0 | F26: 0 | G26: 0 | H26: 0 | I26: ='Sales Forecast'!C27*Assumptions!$E$15 -> 0 | J26: ='Sales Forecast'!D27*Assumptions!$E$15 -> 0 | K26: ='Sales Forecast'!E27*Assumptions!$E$15 -> 13912080 | L26: ='Sales Forecast'!F27*Assumptions!$E$15 -> 13967728 | M26: ='Sales Forecast'!G27*Assumptions!$E$15 -> 14023599 | N26: ='Sales Forecast'!H27*Assumptions!$E$15 -> 14079694 | O26: ='Sales Forecast'!I27*Assumptions!$E$15 -> 14136012 | P26: ='Sales Forecast'!J27*Assumptions!$E$15 -> 14192556 | ... Z26: ='Sales Forecast'!T27*Assumptions!$E$15 -> 14770587
B27: Milestone 2 20% | C27: 0 | D27: 0 | E27: 0 | F27: 0 | G27: 0 | H27: 0 | I27: 0 | J27: 0 | K27: 0 | L27: 0 | M27: 0 | N27: 0 | O27: ='Sales Forecast'!C27*Assumptions!$E$16 -> 0 | P27: ='Sales Forecast'!D27*Assumptions!$E$16 -> 0 | Q27: ='Sales Forecast'!E27*Assumptions!$E$16 -> 13912080 | R27: ='Sales Forecast'!F27*Assumptions!$E$16 -> 13967728 | S27: ='Sales Forecast'!G27*Assumptions!$E$16 -> 14023599 | T27: ='Sales Forecast'!H27*Assumptions!$E$16 -> 14079694 | U27: ='Sales Forecast'!I27*Assumptions!$E$16 -> 14136012 | V27: ='Sales Forecast'!J27*Assumptions!$E$16 -> 14192556 | ... Z27: ='Sales Forecast'!N27*Assumptions!$E$16 -> 14421003
B28: Milestone 3 20% | C28: 0 | D28: 0 | E28: 0 | F28: 0 | G28: 0 | H28: 0 | I28: 0 | J28: 0 | K28: 0 | L28: 0 | M28: 0 | N28: 0 | O28: 0 | P28: 0 | Q28: 0 | R28: 0 | S28: 0 | T28: 0 | U28: ='Sales Forecast'!C27*Assumptions!$E$17 -> 0 | V28: ='Sales Forecast'!D27*Assumptions!$E$17 -> 0 | W28: ='Sales Forecast'!E27*Assumptions!$E$17 -> 13912080 | X28: ='Sales Forecast'!F27*Assumptions!$E$17 -> 13967728 | Y28: ='Sales Forecast'!G27*Assumptions!$E$17 -> 14023599 | Z28: ='Sales Forecast'!H27*Assumptions!$E$17 -> 14079694
B29: Handover 20% | C29: =IF(C$3>=EDATE('Project Database'!$E$7,ROUND('Scenario Toggle'!$E$12,0)),MAX(0,SUM('Sales Forecast'!$C$27:C27)*Assumptions!$E$18-0),0) -> 0 | D29: =IF(D$3>=EDATE('Project Database'!$E$7,ROUND('Scenario Toggle'!$E$12,0)),MAX(0,SUM('Sales Forecast'!$C$27:D27)*Assumptions!$E$18-SUM(C29)),0) -> 0 | E29: =IF(E$3>=EDATE('Project Database'!$E$7,ROUND('Scenario Toggle'!$E$12,0)),MAX(0,SUM('Sales Forecast'!$C$27:E27)*Assumptions!$E$18-SUM(C29:D29)),0) -> 0 | F29: =IF(F$3>=EDATE('Project Database'!$E$7,ROUND('Scenario Toggle'!$E$12,0)),MAX(0,SUM('Sales Forecast'!$C$27:F27)*Assumptions!$E$18-SUM(C29:E29)),0) -> 0 | G29: =IF(G$3>=EDATE('Project Database'!$E$7,ROUND('Scenario Toggle'!$E$12,0)),MAX(0,SUM('Sales Forecast'!$C$27:G27)*Assumptions!$E$18-SUM(C29:F29)),0) -> 0 | H29: =IF(H$3>=EDATE('Project Database'!$E$7,ROUND('Scenario Toggle'!$E$12,0)),MAX(0,SUM('Sales Forecast'!$C$27:H27)*Assumptions!$E$18-SUM(C29:G29)),0) -> 0 | I29: =IF(I$3>=EDATE('Project Database'!$E$7,ROUND('Scenario Toggle'!$E$12,0)),MAX(0,SUM('Sales Forecast'!$C$27:I27)*Assumptions!$E$18-SUM(C29:H29)),0) -> 0 | J29: =IF(J$3>=EDATE('Project Database'!$E$7,ROUND('Scenario Toggle'!$E$12,0)),MAX(0,SUM('Sales Forecast'!$C$27:J27)*Assumptions!$E$18-SUM(C29:I29)),0) -> 0 | K29: =IF(K$3>=EDATE('Project Database'!$E$7,ROUND('Scenario Toggle'!$E$12,0)),MAX(0,SUM('Sales Forecast'!$C$27:K27)*Assumptions!$E$18-SUM(C29:J29)),0) -> 0 | L29: =IF(L$3>=EDATE('Project Database'!$E$7,ROUND('Scenario Toggle'!$E$12,0)),MAX(0,SUM('Sales Forecast'!$C$27:L27)*Assumptions!$E$18-SUM(C29:K29)),0) -> 0 | M29: =IF(M$3>=EDATE('Project Database'!$E$7,ROUND('Scenario Toggle'!$E$12,0)),MAX(0,SUM('Sales Forecast'!$C$27:M27)*Assumptions!$E$18-SUM(C29:L29)),0) -> 0 | N29: =IF(N$3>=EDATE('Project Database'!$E$7,ROUND('Scenario Toggle'!$E$12,0)),MAX(0,SUM('Sales Forecast'!$C$27:N27)*Assumptions!$E$18-SUM(C29:M29)),0) -> 0 | O29: =IF(O$3>=EDATE('Project Database'!$E$7,ROUND('Scenario Toggle'!$E$12,0)),MAX(0,SUM('Sales Forecast'!$C$27:O27)*Assumptions!$E$18-SUM(C29:N29)),0) -> 0 | P29: =IF(P$3>=EDATE('Project Database'!$E$7,ROUND('Scenario Toggle'!$E$12,0)),MAX(0,SUM('Sales Forecast'!$C$27:P27)*Assumptions!$E$18-SUM(C29:O29)),0) -> 0 | Q29: =IF(Q$3>=EDATE('Project Database'!$E$7,ROUND('Scenario Toggle'!$E$12,0)),MAX(0,SUM('Sales Forecast'!$C$27:Q27)*Assumptions!$E$18-SUM(C29:P29)),0) -> 0 | R29: =IF(R$3>=EDATE('Project Database'!$E$7,ROUND('Scenario Toggle'!$E$12,0)),MAX(0,SUM('Sales Forecast'!$C$27:R27)*Assumptions!$E$18-SUM(C29:Q29)),0) -> 0 | S29: =IF(S$3>=EDATE('Project Database'!$E$7,ROUND('Scenario Toggle'!$E$12,0)),MAX(0,SUM('Sales Forecast'!$C$27:S27)*Assumptions!$E$18-SUM(C29:R29)),0) -> 0 | T29: =IF(T$3>=EDATE('Project Database'!$E$7,ROUND('Scenario Toggle'!$E$12,0)),MAX(0,SUM('Sales Forecast'!$C$27:T27)*Assumptions!$E$18-SUM(C29:S29)),0) -> 0 | U29: =IF(U$3>=EDATE('Project Database'!$E$7,ROUND('Scenario Toggle'!$E$12,0)),MAX(0,SUM('Sales Forecast'!$C$27:U27)*Assumptions!$E$18-SUM(C29:T29)),0) -> 0 | V29: =IF(V$3>=EDATE('Project Database'!$E$7,ROUND('Scenario Toggle'!$E$12,0)),MAX(0,SUM('Sales Forecast'!$C$27:V27)*Assumptions!$E$18-SUM(C29:U29)),0) -> 0 | W29: =IF(W$3>=EDATE('Project Database'!$E$7,ROUND('Scenario Toggle'!$E$12,0)),MAX(0,SUM('Sales Forecast'!$C$27:W27)*Assumptions!$E$18-SUM(C29:V29)),0) -> 0 | X29: =IF(X$3>=EDATE('Project Database'!$E$7,ROUND('Scenario Toggle'!$E$12,0)),MAX(0,SUM('Sales Forecast'!$C$27:X27)*Assumptions!$E$18-SUM(C29:W29)),0) -> 0 | Y29: =IF(Y$3>=EDATE('Project Database'!$E$7,ROUND('Scenario Toggle'!$E$12,0)),MAX(0,SUM('Sales Forecast'!$C$27:Y27)*Assumptions!$E$18-SUM(C29:X29)),0) -> 2.9510026e+08 | Z29: =IF(Z$3>=EDATE('Project Database'!$E$7,ROUND('Scenario Toggle'!$E$12,0)),MAX(0,SUM('Sales Forecast'!$C$27:Z27)*Assumptions!$E$18-SUM(C29:Y29)),0) -> 0
B30: Total Customer Collections | C30: =SUM(C25:C29) -> 0 | D30: =SUM(D25:D29) -> 0 | E30: =SUM(E25:E29) -> 13912080 | F30: =SUM(F25:F29) -> 13967728 | G30: =SUM(G25:G29) -> 14023599 | H30: =SUM(H25:H29) -> 14079694 | I30: =SUM(I25:I29) -> 14136012 | J30: =SUM(J25:J29) -> 14192556 | ... Z30: =SUM(Z25:Z29) -> 43271284
B31: Sales Commissions | C31: ='Sales Forecast'!C27*Assumptions!$E$19 -> 0 | D31: ='Sales Forecast'!D27*Assumptions!$E$19 -> 0 | E31: ='Sales Forecast'!E27*Assumptions!$E$19 -> 2086812 | F31: ='Sales Forecast'!F27*Assumptions!$E$19 -> 2095159.2 | G31: ='Sales Forecast'!G27*Assumptions!$E$19 -> 2103539.9 | H31: ='Sales Forecast'!H27*Assumptions!$E$19 -> 2111954 | I31: ='Sales Forecast'!I27*Assumptions!$E$19 -> 2120401.9 | J31: ='Sales Forecast'!J27*Assumptions!$E$19 -> 2128883.5 | ... Z31: ='Sales Forecast'!Z27*Assumptions!$E$19 -> 0
A33: Portfolio | B33: Total Collections | C33: =C9+C16+C23+C30 -> 31360000 | D33: =D9+D16+D23+D30 -> 52124240 | E33: =E9+E16+E23+E30 -> 66244817 | F33: =F9+F16+F23+F30 -> 90382596 | G33: =G9+G16+G23+G30 -> 90744127 | H33: =H9+H16+H23+H30 -> 91107103 | I33: =I9+I16+I23+I30 -> 1.2283153e+08 | J33: =J9+J16+J23+J30 -> 1.4396166e+08 | ... Z33: =Z9+Z16+Z23+Z30 -> 8.2775671e+08
B34: Total Sales Commissions | C34: =C10+C17+C24+C31 -> 4704000 | D34: =D10+D17+D24+D31 -> 7818636 | E34: =E10+E17+E24+E31 -> 9936722.5 | F34: =F10+F17+F24+F31 -> 13557389 | G34: =G10+G17+G24+G31 -> 13611619 | H34: =H10+H17+H24+H31 -> 13666065 | I34: =I10+I17+I24+I31 -> 13720730 | J34: =J10+J17+J24+J31 -> 13775613 | ... Z34: =Z10+Z17+Z24+Z31 -> 3878545.4

Sheet Construction Costs
A1: Project Construction Cost Schedule
A3: Project | B3: Metric | C3: Budget / KPI | D3: 46113 | E3: 46143 | F3: 46174 | G3: 46204 | H3: 46235 | I3: 46266 | J3: 46296 | K3: 46327 | L3: 46357 | M3: 46388 | N3: 46419 | O3: 46447 | P3: 46478 | Q3: 46508 | R3: 46539 | S3: 46569 | T3: 46600 | U3: 46631 | V3: 46661 | W3: 46692 | X3: 46722 | Y3: 46753 | Z3: 46784 | AA3: 46813
A4: Marina Residences Tower | B4: Total Budget | C4: ='Project Database'!$F$4 -> 900000000
B5: Monthly Spend | D5: =IF(AND(D$3>='Project Database'!$D$4,D$3<=EDATE('Project Database'!$E$4,ROUND('Scenario Toggle'!$E$12,0))),('Project Database'!$F$4*(1+'Scenario Toggle'!$E$11))/MAX(1,DATEDIF('Project Database'!$D$4,EDATE('Project Database'!$E$4,ROUND('Scenario Toggle'!$E$12,0)),"m")+1)*(1+Assumptions!$E$6/12)^DATEDIF('Project Database'!$D$4,D$3,"m"),0) -> 50000000 | E5: =IF(AND(E$3>='Project Database'!$D$4,E$3<=EDATE('Project Database'!$E$4,ROUND('Scenario Toggle'!$E$12,0))),('Project Database'!$F$4*(1+'Scenario Toggle'!$E$11))/MAX(1,DATEDIF('Project Database'!$D$4,EDATE('Project Database'!$E$4,ROUND('Scenario Toggle'!$E$12,0)),"m")+1)*(1+Assumptions!$E$6/12)^DATEDIF('Project Database'!$D$4,E$3,"m"),0) -> 50125000 | F5: =IF(AND(F$3>='Project Database'!$D$4,F$3<=EDATE('Project Database'!$E$4,ROUND('Scenario Toggle'!$E$12,0))),('Project Database'!$F$4*(1+'Scenario Toggle'!$E$11))/MAX(1,DATEDIF('Project Database'!$D$4,EDATE('Project Database'!$E$4,ROUND('Scenario Toggle'!$E$12,0)),"m")+1)*(1+Assumptions!$E$6/12)^DATEDIF('Project Database'!$D$4,F$3,"m"),0) -> 50250312 | G5: =IF(AND(G$3>='Project Database'!$D$4,G$3<=EDATE('Project Database'!$E$4,ROUND('Scenario Toggle'!$E$12,0))),('Project Database'!$F$4*(1+'Scenario Toggle'!$E$11))/MAX(1,DATEDIF('Project Database'!$D$4,EDATE('Project Database'!$E$4,ROUND('Scenario Toggle'!$E$12,0)),"m")+1)*(1+Assumptions!$E$6/12)^DATEDIF('Project Database'!$D$4,G$3,"m"),0) -> 50375938 | H5: =IF(AND(H$3>='Project Database'!$D$4,H$3<=EDATE('Project Database'!$E$4,ROUND('Scenario Toggle'!$E$12,0))),('Project Database'!$F$4*(1+'Scenario Toggle'!$E$11))/MAX(1,DATEDIF('Project Database'!$D$4,EDATE('Project Database'!$E$4,ROUND('Scenario Toggle'!$E$12,0)),"m")+1)*(1+Assumptions!$E$6/12)^DATEDIF('Project Database'!$D$4,H$3,"m"),0) -> 50501878 | I5: =IF(AND(I$3>='Project Database'!$D$4,I$3<=EDATE('Project Database'!$E$4,ROUND('Scenario Toggle'!$E$12,0))),('Project Database'!$F$4*(1+'Scenario Toggle'!$E$11))/MAX(1,DATEDIF('Project Database'!$D$4,EDATE('Project Database'!$E$4,ROUND('Scenario Toggle'!$E$12,0)),"m")+1)*(1+Assumptions!$E$6/12)^DATEDIF('Project Database'!$D$4,I$3,"m"),0) -> 50628133 | J5: =IF(AND(J$3>='Project Database'!$D$4,J$3<=EDATE('Project Database'!$E$4,ROUND('Scenario Toggle'!$E$12,0))),('Project Database'!$F$4*(1+'Scenario Toggle'!$E$11))/MAX(1,DATEDIF('Project Database'!$D$4,EDATE('Project Database'!$E$4,ROUND('Scenario Toggle'!$E$12,0)),"m")+1)*(1+Assumptions!$E$6/12)^DATEDIF('Project Database'!$D$4,J$3,"m"),0) -> 50754703 | K5: =IF(AND(K$3>='Project Database'!$D$4,K$3<=EDATE('Project Database'!$E$4,ROUND('Scenario Toggle'!$E$12,0))),('Project Database'!$F$4*(1+'Scenario Toggle'!$E$11))/MAX(1,DATEDIF('Project Database'!$D$4,EDATE('Project Database'!$E$4,ROUND('Scenario Toggle'!$E$12,0)),"m")+1)*(1+Assumptions!$E$6/12)^DATEDIF('Project Database'!$D$4,K$3,"m"),0) -> 50881590 | ... AA5: =IF(AND(AA$3>='Project Database'!$D$4,AA$3<=EDATE('Project Database'!$E$4,ROUND('Scenario Toggle'!$E$12,0))),('Project Database'!$F$4*(1+'Scenario Toggle'!$E$11))/MAX(1,DATEDIF('Project Database'!$D$4,EDATE('Project Database'!$E$4,ROUND('Scenario Toggle'!$E$12,0)),"m")+1)*(1+Assumptions!$E$6/12)^DATEDIF('Project Database'!$D$4,AA$3,"m"),0) -> 0
B6: Cumulative Spend | D6: =SUM($D5:D5) -> 50000000 | E6: =SUM($D5:E5) -> 100125000 | F6: =SUM($D5:F5) -> 1.5037531e+08 | G6: =SUM($D5:G5) -> 2.0075125e+08 | H6: =SUM($D5:H5) -> 2.5125313e+08 | I6: =SUM($D5:I5) -> 3.0188126e+08 | J6: =SUM($D5:J5) -> 3.5263596e+08 | K6: =SUM($D5:K5) -> 4.0351755e+08 | ... AA6: =SUM($D5:AA5) -> 9.1938241e+08
B7: Remaining Cost | D7: =MAX(0,$C4-D6) -> 850000000 | E7: =MAX(0,$C4-E6) -> 799875000 | F7: =MAX(0,$C4-F6) -> 7.4962469e+08 | G7: =MAX(0,$C4-G6) -> 6.9924875e+08 | H7: =MAX(0,$C4-H6) -> 6.4874687e+08 | I7: =MAX(0,$C4-I6) -> 5.9811874e+08 | J7: =MAX(0,$C4-J6) -> 5.4736404e+08 | K7: =MAX(0,$C4-K6) -> 4.9648245e+08 | ... AA7: =MAX(0,$C4-AA6) -> 0
B8: Construction Progress % | D8: =MIN(1,D6/($C4)) -> 0.055555556 | E8: =MIN(1,E6/($C4)) -> 0.11125 | F8: =MIN(1,F6/($C4)) -> 0.16708368 | G8: =MIN(1,G6/($C4)) -> 0.22305695 | H8: =MIN(1,H6/($C4)) -> 0.27917014 | I8: =MIN(1,I6/($C4)) -> 0.33542362 | J8: =MIN(1,J6/($C4)) -> 0.39181774 | K8: =MIN(1,K6/($C4)) -> 0.44835284 | ... AA8: =MIN(1,AA6/($C4)) -> 1
B9: Approved Release % | D9: =MIN(0.9,D8) -> 0.055555556 | E9: =MIN(0.9,E8) -> 0.11125 | F9: =MIN(0.9,F8) -> 0.16708368 | G9: =MIN(0.9,G8) -> 0.22305695 | H9: =MIN(0.9,H8) -> 0.27917014 | I9: =MIN(0.9,I8) -> 0.33542362 | J9: =MIN(0.9,J8) -> 0.39181774 | K9: =MIN(0.9,K8) -> 0.44835284 | ... AA9: =MIN(0.9,AA8) -> 0.9
A10: Palm Waterfront Villas | B10: Total Budget | C10: ='Project Database'!$F$5 -> 650000000
B11: Monthly Spend | D11: =IF(AND(D$3>='Project Database'!$D$5,D$3<=EDATE('Project Database'!$E$5,ROUND('Scenario Toggle'!$E$12,0))),('Project Database'!$F$5*(1+'Scenario Toggle'!$E$11))/MAX(1,DATEDIF('Project Database'!$D$5,EDATE('Project Database'!$E$5,ROUND('Scenario Toggle'!$E$12,0)),"m")+1)*(1+Assumptions!$E$6/12)^DATEDIF('Project Database'!$D$5,D$3,"m"),0) -> 0 | E11: =IF(AND(E$3>='Project Database'!$D$5,E$3<=EDATE('Project Database'!$E$5,ROUND('Scenario Toggle'!$E$12,0))),('Project Database'!$F$5*(1+'Scenario Toggle'!$E$11))/MAX(1,DATEDIF('Project Database'!$D$5,EDATE('Project Database'!$E$5,ROUND('Scenario Toggle'!$E$12,0)),"m")+1)*(1+Assumptions!$E$6/12)^DATEDIF('Project Database'!$D$5,E$3,"m"),0) -> 32500000 | F11: =IF(AND(F$3>='Project Database'!$D$5,F$3<=EDATE('Project Database'!$E$5,ROUND('Scenario Toggle'!$E$12,0))),('Project Database'!$F$5*(1+'Scenario Toggle'!$E$11))/MAX(1,DATEDIF('Project Database'!$D$5,EDATE('Project Database'!$E$5,ROUND('Scenario Toggle'!$E$12,0)),"m")+1)*(1+Assumptions!$E$6/12)^DATEDIF('Project Database'!$D$5,F$3,"m"),0) -> 32581250 | G11: =IF(AND(G$3>='Project Database'!$D$5,G$3<=EDATE('Project Database'!$E$5,ROUND('Scenario Toggle'!$E$12,0))),('Project Database'!$F$5*(1+'Scenario Toggle'!$E$11))/MAX(1,DATEDIF('Project Database'!$D$5,EDATE('Project Database'!$E$5,ROUND('Scenario Toggle'!$E$12,0)),"m")+1)*(1+Assumptions!$E$6/12)^DATEDIF('Project Database'!$D$5,G$3,"m"),0) -> 32662703 | H11: =IF(AND(H$3>='Project Database'!$D$5,H$3<=EDATE('Project Database'!$E$5,ROUND('Scenario Toggle'!$E$12,0))),('Project Database'!$F$5*(1+'Scenario Toggle'!$E$11))/MAX(1,DATEDIF('Project Database'!$D$5,EDATE('Project Database'!$E$5,ROUND('Scenario Toggle'!$E$12,0)),"m")+1)*(1+Assumptions!$E$6/12)^DATEDIF('Project Database'!$D$5,H$3,"m"),0) -> 32744360 | I11: =IF(AND(I$3>='Project Database'!$D$5,I$3<=EDATE('Project Database'!$E$5,ROUND('Scenario Toggle'!$E$12,0))),('Project Database'!$F$5*(1+'Scenario Toggle'!$E$11))/MAX(1,DATEDIF('Project Database'!$D$5,EDATE('Project Database'!$E$5,ROUND('Scenario Toggle'!$E$12,0)),"m")+1)*(1+Assumptions!$E$6/12)^DATEDIF('Project Database'!$D$5,I$3,"m"),0) -> 32826221 | J11: =IF(AND(J$3>='Project Database'!$D$5,J$3<=EDATE('Project Database'!$E$5,ROUND('Scenario Toggle'!$E$12,0))),('Project Database'!$F$5*(1+'Scenario Toggle'!$E$11))/MAX(1,DATEDIF('Project Database'!$D$5,EDATE('Project Database'!$E$5,ROUND('Scenario Toggle'!$E$12,0)),"m")+1)*(1+Assumptions!$E$6/12)^DATEDIF('Project Database'!$D$5,J$3,"m"),0) -> 32908286 | K11: =IF(AND(K$3>='Project Database'!$D$5,K$3<=EDATE('Project Database'!$E$5,ROUND('Scenario Toggle'!$E$12,0))),('Project Database'!$F$5*(1+'Scenario Toggle'!$E$11))/MAX(1,DATEDIF('Project Database'!$D$5,EDATE('Project Database'!$E$5,ROUND('Scenario Toggle'!$E$12,0)),"m")+1)*(1+Assumptions!$E$6/12)^DATEDIF('Project Database'!$D$5,K$3,"m"),0) -> 32990557 | ... AA11: =IF(AND(AA$3>='Project Database'!$D$5,AA$3<=EDATE('Project Database'!$E$5,ROUND('Scenario Toggle'!$E$12,0))),('Project Database'!$F$5*(1+'Scenario Toggle'!$E$11))/MAX(1,DATEDIF('Project Database'!$D$5,EDATE('Project Database'!$E$5,ROUND('Scenario Toggle'!$E$12,0)),"m")+1)*(1+Assumptions!$E$6/12)^DATEDIF('Project Database'!$D$5,AA$3,"m"),0) -> 0
B12: Cumulative Spend | D12: =SUM($D11:D11) -> 0 | E12: =SUM($D11:E11) -> 32500000 | F12: =SUM($D11:F11) -> 65081250 | G12: =SUM($D11:G11) -> 97743953 | H12: =SUM($D11:H11) -> 1.3048831e+08 | I12: =SUM($D11:I11) -> 1.6331453e+08 | J12: =SUM($D11:J11) -> 1.9622282e+08 | K12: =SUM($D11:K11) -> 2.2921338e+08 | ... AA12: =SUM($D11:AA11) -> 6.6567154e+08
B13: Remaining Cost | D13: =MAX(0,$C10-D12) -> 650000000 | E13: =MAX(0,$C10-E12) -> 617500000 | F13: =MAX(0,$C10-F12) -> 584918750 | G13: =MAX(0,$C10-G12) -> 5.5225605e+08 | H13: =MAX(0,$C10-H12) -> 5.1951169e+08 | I13: =MAX(0,$C10-I12) -> 4.8668547e+08 | J13: =MAX(0,$C10-J12) -> 4.5377718e+08 | K13: =MAX(0,$C10-K12) -> 4.2078662e+08 | ... AA13: =MAX(0,$C10-AA12) -> 0
B14: Construction Progress % | D14: =MIN(1,D12/($C10)) -> 0 | E14: =MIN(1,E12/($C10)) -> 0.05 | F14: =MIN(1,F12/($C10)) -> 0.100125 | G14: =MIN(1,G12/($C10)) -> 0.15037531 | H14: =MIN(1,H12/($C10)) -> 0.20075125 | I14: =MIN(1,I12/($C10)) -> 0.25125313 | J14: =MIN(1,J12/($C10)) -> 0.30188126 | K14: =MIN(1,K12/($C10)) -> 0.35263596 | ... AA14: =MIN(1,AA12/($C10)) -> 1
B15: Approved Release % | D15: =MIN(0.9,D14) -> 0 | E15: =MIN(0.9,E14) -> 0.05 | F15: =MIN(0.9,F14) -> 0.100125 | G15: =MIN(0.9,G14) -> 0.15037531 | H15: =MIN(0.9,H14) -> 0.20075125 | I15: =MIN(0.9,I14) -> 0.25125313 | J15: =MIN(0.9,J14) -> 0.30188126 | K15: =MIN(0.9,K14) -> 0.35263596 | ... AA15: =MIN(0.9,AA14) -> 0.9
A16: Downtown Branded Residences | B16: Total Budget | C16: ='Project Database'!$F$6 -> 1100000000
B17: Monthly Spend | D17: =IF(AND(D$3>='Project Database'!$D$6,D$3<=EDATE('Project Database'!$E$6,ROUND('Scenario Toggle'!$E$12,0))),('Project Database'!$F$6*(1+'Scenario Toggle'!$E$11))/MAX(1,DATEDIF('Project Database'!$D$6,EDATE('Project Database'!$E$6,ROUND('Scenario Toggle'!$E$12,0)),"m")+1)*(1+Assumptions!$E$6/12)^DATEDIF('Project Database'!$D$6,D$3,"m"),0) -> 0 | E17: =IF(AND(E$3>='Project Database'!$D$6,E$3<=EDATE('Project Database'!$E$6,ROUND('Scenario Toggle'!$E$12,0))),('Project Database'!$F$6*(1+'Scenario Toggle'!$E$11))/MAX(1,DATEDIF('Project Database'!$D$6,EDATE('Project Database'!$E$6,ROUND('Scenario Toggle'!$E$12,0)),"m")+1)*(1+Assumptions!$E$6/12)^DATEDIF('Project Database'!$D$6,E$3,"m"),0) -> 0 | F17: =IF(AND(F$3>='Project Database'!$D$6,F$3<=EDATE('Project Database'!$E$6,ROUND('Scenario Toggle'!$E$12,0))),('Project Database'!$F$6*(1+'Scenario Toggle'!$E$11))/MAX(1,DATEDIF('Project Database'!$D$6,EDATE('Project Database'!$E$6,ROUND('Scenario Toggle'!$E$12,0)),"m")+1)*(1+Assumptions!$E$6/12)^DATEDIF('Project Database'!$D$6,F$3,"m"),0) -> 0 | G17: =IF(AND(G$3>='Project Database'!$D$6,G$3<=EDATE('Project Database'!$E$6,ROUND('Scenario Toggle'!$E$12,0))),('Project Database'!$F$6*(1+'Scenario Toggle'!$E$11))/MAX(1,DATEDIF('Project Database'!$D$6,EDATE('Project Database'!$E$6,ROUND('Scenario Toggle'!$E$12,0)),"m")+1)*(1+Assumptions!$E$6/12)^DATEDIF('Project Database'!$D$6,G$3,"m"),0) -> 52380952 | H17: =IF(AND(H$3>='Project Database'!$D$6,H$3<=EDATE('Project Database'!$E$6,ROUND('Scenario Toggle'!$E$12,0))),('Project Database'!$F$6*(1+'Scenario Toggle'!$E$11))/MAX(1,DATEDIF('Project Database'!$D$6,EDATE('Project Database'!$E$6,ROUND('Scenario Toggle'!$E$12,0)),"m")+1)*(1+Assumptions!$E$6/12)^DATEDIF('Project Database'!$D$6,H$3,"m"),0) -> 52511905 | I17: =IF(AND(I$3>='Project Database'!$D$6,I$3<=EDATE('Project Database'!$E$6,ROUND('Scenario Toggle'!$E$12,0))),('Project Database'!$F$6*(1+'Scenario Toggle'!$E$11))/MAX(1,DATEDIF('Project Database'!$D$6,EDATE('Project Database'!$E$6,ROUND('Scenario Toggle'!$E$12,0)),"m")+1)*(1+Assumptions!$E$6/12)^DATEDIF('Project Database'!$D$6,I$3,"m"),0) -> 52643185 | J17: =IF(AND(J$3>='Project Database'!$D$6,J$3<=EDATE('Project Database'!$E$6,ROUND('Scenario Toggle'!$E$12,0))),('Project Database'!$F$6*(1+'Scenario Toggle'!$E$11))/MAX(1,DATEDIF('Project Database'!$D$6,EDATE('Project Database'!$E$6,ROUND('Scenario Toggle'!$E$12,0)),"m")+1)*(1+Assumptions!$E$6/12)^DATEDIF('Project Database'!$D$6,J$3,"m"),0) -> 52774792 | K17: =IF(AND(K$3>='Project Database'!$D$6,K$3<=EDATE('Project Database'!$E$6,ROUND('Scenario Toggle'!$E$12,0))),('Project Database'!$F$6*(1+'Scenario Toggle'!$E$11))/MAX(1,DATEDIF('Project Database'!$D$6,EDATE('Project Database'!$E$6,ROUND('Scenario Toggle'!$E$12,0)),"m")+1)*(1+Assumptions!$E$6/12)^DATEDIF('Project Database'!$D$6,K$3,"m"),0) -> 52906729 | ... AA17: =IF(AND(AA$3>='Project Database'!$D$6,AA$3<=EDATE('Project Database'!$E$6,ROUND('Scenario Toggle'!$E$12,0))),('Project Database'!$F$6*(1+'Scenario Toggle'!$E$11))/MAX(1,DATEDIF('Project Database'!$D$6,EDATE('Project Database'!$E$6,ROUND('Scenario Toggle'!$E$12,0)),"m")+1)*(1+Assumptions!$E$6/12)^DATEDIF('Project Database'!$D$6,AA$3,"m"),0) -> 55063145
B18: Cumulative Spend | D18: =SUM($D17:D17) -> 0 | E18: =SUM($D17:E17) -> 0 | F18: =SUM($D17:F17) -> 0 | G18: =SUM($D17:G17) -> 52380952 | H18: =SUM($D17:H17) -> 1.0489286e+08 | I18: =SUM($D17:I17) -> 1.5753604e+08 | J18: =SUM($D17:J17) -> 2.1031083e+08 | K18: =SUM($D17:K17) -> 2.6321756e+08 | ... AA18: =SUM($D17:AA17) -> 1.1279404e+09
B19: Remaining Cost | D19: =MAX(0,$C16-D18) -> 1100000000 | E19: =MAX(0,$C16-E18) -> 1100000000 | F19: =MAX(0,$C16-F18) -> 1100000000 | G19: =MAX(0,$C16-G18) -> 1.047619e+09 | H19: =MAX(0,$C16-H18) -> 9.9510714e+08 | I19: =MAX(0,$C16-I18) -> 9.4246396e+08 | J19: =MAX(0,$C16-J18) -> 8.8968917e+08 | K19: =MAX(0,$C16-K18) -> 8.3678244e+08 | ... AA19: =MAX(0,$C16-AA18) -> 0
B20: Construction Progress % | D20: =MIN(1,D18/($C16)) -> 0 | E20: =MIN(1,E18/($C16)) -> 0 | F20: =MIN(1,F18/($C16)) -> 0 | G20: =MIN(1,G18/($C16)) -> 0.047619048 | H20: =MIN(1,H18/($C16)) -> 0.095357143 | I20: =MIN(1,I18/($C16)) -> 0.14321458 | J20: =MIN(1,J18/($C16)) -> 0.19119167 | K20: =MIN(1,K18/($C16)) -> 0.23928869 | ... AA20: =MIN(1,AA18/($C16)) -> 1
B21: Approved Release % | D21: =MIN(0.9,D20) -> 0 | E21: =MIN(0.9,E20) -> 0 | F21: =MIN(0.9,F20) -> 0 | G21: =MIN(0.9,G20) -> 0.047619048 | H21: =MIN(0.9,H20) -> 0.095357143 | I21: =MIN(0.9,I20) -> 0.14321458 | J21: =MIN(0.9,J20) -> 0.19119167 | K21: =MIN(0.9,K20) -> 0.23928869 | ... AA21: =MIN(0.9,AA20) -> 0.9
A22: Jumeirah Mixed-Use Development | B22: Total Budget | C22: ='Project Database'!$F$7 -> 850000000
B23: Monthly Spend | D23: =IF(AND(D$3>='Project Database'!$D$7,D$3<=EDATE('Project Database'!$E$7,ROUND('Scenario Toggle'!$E$12,0))),('Project Database'!$F$7*(1+'Scenario Toggle'!$E$11))/MAX(1,DATEDIF('Project Database'!$D$7,EDATE('Project Database'!$E$7,ROUND('Scenario Toggle'!$E$12,0)),"m")+1)*(1+Assumptions!$E$6/12)^DATEDIF('Project Database'!$D$7,D$3,"m"),0) -> 0 | E23: =IF(AND(E$3>='Project Database'!$D$7,E$3<=EDATE('Project Database'!$E$7,ROUND('Scenario Toggle'!$E$12,0))),('Project Database'!$F$7*(1+'Scenario Toggle'!$E$11))/MAX(1,DATEDIF('Project Database'!$D$7,EDATE('Project Database'!$E$7,ROUND('Scenario Toggle'!$E$12,0)),"m")+1)*(1+Assumptions!$E$6/12)^DATEDIF('Project Database'!$D$7,E$3,"m"),0) -> 0 | F23: =IF(AND(F$3>='Project Database'!$D$7,F$3<=EDATE('Project Database'!$E$7,ROUND('Scenario Toggle'!$E$12,0))),('Project Database'!$F$7*(1+'Scenario Toggle'!$E$11))/MAX(1,DATEDIF('Project Database'!$D$7,EDATE('Project Database'!$E$7,ROUND('Scenario Toggle'!$E$12,0)),"m")+1)*(1+Assumptions!$E$6/12)^DATEDIF('Project Database'!$D$7,F$3,"m"),0) -> 40476190 | G23: =IF(AND(G$3>='Project Database'!$D$7,G$3<=EDATE('Project Database'!$E$7,ROUND('Scenario Toggle'!$E$12,0))),('Project Database'!$F$7*(1+'Scenario Toggle'!$E$11))/MAX(1,DATEDIF('Project Database'!$D$7,EDATE('Project Database'!$E$7,ROUND('Scenario Toggle'!$E$12,0)),"m")+1)*(1+Assumptions!$E$6/12)^DATEDIF('Project Database'!$D$7,G$3,"m"),0) -> 40577381 | H23: =IF(AND(H$3>='Project Database'!$D$7,H$3<=EDATE('Project Database'!$E$7,ROUND('Scenario Toggle'!$E$12,0))),('Project Database'!$F$7*(1+'Scenario Toggle'!$E$11))/MAX(1,DATEDIF('Project Database'!$D$7,EDATE('Project Database'!$E$7,ROUND('Scenario Toggle'!$E$12,0)),"m")+1)*(1+Assumptions!$E$6/12)^DATEDIF('Project Database'!$D$7,H$3,"m"),0) -> 40678824 | I23: =IF(AND(I$3>='Project Database'!$D$7,I$3<=EDATE('Project Database'!$E$7,ROUND('Scenario Toggle'!$E$12,0))),('Project Database'!$F$7*(1+'Scenario Toggle'!$E$11))/MAX(1,DATEDIF('Project Database'!$D$7,EDATE('Project Database'!$E$7,ROUND('Scenario Toggle'!$E$12,0)),"m")+1)*(1+Assumptions!$E$6/12)^DATEDIF('Project Database'!$D$7,I$3,"m"),0) -> 40780521 | J23: =IF(AND(J$3>='Project Database'!$D$7,J$3<=EDATE('Project Database'!$E$7,ROUND('Scenario Toggle'!$E$12,0))),('Project Database'!$F$7*(1+'Scenario Toggle'!$E$11))/MAX(1,DATEDIF('Project Database'!$D$7,EDATE('Project Database'!$E$7,ROUND('Scenario Toggle'!$E$12,0)),"m")+1)*(1+Assumptions!$E$6/12)^DATEDIF('Project Database'!$D$7,J$3,"m"),0) -> 40882473 | K23: =IF(AND(K$3>='Project Database'!$D$7,K$3<=EDATE('Project Database'!$E$7,ROUND('Scenario Toggle'!$E$12,0))),('Project Database'!$F$7*(1+'Scenario Toggle'!$E$11))/MAX(1,DATEDIF('Project Database'!$D$7,EDATE('Project Database'!$E$7,ROUND('Scenario Toggle'!$E$12,0)),"m")+1)*(1+Assumptions!$E$6/12)^DATEDIF('Project Database'!$D$7,K$3,"m"),0) -> 40984679 | ... AA23: =IF(AND(AA$3>='Project Database'!$D$7,AA$3<=EDATE('Project Database'!$E$7,ROUND('Scenario Toggle'!$E$12,0))),('Project Database'!$F$7*(1+'Scenario Toggle'!$E$11))/MAX(1,DATEDIF('Project Database'!$D$7,EDATE('Project Database'!$E$7,ROUND('Scenario Toggle'!$E$12,0)),"m")+1)*(1+Assumptions!$E$6/12)^DATEDIF('Project Database'!$D$7,AA$3,"m"),0) -> 0
B24: Cumulative Spend | D24: =SUM($D23:D23) -> 0 | E24: =SUM($D23:E23) -> 0 | F24: =SUM($D23:F23) -> 40476190 | G24: =SUM($D23:G23) -> 81053571 | H24: =SUM($D23:H23) -> 1.217324e+08 | I24: =SUM($D23:I23) -> 1.6251292e+08 | J24: =SUM($D23:J23) -> 2.0339539e+08 | K24: =SUM($D23:K23) -> 2.4438007e+08 | ... AA24: =SUM($D23:AA23) -> 8.7159028e+08
B25: Remaining Cost | D25: =MAX(0,$C22-D24) -> 850000000 | E25: =MAX(0,$C22-E24) -> 850000000 | F25: =MAX(0,$C22-F24) -> 8.0952381e+08 | G25: =MAX(0,$C22-G24) -> 7.6894643e+08 | H25: =MAX(0,$C22-H24) -> 7.282676e+08 | I25: =MAX(0,$C22-I24) -> 6.8748708e+08 | J25: =MAX(0,$C22-J24) -> 6.4660461e+08 | K25: =MAX(0,$C22-K24) -> 6.0561993e+08 | ... AA25: =MAX(0,$C22-AA24) -> 0
B26: Construction Progress % | D26: =MIN(1,D24/($C22)) -> 0 | E26: =MIN(1,E24/($C22)) -> 0 | F26: =MIN(1,F24/($C22)) -> 0.047619048 | G26: =MIN(1,G24/($C22)) -> 0.095357143 | H26: =MIN(1,H24/($C22)) -> 0.14321458 | I26: =MIN(1,I24/($C22)) -> 0.19119167 | J26: =MIN(1,J24/($C22)) -> 0.23928869 | K26: =MIN(1,K24/($C22)) -> 0.28750596 | ... AA26: =MIN(1,AA24/($C22)) -> 1
B27: Approved Release % | D27: =MIN(0.9,D26) -> 0 | E27: =MIN(0.9,E26) -> 0 | F27: =MIN(0.9,F26) -> 0.047619048 | G27: =MIN(0.9,G26) -> 0.095357143 | H27: =MIN(0.9,H26) -> 0.14321458 | I27: =MIN(0.9,I26) -> 0.19119167 | J27: =MIN(0.9,J26) -> 0.23928869 | K27: =MIN(0.9,K26) -> 0.28750596 | ... AA27: =MIN(0.9,AA26) -> 0.9
A29: Portfolio | B29: Total Monthly Construction Spend | D29: =D5+D11+D17+D23 -> 50000000 | E29: =E5+E11+E17+E23 -> 82625000 | F29: =F5+F11+F17+F23 -> 1.2330775e+08 | G29: =G5+G11+G17+G23 -> 1.7599697e+08 | H29: =H5+H11+H17+H23 -> 1.7643697e+08 | I29: =I5+I11+I17+I23 -> 1.7687806e+08 | J29: =J5+J11+J17+J23 -> 1.7732025e+08 | K29: =K5+K11+K17+K23 -> 1.7776356e+08 | ... AA29: =AA5+AA11+AA17+AA23 -> 55063145
B30: Total Remaining Cost | D30: =D7+D13+D19+D25 -> 3450000000 | E30: =E7+E13+E19+E25 -> 3367375000 | F30: =F7+F13+F19+F25 -> 3.2440672e+09 | G30: =G7+G13+G19+G25 -> 3.0680703e+09 | H30: =H7+H13+H19+H25 -> 2.8916333e+09 | I30: =I7+I13+I19+I25 -> 2.7147552e+09 | J30: =J7+J13+J19+J25 -> 2.537435e+09 | K30: =K7+K13+K19+K25 -> 2.3596714e+09 | ... AA30: =AA7+AA13+AA19+AA25 -> 0

Sheet Escrow
A1: Project Escrow Account Schedule
A3: Project | B3: Metric | C3: Opening | D3: 46113 | E3: 46143 | F3: 46174 | G3: 46204 | H3: 46235 | I3: 46266 | J3: 46296 | K3: 46327 | L3: 46357 | M3: 46388 | N3: 46419 | O3: 46447 | P3: 46478 | Q3: 46508 | R3: 46539 | S3: 46569 | T3: 46600 | U3: 46631 | V3: 46661 | W3: 46692 | X3: 46722 | Y3: 46753 | Z3: 46784 | AA3: 46813
A4: Marina Residences Tower | B4: Opening Balance | C4: ='Project Database'!$J$4 -> 120000000 | D4: =$C4 -> 120000000 | E4: =D7 -> 101485440 | F4: =E7 -> 82971822 | G4: =F7 -> 64459337 | H4: =G7 -> 45948177 | I4: =H7 -> 27438536 | J4: =I7 -> 40290610 | K4: =J7 -> 53270035 | L4: =K7 -> 66377509 | ... AA4: =Z7 -> 1.4962836e+09
B5: Customer Deposits | D5: =Collections!D9 -> 31485440 | E5: =Collections!E9 -> 31611382 | F5: =Collections!F9 -> 31737827 | G5: =Collections!G9 -> 31864779 | H5: =Collections!H9 -> 31992238 | I5: =Collections!I9 -> 63480207 | J5: =Collections!J9 -> 63734127 | K5: =Collections!K9 -> 63989064 | ... AA5: =Collections!AA9 -> 0
B6: Approved Releases | D6: =MIN('Construction Costs'!D5,MAX(0,D4+D5-(SUM(Collections!$C$9:D9)*$C8))) -> 50000000 | E6: =MIN('Construction Costs'!E5,MAX(0,E4+E5-(SUM(Collections!$C$9:E9)*$C8))) -> 50125000 | F6: =MIN('Construction Costs'!F5,MAX(0,F4+F5-(SUM(Collections!$C$9:F9)*$C8))) -> 50250312 | G6: =MIN('Construction Costs'!G5,MAX(0,G4+G5-(SUM(Collections!$C$9:G9)*$C8))) -> 50375938 | H6: =MIN('Construction Costs'!H5,MAX(0,H4+H5-(SUM(Collections!$C$9:H9)*$C8))) -> 50501878 | I6: =MIN('Construction Costs'!I5,MAX(0,I4+I5-(SUM(Collections!$C$9:I9)*$C8))) -> 50628133 | J6: =MIN('Construction Costs'!J5,MAX(0,J4+J5-(SUM(Collections!$C$9:J9)*$C8))) -> 50754703 | K6: =MIN('Construction Costs'!K5,MAX(0,K4+K5-(SUM(Collections!$C$9:K9)*$C8))) -> 50881590 | ... AA6: =MIN('Construction Costs'!AA5,MAX(0,AA4+AA5-(SUM(Collections!$C$9:AA9)*$C8))) -> 0
B7: Closing Balance | D7: =D4+D5-D6 -> 101485440 | E7: =E4+E5-E6 -> 82971822 | F7: =F4+F5-F6 -> 64459337 | G7: =G4+G5-G6 -> 45948177 | H7: =H4+H5-H6 -> 27438536 | I7: =I4+I5-I6 -> 40290610 | J7: =J4+J5-J6 -> 53270035 | K7: =K4+K5-K6 -> 66377509 | ... AA7: =AA4+AA5-AA6 -> 1.4962836e+09
B8: Min Escrow Reserve % | C8: 0.1
A9: Palm Waterfront Villas | B9: Opening Balance | C9: ='Project Database'!$J$5 -> 80000000 | D9: =$C9 -> 80000000 | E9: =D12 -> 100638800 | F9: =E12 -> 88860155 | G9: =F12 -> 77083146 | H9: =G12 -> 65307900 | I9: =H12 -> 53534548 | J9: =I12 -> 41763218 | K9: =J12 -> 50632843 | L9: =K12 -> 59587309 | ... AA9: =Z12 -> 9.6997726e+08
B10: Customer Deposits | D10: =Collections!D16 -> 20638800 | E10: =Collections!E16 -> 20721355 | F10: =Collections!F16 -> 20804241 | G10: =Collections!G16 -> 20887458 | H10: =Collections!H16 -> 20971007 | I10: =Collections!I16 -> 21054891 | J10: =Collections!J16 -> 41777911 | K10: =Collections!K16 -> 41945023 | ... AA10: =Collections!AA16 -> 0
B11: Approved Releases | D11: =MIN('Construction Costs'!D11,MAX(0,D9+D10-(SUM(Collections!$C$16:D16)*$C13))) -> 0 | E11: =MIN('Construction Costs'!E11,MAX(0,E9+E10-(SUM(Collections!$C$16:E16)*$C13))) -> 32500000 | F11: =MIN('Construction Costs'!F11,MAX(0,F9+F10-(SUM(Collections!$C$16:F16)*$C13))) -> 32581250 | G11: =MIN('Construction Costs'!G11,MAX(0,G9+G10-(SUM(Collections!$C$16:G16)*$C13))) -> 32662703 | H11: =MIN('Construction Costs'!H11,MAX(0,H9+H10-(SUM(Collections!$C$16:H16)*$C13))) -> 32744360 | I11: =MIN('Construction Costs'!I11,MAX(0,I9+I10-(SUM(Collections!$C$16:I16)*$C13))) -> 32826221 | J11: =MIN('Construction Costs'!J11,MAX(0,J9+J10-(SUM(Collections!$C$16:J16)*$C13))) -> 32908286 | K11: =MIN('Construction Costs'!K11,MAX(0,K9+K10-(SUM(Collections!$C$16:K16)*$C13))) -> 32990557 | ... AA11: =MIN('Construction Costs'!AA11,MAX(0,AA9+AA10-(SUM(Collections!$C$16:AA16)*$C13))) -> 0
B12: Closing Balance | D12: =D9+D10-D11 -> 100638800 | E12: =E9+E10-E11 -> 88860155 | F12: =F9+F10-F11 -> 77083146 | G12: =G9+G10-G11 -> 65307900 | H12: =H9+H10-H11 -> 53534548 | I12: =I9+I10-I11 -> 41763218 | J12: =J9+J10-J11 -> 50632843 | K12: =K9+K10-K11 -> 59587309 | ... AA12: =AA9+AA10-AA11 -> 9.6997726e+08
B13: Min Escrow Reserve % | C13: 0.1
A14: Downtown Branded Residences | B14: Opening Balance | C14: ='Project Database'!$J$6 -> 150000000 | D14: =$C14 -> 150000000 | E14: =D17 -> 150000000 | F14: =E17 -> 150000000 | G14: =F17 -> 173872800 | H14: =G17 -> 1.4546014e+08 | I14: =H17 -> 1.170124e+08 | J14: =I17 -> 88529635 | K14: =J17 -> 60011905 | L14: =K17 -> 31459267 | ... AA14: =Z17 -> 8.1910942e+08
B15: Customer Deposits | D15: =Collections!D23 -> 0 | E15: =Collections!E23 -> 0 | F15: =Collections!F23 -> 23872800 | G15: =Collections!G23 -> 23968291 | H15: =Collections!H23 -> 24064164 | I15: =Collections!I23 -> 24160421 | J15: =Collections!J23 -> 24257063 | K15: =Collections!K23 -> 24354091 | ... AA15: =Collections!AA23 -> 0
B16: Approved Releases | D16: =MIN('Construction Costs'!D17,MAX(0,D14+D15-(SUM(Collections!$C$23:D23)*$C18))) -> 0 | E16: =MIN('Construction Costs'!E17,MAX(0,E14+E15-(SUM(Collections!$C$23:E23)*$C18))) -> 0 | F16: =MIN('Construction Costs'!F17,MAX(0,F14+F15-(SUM(Collections!$C$23:F23)*$C18))) -> 0 | G16: =MIN('Construction Costs'!G17,MAX(0,G14+G15-(SUM(Collections!$C$23:G23)*$C18))) -> 52380952 | H16: =MIN('Construction Costs'!H17,MAX(0,H14+H15-(SUM(Collections!$C$23:H23)*$C18))) -> 52511905 | I16: =MIN('Construction Costs'!I17,MAX(0,I14+I15-(SUM(Collections!$C$23:I23)*$C18))) -> 52643185 | J16: =MIN('Construction Costs'!J17,MAX(0,J14+J15-(SUM(Collections!$C$23:J23)*$C18))) -> 52774792 | K16: =MIN('Construction Costs'!K17,MAX(0,K14+K15-(SUM(Collections!$C$23:K23)*$C18))) -> 52906729 | ... AA16: =MIN('Construction Costs'!AA17,MAX(0,AA14+AA15-(SUM(Collections!$C$23:AA23)*$C18))) -> 55063145
B17: Closing Balance | D17: =D14+D15-D16 -> 150000000 | E17: =E14+E15-E16 -> 150000000 | F17: =F14+F15-F16 -> 173872800 | G17: =G14+G15-G16 -> 1.4546014e+08 | H17: =H14+H15-H16 -> 1.170124e+08 | I17: =I14+I15-I16 -> 88529635 | J17: =J14+J15-J16 -> 60011905 | K17: =K14+K15-K16 -> 31459267 | ... AA17: =AA14+AA15-AA16 -> 7.6404627e+08
B18: Min Escrow Reserve % | C18: 0.1
A19: Jumeirah Mixed-Use Development | B19: Opening Balance | C19: ='Project Database'!$J$7 -> 100000000 | D19: =$C19 -> 100000000 | E19: =D22 -> 100000000 | F19: =E22 -> 113912080 | G19: =F22 -> 87403618 | H19: =G22 -> 60849836 | I19: =H22 -> 34250705 | J19: =I22 -> 7606196.3 | K19: =J22 -> 8431167 | L19: =K22 -> 11247308 | ... AA19: =Z22 -> 3.8498789e+08
B20: Customer Deposits | D20: =Collections!D30 -> 0 | E20: =Collections!E30 -> 13912080 | F20: =Collections!F30 -> 13967728 | G20: =Collections!G30 -> 14023599 | H20: =Collections!H30 -> 14079694 | I20: =Collections!I30 -> 14136012 | J20: =Collections!J30 -> 14192556 | K20: =Collections!K30 -> 28161407 | ... AA20: =Collections!AA30 -> 0
B21: Approved Releases | D21: =MIN('Construction Costs'!D23,MAX(0,D19+D20-(SUM(Collections!$C$30:D30)*$C23))) -> 0 | E21: =MIN('Construction Costs'!E23,MAX(0,E19+E20-(SUM(Collections!$C$30:E30)*$C23))) -> 0 | F21: =MIN('Construction Costs'!F23,MAX(0,F19+F20-(SUM(Collections!$C$30:F30)*$C23))) -> 40476190 | G21: =MIN('Construction Costs'!G23,MAX(0,G19+G20-(SUM(Collections!$C$30:G30)*$C23))) -> 40577381 | H21: =MIN('Construction Costs'!H23,MAX(0,H19+H20-(SUM(Collections!$C$30:H30)*$C23))) -> 40678824 | I21: =MIN('Construction Costs'!I23,MAX(0,I19+I20-(SUM(Collections!$C$30:I30)*$C23))) -> 40780521 | J21: =MIN('Construction Costs'!J23,MAX(0,J19+J20-(SUM(Collections!$C$30:J30)*$C23))) -> 13367586 | K21: =MIN('Construction Costs'!K23,MAX(0,K19+K20-(SUM(Collections!$C$30:K30)*$C23))) -> 25345266 | ... AA21: =MIN('Construction Costs'!AA23,MAX(0,AA19+AA20-(SUM(Collections!$C$30:AA30)*$C23))) -> 0
B22: Closing Balance | D22: =D19+D20-D21 -> 100000000 | E22: =E19+E20-E21 -> 113912080 | F22: =F19+F20-F21 -> 87403618 | G22: =G19+G20-G21 -> 60849836 | H22: =H19+H20-H21 -> 34250705 | I22: =I19+I20-I21 -> 7606196.3 | J22: =J19+J20-J21 -> 8431167 | K22: =K19+K20-K21 -> 11247308 | ... AA22: =AA19+AA20-AA21 -> 3.8498789e+08
B23: Min Escrow Reserve % | C23: 0.1

Sheet Corporate Opex
A1: Corporate Operating Expense Schedule
B3: 46113 | C3: 46143 | D3: 46174 | E3: 46204 | F3: 46235 | G3: 46266 | H3: 46296 | I3: 46327 | J3: 46357 | K3: 46388 | L3: 46419 | M3: 46447 | N3: 46478 | O3: 46508 | P3: 46539 | Q3: 46569 | R3: 46600 | S3: 46631 | T3: 46661 | U3: 46692 | V3: 46722 | W3: 46753 | X3: 46784 | Y3: 46813
A5: Monthly Corporate Cost Schedule
A6: Executive salaries | B6: =Assumptions!$E$30*(1+Assumptions!$E$38/12)^(COLUMN()-2) -> 450000 | C6: =Assumptions!$E$30*(1+Assumptions!$E$38/12)^(COLUMN()-2) -> 450000 | D6: =Assumptions!$E$30*(1+Assumptions!$E$38/12)^(COLUMN()-2) -> 450000 | E6: =Assumptions!$E$30*(1+Assumptions!$E$38/12)^(COLUMN()-2) -> 450000 | F6: =Assumptions!$E$30*(1+Assumptions!$E$38/12)^(COLUMN()-2) -> 450000 | G6: =Assumptions!$E$30*(1+Assumptions!$E$38/12)^(COLUMN()-2) -> 450000 | H6: =Assumptions!$E$30*(1+Assumptions!$E$38/12)^(COLUMN()-2) -> 450000 | I6: =Assumptions!$E$30*(1+Assumptions!$E$38/12)^(COLUMN()-2) -> 450000 | ... Y6: =Assumptions!$E$30*(1+Assumptions!$E$38/12)^(COLUMN()-2) -> 450000
A7: Employee payroll | B7: =Assumptions!$E$31*(1+Assumptions!$E$37/12)^(COLUMN()-2) -> 750000 | C7: =Assumptions!$E$31*(1+Assumptions!$E$37/12)^(COLUMN()-2) -> 750000 | D7: =Assumptions!$E$31*(1+Assumptions!$E$37/12)^(COLUMN()-2) -> 750000 | E7: =Assumptions!$E$31*(1+Assumptions!$E$37/12)^(COLUMN()-2) -> 750000 | F7: =Assumptions!$E$31*(1+Assumptions!$E$37/12)^(COLUMN()-2) -> 750000 | G7: =Assumptions!$E$31*(1+Assumptions!$E$37/12)^(COLUMN()-2) -> 750000 | H7: =Assumptions!$E$31*(1+Assumptions!$E$37/12)^(COLUMN()-2) -> 750000 | I7: =Assumptions!$E$31*(1+Assumptions!$E$37/12)^(COLUMN()-2) -> 750000 | ... Y7: =Assumptions!$E$31*(1+Assumptions!$E$37/12)^(COLUMN()-2) -> 750000
A8: Office rent | B8: =Assumptions!$E$32*(1+Assumptions!$E$38/12)^(COLUMN()-2) -> 0.05 | C8: =Assumptions!$E$32*(1+Assumptions!$E$38/12)^(COLUMN()-2) -> 0.05 | D8: =Assumptions!$E$32*(1+Assumptions!$E$38/12)^(COLUMN()-2) -> 0.05 | E8: =Assumptions!$E$32*(1+Assumptions!$E$38/12)^(COLUMN()-2) -> 0.05 | F8: =Assumptions!$E$32*(1+Assumptions!$E$38/12)^(COLUMN()-2) -> 0.05 | G8: =Assumptions!$E$32*(1+Assumptions!$E$38/12)^(COLUMN()-2) -> 0.05 | H8: =Assumptions!$E$32*(1+Assumptions!$E$38/12)^(COLUMN()-2) -> 0.05 | I8: =Assumptions!$E$32*(1+Assumptions!$E$38/12)^(COLUMN()-2) -> 0.05 | ... Y8: =Assumptions!$E$32*(1+Assumptions!$E$38/12)^(COLUMN()-2) -> 0.05
A9: Insurance | B9: =Assumptions!$E$33*(1+Assumptions!$E$38/12)^(COLUMN()-2) -> 0.03 | C9: =Assumptions!$E$33*(1+Assumptions!$E$38/12)^(COLUMN()-2) -> 0.03 | D9: =Assumptions!$E$33*(1+Assumptions!$E$38/12)^(COLUMN()-2) -> 0.03 | E9: =Assumptions!$E$33*(1+Assumptions!$E$38/12)^(COLUMN()-2) -> 0.03 | F9: =Assumptions!$E$33*(1+Assumptions!$E$38/12)^(COLUMN()-2) -> 0.03 | G9: =Assumptions!$E$33*(1+Assumptions!$E$38/12)^(COLUMN()-2) -> 0.03 | H9: =Assumptions!$E$33*(1+Assumptions!$E$38/12)^(COLUMN()-2) -> 0.03 | I9: =Assumptions!$E$33*(1+Assumptions!$E$38/12)^(COLUMN()-2) -> 0.03 | ... Y9: =Assumptions!$E$33*(1+Assumptions!$E$38/12)^(COLUMN()-2) -> 0.03
A10: Legal & professional fees | B10: =Assumptions!$E$34*(1+Assumptions!$E$38/12)^(COLUMN()-2) -> 0 | C10: =Assumptions!$E$34*(1+Assumptions!$E$38/12)^(COLUMN()-2) -> 0 | D10: =Assumptions!$E$34*(1+Assumptions!$E$38/12)^(COLUMN()-2) -> 0 | E10: =Assumptions!$E$34*(1+Assumptions!$E$38/12)^(COLUMN()-2) -> 0 | F10: =Assumptions!$E$34*(1+Assumptions!$E$38/12)^(COLUMN()-2) -> 0 | G10: =Assumptions!$E$34*(1+Assumptions!$E$38/12)^(COLUMN()-2) -> 0 | H10: =Assumptions!$E$34*(1+Assumptions!$E$38/12)^(COLUMN()-2) -> 0 | I10: =Assumptions!$E$34*(1+Assumptions!$E$38/12)^(COLUMN()-2) -> 0 | ... Y10: =Assumptions!$E$34*(1+Assumptions!$E$38/12)^(COLUMN()-2) -> 0
A11: IT costs | B11: =Assumptions!$E$35*(1+Assumptions!$E$38/12)^(COLUMN()-2) -> 0 | C11: =Assumptions!$E$35*(1+Assumptions!$E$38/12)^(COLUMN()-2) -> 0 | D11: =Assumptions!$E$35*(1+Assumptions!$E$38/12)^(COLUMN()-2) -> 0 | E11: =Assumptions!$E$35*(1+Assumptions!$E$38/12)^(COLUMN()-2) -> 0 | F11: =Assumptions!$E$35*(1+Assumptions!$E$38/12)^(COLUMN()-2) -> 0 | G11: =Assumptions!$E$35*(1+Assumptions!$E$38/12)^(COLUMN()-2) -> 0 | H11: =Assumptions!$E$35*(1+Assumptions!$E$38/12)^(COLUMN()-2) -> 0 | I11: =Assumptions!$E$35*(1+Assumptions!$E$38/12)^(COLUMN()-2) -> 0 | ... Y11: =Assumptions!$E$35*(1+Assumptions!$E$38/12)^(COLUMN()-2) -> 0
A12: General admin | B12: =Assumptions!$E$36*(1+Assumptions!$E$38/12)^(COLUMN()-2) -> 0 | C12: =Assumptions!$E$36*(1+Assumptions!$E$38/12)^(COLUMN()-2) -> 0 | D12: =Assumptions!$E$36*(1+Assumptions!$E$38/12)^(COLUMN()-2) -> 0 | E12: =Assumptions!$E$36*(1+Assumptions!$E$38/12)^(COLUMN()-2) -> 0 | F12: =Assumptions!$E$36*(1+Assumptions!$E$38/12)^(COLUMN()-2) -> 0 | G12: =Assumptions!$E$36*(1+Assumptions!$E$38/12)^(COLUMN()-2) -> 0 | H12: =Assumptions!$E$36*(1+Assumptions!$E$38/12)^(COLUMN()-2) -> 0 | I12: =Assumptions!$E$36*(1+Assumptions!$E$38/12)^(COLUMN()-2) -> 0 | ... Y12: =Assumptions!$E$36*(1+Assumptions!$E$38/12)^(COLUMN()-2) -> 0
A13: Total Corporate Opex | B13: =SUM(B6:B12) -> 1200000.1 | C13: =SUM(C6:C12) -> 1200000.1 | D13: =SUM(D6:D12) -> 1200000.1 | E13: =SUM(E6:E12) -> 1200000.1 | F13: =SUM(F6:F12) -> 1200000.1 | G13: =SUM(G6:G12) -> 1200000.1 | H13: =SUM(H6:H12) -> 1200000.1 | I13: =SUM(I6:I12) -> 1200000.1 | ... Y13: =SUM(Y6:Y12) -> 1200000.1

Sheet Debt Model
A1: Debt and Financing Schedule
A3: Project | B3: Metric | C3: Opening / Rate | D3: 46113 | E3: 46143 | F3: 46174 | G3: 46204 | H3: 46235 | I3: 46266 | J3: 46296 | K3: 46327 | L3: 46357 | M3: 46388 | N3: 46419 | O3: 46447 | P3: 46478 | Q3: 46508 | R3: 46539 | S3: 46569 | T3: 46600 | U3: 46631 | V3: 46661 | W3: 46692 | X3: 46722 | Y3: 46753 | Z3: 46784 | AA3: 46813
A4: Marina Residences Tower | B4: Opening Balance | C4: ='Project Database'!$K$4 -> 220000000 | D4: =$C4 -> 220000000 | E4: =D10 -> 220000000 | F4: =E10 -> 220000000 | G4: =F10 -> 220000000 | H4: =G10 -> 220000000 | I4: =H10 -> 220000000 | J4: =I10 -> 220000000 | K4: =J10 -> 220000000 | L4: =K10 -> 220000000 | ... AA4: =Z10 -> 1.4239013e+08
B5: Drawdowns | D5: =MAX(0,'Construction Costs'!D5-Escrow!D6) -> 0 | E5: =MAX(0,'Construction Costs'!E5-Escrow!E6) -> 0 | F5: =MAX(0,'Construction Costs'!F5-Escrow!F6) -> 0 | G5: =MAX(0,'Construction Costs'!G5-Escrow!G6) -> 0 | H5: =MAX(0,'Construction Costs'!H5-Escrow!H6) -> 0 | I5: =MAX(0,'Construction Costs'!I5-Escrow!I6) -> 0 | J5: =MAX(0,'Construction Costs'!J5-Escrow!J6) -> 0 | K5: =MAX(0,'Construction Costs'!K5-Escrow!K6) -> 0 | ... AA5: =MAX(0,'Construction Costs'!AA5-Escrow!AA6) -> 0
B6: Interest Rate | C6: =Assumptions!$E$7+'Scenario Toggle'!$E$13 -> 0.065 | D6: =$C6 -> 0.065 | E6: =$C6 -> 0.065 | F6: =$C6 -> 0.065 | G6: =$C6 -> 0.065 | H6: =$C6 -> 0.065 | I6: =$C6 -> 0.065 | J6: =$C6 -> 0.065 | K6: =$C6 -> 0.065 | ... AA6: =$C6 -> 0.065
B7: Interest Accrued | D7: =D4*D6/12 -> 1191666.7 | E7: =E4*E6/12 -> 1191666.7 | F7: =F4*F6/12 -> 1191666.7 | G7: =G4*G6/12 -> 1191666.7 | H7: =H4*H6/12 -> 1191666.7 | I7: =I4*I6/12 -> 1191666.7 | J7: =J4*J6/12 -> 1191666.7 | K7: =K4*K6/12 -> 1191666.7 | ... AA7: =AA4*AA6/12 -> 771279.85
B8: Interest Paid | D8: =D7 -> 1191666.7 | E8: =E7 -> 1191666.7 | F8: =F7 -> 1191666.7 | G8: =G7 -> 1191666.7 | H8: =H7 -> 1191666.7 | I8: =I7 -> 1191666.7 | J8: =J7 -> 1191666.7 | K8: =K7 -> 1191666.7 | ... AA8: =AA7 -> 771279.85
B9: Principal Repayment | D9: =IF(D$3>EDATE('Project Database'!$E$4,ROUND('Scenario Toggle'!$E$12,0)),MIN((D4+D5)/12,D4+D5),0) -> 0 | E9: =IF(E$3>EDATE('Project Database'!$E$4,ROUND('Scenario Toggle'!$E$12,0)),MIN((E4+E5)/12,E4+E5),0) -> 0 | F9: =IF(F$3>EDATE('Project Database'!$E$4,ROUND('Scenario Toggle'!$E$12,0)),MIN((F4+F5)/12,F4+F5),0) -> 0 | G9: =IF(G$3>EDATE('Project Database'!$E$4,ROUND('Scenario Toggle'!$E$12,0)),MIN((G4+G5)/12,G4+G5),0) -> 0 | H9: =IF(H$3>EDATE('Project Database'!$E$4,ROUND('Scenario Toggle'!$E$12,0)),MIN((H4+H5)/12,H4+H5),0) -> 0 | I9: =IF(I$3>EDATE('Project Database'!$E$4,ROUND('Scenario Toggle'!$E$12,0)),MIN((I4+I5)/12,I4+I5),0) -> 0 | J9: =IF(J$3>EDATE('Project Database'!$E$4,ROUND('Scenario Toggle'!$E$12,0)),MIN((J4+J5)/12,J4+J5),0) -> 0 | K9: =IF(K$3>EDATE('Project Database'!$E$4,ROUND('Scenario Toggle'!$E$12,0)),MIN((K4+K5)/12,K4+K5),0) -> 0 | ... AA9: =IF(AA$3>EDATE('Project Database'!$E$4,ROUND('Scenario Toggle'!$E$12,0)),MIN((AA4+AA5)/12,AA4+AA5),0) -> 11865844
B10: Closing Balance | D10: =MAX(0,D4+D5+D7-D8-D9) -> 220000000 | E10: =MAX(0,E4+E5+E7-E8-E9) -> 220000000 | F10: =MAX(0,F4+F5+F7-F8-F9) -> 220000000 | G10: =MAX(0,G4+G5+G7-G8-G9) -> 220000000 | H10: =MAX(0,H4+H5+H7-H8-H9) -> 220000000 | I10: =MAX(0,I4+I5+I7-I8-I9) -> 220000000 | J10: =MAX(0,J4+J5+J7-J8-J9) -> 220000000 | K10: =MAX(0,K4+K5+K7-K8-K9) -> 220000000 | ... AA10: =MAX(0,AA4+AA5+AA7-AA8-AA9) -> 1.3052428e+08
A11: Palm Waterfront Villas | B11: Opening Balance | C11: ='Project Database'!$K$5 -> 140000000 | D11: =$C11 -> 140000000 | E11: =D17 -> 140000000 | F11: =E17 -> 140000000 | G11: =F17 -> 140000000 | H11: =G17 -> 140000000 | I11: =H17 -> 140000000 | J11: =I17 -> 140000000 | K11: =J17 -> 140000000 | L11: =K17 -> 140000000 | ... AA11: =Z17 -> 1.1763889e+08
B12: Drawdowns | D12: =MAX(0,'Construction Costs'!D11-Escrow!D11) -> 0 | E12: =MAX(0,'Construction Costs'!E11-Escrow!E11) -> 0 | F12: =MAX(0,'Construction Costs'!F11-Escrow!F11) -> 0 | G12: =MAX(0,'Construction Costs'!G11-Escrow!G11) -> 0 | H12: =MAX(0,'Construction Costs'!H11-Escrow!H11) -> 0 | I12: =MAX(0,'Construction Costs'!I11-Escrow!I11) -> 0 | J12: =MAX(0,'Construction Costs'!J11-Escrow!J11) -> 0 | K12: =MAX(0,'Construction Costs'!K11-Escrow!K11) -> 0 | ... AA12: =MAX(0,'Construction Costs'!AA11-Escrow!AA11) -> 0
B13: Interest Rate | C13: =Assumptions!$E$7+'Scenario Toggle'!$E$13 -> 0.065 | D13: =$C13 -> 0.065 | E13: =$C13 -> 0.065 | F13: =$C13 -> 0.065 | G13: =$C13 -> 0.065 | H13: =$C13 -> 0.065 | I13: =$C13 -> 0.065 | J13: =$C13 -> 0.065 | K13: =$C13 -> 0.065 | ... AA13: =$C13 -> 0.065
B14: Interest Accrued | D14: =D11*D13/12 -> 758333.33 | E14: =E11*E13/12 -> 758333.33 | F14: =F11*F13/12 -> 758333.33 | G14: =G11*G13/12 -> 758333.33 | H14: =H11*H13/12 -> 758333.33 | I14: =I11*I13/12 -> 758333.33 | J14: =J11*J13/12 -> 758333.33 | K14: =K11*K13/12 -> 758333.33 | ... AA14: =AA11*AA13/12 -> 637210.65
B15: Interest Paid | D15: =D14 -> 758333.33 | E15: =E14 -> 758333.33 | F15: =F14 -> 758333.33 | G15: =G14 -> 758333.33 | H15: =H14 -> 758333.33 | I15: =I14 -> 758333.33 | J15: =J14 -> 758333.33 | K15: =K14 -> 758333.33 | ... AA15: =AA14 -> 637210.65
B16: Principal Repayment | D16: =IF(D$3>EDATE('Project Database'!$E$5,ROUND('Scenario Toggle'!$E$12,0)),MIN((D11+D12)/12,D11+D12),0) -> 0 | E16: =IF(E$3>EDATE('Project Database'!$E$5,ROUND('Scenario Toggle'!$E$12,0)),MIN((E11+E12)/12,E11+E12),0) -> 0 | F16: =IF(F$3>EDATE('Project Database'!$E$5,ROUND('Scenario Toggle'!$E$12,0)),MIN((F11+F12)/12,F11+F12),0) -> 0 | G16: =IF(G$3>EDATE('Project Database'!$E$5,ROUND('Scenario Toggle'!$E$12,0)),MIN((G11+G12)/12,G11+G12),0) -> 0 | H16: =IF(H$3>EDATE('Project Database'!$E$5,ROUND('Scenario Toggle'!$E$12,0)),MIN((H11+H12)/12,H11+H12),0) -> 0 | I16: =IF(I$3>EDATE('Project Database'!$E$5,ROUND('Scenario Toggle'!$E$12,0)),MIN((I11+I12)/12,I11+I12),0) -> 0 | J16: =IF(J$3>EDATE('Project Database'!$E$5,ROUND('Scenario Toggle'!$E$12,0)),MIN((J11+J12)/12,J11+J12),0) -> 0 | K16: =IF(K$3>EDATE('Project Database'!$E$5,ROUND('Scenario Toggle'!$E$12,0)),MIN((K11+K12)/12,K11+K12),0) -> 0 | ... AA16: =IF(AA$3>EDATE('Project Database'!$E$5,ROUND('Scenario Toggle'!$E$12,0)),MIN((AA11+AA12)/12,AA11+AA12),0) -> 9803240.7
B17: Closing Balance | D17: =MAX(0,D11+D12+D14-D15-D16) -> 140000000 | E17: =MAX(0,E11+E12+E14-E15-E16) -> 140000000 | F17: =MAX(0,F11+F12+F14-F15-F16) -> 140000000 | G17: =MAX(0,G11+G12+G14-G15-G16) -> 140000000 | H17: =MAX(0,H11+H12+H14-H15-H16) -> 140000000 | I17: =MAX(0,I11+I12+I14-I15-I16) -> 140000000 | J17: =MAX(0,J11+J12+J14-J15-J16) -> 140000000 | K17: =MAX(0,K11+K12+K14-K15-K16) -> 140000000 | ... AA17: =MAX(0,AA11+AA12+AA14-AA15-AA16) -> 1.0783565e+08
A18: Downtown Branded Residences | B18: Opening Balance | C18: ='Project Database'!$K$6 -> 260000000 | D18: =$C18 -> 260000000 | E18: =D24 -> 260000000 | F18: =E24 -> 260000000 | G18: =F24 -> 260000000 | H18: =G24 -> 260000000 | I18: =H24 -> 260000000 | J18: =I24 -> 260000000 | K18: =J24 -> 260000000 | L18: =K24 -> 260000000 | ... AA18: =Z24 -> 2.9966327e+08
B19: Drawdowns | D19: =MAX(0,'Construction Costs'!D17-Escrow!D16) -> 0 | E19: =MAX(0,'Construction Costs'!E17-Escrow!E16) -> 0 | F19: =MAX(0,'Construction Costs'!F17-Escrow!F16) -> 0 | G19: =MAX(0,'Construction Costs'!G17-Escrow!G16) -> 0 | H19: =MAX(0,'Construction Costs'!H17-Escrow!H16) -> 0 | I19: =MAX(0,'Construction Costs'!I17-Escrow!I16) -> 0 | J19: =MAX(0,'Construction Costs'!J17-Escrow!J16) -> 0 | K19: =MAX(0,'Construction Costs'!K17-Escrow!K16) -> 0 | ... AA19: =MAX(0,'Construction Costs'!AA17-Escrow!AA16) -> 0
B20: Interest Rate | C20: =Assumptions!$E$7+'Scenario Toggle'!$E$13 -> 0.065 | D20: =$C20 -> 0.065 | E20: =$C20 -> 0.065 | F20: =$C20 -> 0.065 | G20: =$C20 -> 0.065 | H20: =$C20 -> 0.065 | I20: =$C20 -> 0.065 | J20: =$C20 -> 0.065 | K20: =$C20 -> 0.065 | ... AA20: =$C20 -> 0.065
B21: Interest Accrued | D21: =D18*D20/12 -> 1408333.3 | E21: =E18*E20/12 -> 1408333.3 | F21: =F18*F20/12 -> 1408333.3 | G21: =G18*G20/12 -> 1408333.3 | H21: =H18*H20/12 -> 1408333.3 | I21: =I18*I20/12 -> 1408333.3 | J21: =J18*J20/12 -> 1408333.3 | K21: =K18*K20/12 -> 1408333.3 | ... AA21: =AA18*AA20/12 -> 1623176
B22: Interest Paid | D22: =D21 -> 1408333.3 | E22: =E21 -> 1408333.3 | F22: =F21 -> 1408333.3 | G22: =G21 -> 1408333.3 | H22: =H21 -> 1408333.3 | I22: =I21 -> 1408333.3 | J22: =J21 -> 1408333.3 | K22: =K21 -> 1408333.3 | ... AA22: =AA21 -> 1623176
B23: Principal Repayment | D23: =IF(D$3>EDATE('Project Database'!$E$6,ROUND('Scenario Toggle'!$E$12,0)),MIN((D18+D19)/12,D18+D19),0) -> 0 | E23: =IF(E$3>EDATE('Project Database'!$E$6,ROUND('Scenario Toggle'!$E$12,0)),MIN((E18+E19)/12,E18+E19),0) -> 0 | F23: =IF(F$3>EDATE('Project Database'!$E$6,ROUND('Scenario Toggle'!$E$12,0)),MIN((F18+F19)/12,F18+F19),0) -> 0 | G23: =IF(G$3>EDATE('Project Database'!$E$6,ROUND('Scenario Toggle'!$E$12,0)),MIN((G18+G19)/12,G18+G19),0) -> 0 | H23: =IF(H$3>EDATE('Project Database'!$E$6,ROUND('Scenario Toggle'!$E$12,0)),MIN((H18+H19)/12,H18+H19),0) -> 0 | I23: =IF(I$3>EDATE('Project Database'!$E$6,ROUND('Scenario Toggle'!$E$12,0)),MIN((I18+I19)/12,I18+I19),0) -> 0 | J23: =IF(J$3>EDATE('Project Database'!$E$6,ROUND('Scenario Toggle'!$E$12,0)),MIN((J18+J19)/12,J18+J19),0) -> 0 | K23: =IF(K$3>EDATE('Project Database'!$E$6,ROUND('Scenario Toggle'!$E$12,0)),MIN((K18+K19)/12,K18+K19),0) -> 0 | ... AA23: =IF(AA$3>EDATE('Project Database'!$E$6,ROUND('Scenario Toggle'!$E$12,0)),MIN((AA18+AA19)/12,AA18+AA19),0) -> 0
B24: Closing Balance | D24: =MAX(0,D18+D19+D21-D22-D23) -> 260000000 | E24: =MAX(0,E18+E19+E21-E22-E23) -> 260000000 | F24: =MAX(0,F18+F19+F21-F22-F23) -> 260000000 | G24: =MAX(0,G18+G19+G21-G22-G23) -> 260000000 | H24: =MAX(0,H18+H19+H21-H22-H23) -> 260000000 | I24: =MAX(0,I18+I19+I21-I22-I23) -> 260000000 | J24: =MAX(0,J18+J19+J21-J22-J23) -> 260000000 | K24: =MAX(0,K18+K19+K21-K22-K23) -> 260000000 | ... AA24: =MAX(0,AA18+AA19+AA21-AA22-AA23) -> 2.9966327e+08
A25: Jumeirah Mixed-Use Development | B25: Opening Balance | C25: ='Project Database'!$K$7 -> 180000000 | D25: =$C25 -> 180000000 | E25: =D31 -> 180000000 | F25: =E31 -> 180000000 | G25: =F31 -> 180000000 | H25: =G31 -> 180000000 | I25: =H31 -> 180000000 | J25: =I31 -> 180000000 | K25: =J31 -> 2.0751489e+08 | L25: =K31 -> 2.231543e+08 | ... AA25: =Z31 -> 3.1934531e+08
B26: Drawdowns | D26: =MAX(0,'Construction Costs'!D23-Escrow!D21) -> 0 | E26: =MAX(0,'Construction Costs'!E23-Escrow!E21) -> 0 | F26: =MAX(0,'Construction Costs'!F23-Escrow!F21) -> 0 | G26: =MAX(0,'Construction Costs'!G23-Escrow!G21) -> 0 | H26: =MAX(0,'Construction Costs'!H23-Escrow!H21) -> 0 | I26: =MAX(0,'Construction Costs'!I23-Escrow!I21) -> 0 | J26: =MAX(0,'Construction Costs'!J23-Escrow!J21) -> 27514887 | K26: =MAX(0,'Construction Costs'!K23-Escrow!K21) -> 15639413 | ... AA26: =MAX(0,'Construction Costs'!AA23-Escrow!AA21) -> 0
B27: Interest Rate | C27: =Assumptions!$E$7+'Scenario Toggle'!$E$13 -> 0.065 | D27: =$C27 -> 0.065 | E27: =$C27 -> 0.065 | F27: =$C27 -> 0.065 | G27: =$C27 -> 0.065 | H27: =$C27 -> 0.065 | I27: =$C27 -> 0.065 | J27: =$C27 -> 0.065 | K27: =$C27 -> 0.065 | ... AA27: =$C27 -> 0.065
B28: Interest Accrued | D28: =D25*D27/12 -> 975000 | E28: =E25*E27/12 -> 975000 | F28: =F25*F27/12 -> 975000 | G28: =G25*G27/12 -> 975000 | H28: =H25*H27/12 -> 975000 | I28: =I25*I27/12 -> 975000 | J28: =J25*J27/12 -> 975000 | K28: =K25*K27/12 -> 1124039 | ... AA28: =AA25*AA27/12 -> 1729787.1
B29: Interest Paid | D29: =D28 -> 975000 | E29: =E28 -> 975000 | F29: =F28 -> 975000 | G29: =G28 -> 975000 | H29: =H28 -> 975000 | I29: =I28 -> 975000 | J29: =J28 -> 975000 | K29: =K28 -> 1124039 | ... AA29: =AA28 -> 1729787.1
B30: Principal Repayment | D30: =IF(D$3>EDATE('Project Database'!$E$7,ROUND('Scenario Toggle'!$E$12,0)),MIN((D25+D26)/12,D25+D26),0) -> 0 | E30: =IF(E$3>EDATE('Project Database'!$E$7,ROUND('Scenario Toggle'!$E$12,0)),MIN((E25+E26)/12,E25+E26),0) -> 0 | F30: =IF(F$3>EDATE('Project Database'!$E$7,ROUND('Scenario Toggle'!$E$12,0)),MIN((F25+F26)/12,F25+F26),0) -> 0 | G30: =IF(G$3>EDATE('Project Database'!$E$7,ROUND('Scenario Toggle'!$E$12,0)),MIN((G25+G26)/12,G25+G26),0) -> 0 | H30: =IF(H$3>EDATE('Project Database'!$E$7,ROUND('Scenario Toggle'!$E$12,0)),MIN((H25+H26)/12,H25+H26),0) -> 0 | I30: =IF(I$3>EDATE('Project Database'!$E$7,ROUND('Scenario Toggle'!$E$12,0)),MIN((I25+I26)/12,I25+I26),0) -> 0 | J30: =IF(J$3>EDATE('Project Database'!$E$7,ROUND('Scenario Toggle'!$E$12,0)),MIN((J25+J26)/12,J25+J26),0) -> 0 | K30: =IF(K$3>EDATE('Project Database'!$E$7,ROUND('Scenario Toggle'!$E$12,0)),MIN((K25+K26)/12,K25+K26),0) -> 0 | ... AA30: =IF(AA$3>EDATE('Project Database'!$E$7,ROUND('Scenario Toggle'!$E$12,0)),MIN((AA25+AA26)/12,AA25+AA26),0) -> 26612109
B31: Closing Balance | D31: =MAX(0,D25+D26+D28-D29-D30) -> 180000000 | E31: =MAX(0,E25+E26+E28-E29-E30) -> 180000000 | F31: =MAX(0,F25+F26+F28-F29-F30) -> 180000000 | G31: =MAX(0,G25+G26+G28-G29-G30) -> 180000000 | H31: =MAX(0,H25+H26+H28-H29-H30) -> 180000000 | I31: =MAX(0,I25+I26+I28-I29-I30) -> 180000000 | J31: =MAX(0,J25+J26+J28-J29-J30) -> 2.0751489e+08 | K31: =MAX(0,K25+K26+K28-K29-K30) -> 2.231543e+08 | ... AA31: =MAX(0,AA25+AA26+AA28-AA29-AA30) -> 2.927332e+08
A33: Corporate Revolver | B33: Opening Balance | C33: 0 | D33: =$C33 -> 0 | E33: =D39 -> 0 | F33: =E39 -> 0 | G33: =F39 -> 0 | H33: =G39 -> 0 | I33: =H39 -> 0 | J33: =I39 -> 0 | K33: =J39 -> 0 | L33: =K39 -> 0 | ... AA33: =Z39 -> 0
B34: Drawdowns | D34: 0 | E34: 0 | F34: 0 | G34: 0 | H34: 0 | I34: 0 | J34: 0 | K34: 0 | L34: 0 | M34: 0 | N34: 0 | O34: 0 | P34: 0 | Q34: 0 | R34: 0 | S34: 0 | T34: 0 | U34: 0 | V34: 0 | W34: 0 | X34: 0 | Y34: 0 | Z34: 0 | AA34: 0
B35: Interest Rate | C35: =Assumptions!$E$7+'Scenario Toggle'!$E$13+1% -> 0.075 | D35: =$C35 -> 0.075 | E35: =$C35 -> 0.075 | F35: =$C35 -> 0.075 | G35: =$C35 -> 0.075 | H35: =$C35 -> 0.075 | I35: =$C35 -> 0.075 | J35: =$C35 -> 0.075 | K35: =$C35 -> 0.075 | ... AA35: =$C35 -> 0.075
B36: Interest Accrued | D36: =D33*D35/12 -> 0 | E36: =E33*E35/12 -> 0 | F36: =F33*F35/12 -> 0 | G36: =G33*G35/12 -> 0 | H36: =H33*H35/12 -> 0 | I36: =I33*I35/12 -> 0 | J36: =J33*J35/12 -> 0 | K36: =K33*K35/12 -> 0 | ... AA36: =AA33*AA35/12 -> 0
B37: Interest Paid | D37: =D36 -> 0 | E37: =E36 -> 0 | F37: =F36 -> 0 | G37: =G36 -> 0 | H37: =H36 -> 0 | I37: =I36 -> 0 | J37: =J36 -> 0 | K37: =K36 -> 0 | ... AA37: =AA36 -> 0
B38: Principal Repayment | D38: 0 | E38: 0 | F38: 0 | G38: 0 | H38: 0 | I38: 0 | J38: 0 | K38: 0 | L38: 0 | M38: 0 | N38: 0 | O38: 0 | P38: 0 | Q38: 0 | R38: 0 | S38: 0 | T38: 0 | U38: 0 | V38: 0 | W38: 0 | X38: 0 | Y38: 0 | Z38: 0 | AA38: 0
B39: Closing Balance | D39: =MAX(0,D33+D34+D36-D37-D38) -> 0 | E39: =MAX(0,E33+E34+E36-E37-E38) -> 0 | F39: =MAX(0,F33+F34+F36-F37-F38) -> 0 | G39: =MAX(0,G33+G34+G36-G37-G38) -> 0 | H39: =MAX(0,H33+H34+H36-H37-H38) -> 0 | I39: =MAX(0,I33+I34+I36-I37-I38) -> 0 | J39: =MAX(0,J33+J34+J36-J37-J38) -> 0 | K39: =MAX(0,K33+K34+K36-K37-K38) -> 0 | ... AA39: =MAX(0,AA33+AA34+AA36-AA37-AA38) -> 0

Sheet CapEx
A1: Capital Expenditure Schedule
B3: 46113 | C3: 46143 | D3: 46174 | E3: 46204 | F3: 46235 | G3: 46266 | H3: 46296 | I3: 46327 | J3: 46357 | K3: 46388 | L3: 46419 | M3: 46447 | N3: 46478 | O3: 46508 | P3: 46539 | Q3: 46569 | R3: 46600 | S3: 46631 | T3: 46661 | U3: 46692 | V3: 46722 | W3: 46753 | X3: 46784 | Y3: 46813
A5: Land acquisitions | B5: 25000000 | C5: 0 | D5: 0 | E5: 0 | F5: 0 | G5: 25000000 | H5: 0 | I5: 0 | J5: 0 | K5: 0 | L5: 0 | M5: 0 | N5: 25000000 | O5: 0 | P5: 0 | Q5: 0 | R5: 0 | S5: 0 | T5: 0 | U5: 0 | V5: 0 | W5: 0 | X5: 0 | Y5: 0
A6: Sales center construction | B6: 6000000 | C6: 6000000 | D6: 6000000 | E6: 6000000 | F6: 6000000 | G6: 6000000 | H6: 0 | I6: 0 | J6: 0 | K6: 0 | L6: 0 | M6: 0 | N6: 0 | O6: 0 | P6: 0 | Q6: 0 | R6: 0 | S6: 0 | T6: 0 | U6: 0 | V6: 0 | W6: 0 | X6: 0 | Y6: 0
A7: Office expansion | B7: 0 | C7: 0 | D7: 0 | E7: 0 | F7: 8000000 | G7: 0 | H7: 0 | I7: 0 | J7: 0 | K7: 0 | L7: 0 | M7: 0 | N7: 0 | O7: 0 | P7: 0 | Q7: 0 | R7: 0 | S7: 0 | T7: 0 | U7: 0 | V7: 0 | W7: 0 | X7: 0 | Y7: 0
A8: Technology investment | B8: 1500000 | C8: 1500000 | D8: 1500000 | E8: 1500000 | F8: 1500000 | G8: 1500000 | H8: 1500000 | I8: 1500000 | J8: 1500000 | K8: 1500000 | L8: 1500000 | M8: 1500000 | N8: 1500000 | O8: 1500000 | P8: 1500000 | Q8: 1500000 | R8: 1500000 | S8: 1500000 | T8: 1500000 | U8: 1500000 | V8: 1500000 | W8: 1500000 | X8: 1500000 | Y8: 1500000
A9: Total CapEx | B9: =SUM(B5:B8) -> 32500000 | C9: =SUM(C5:C8) -> 7500000 | D9: =SUM(D5:D8) -> 7500000 | E9: =SUM(E5:E8) -> 7500000 | F9: =SUM(F5:F8) -> 15500000 | G9: =SUM(G5:G8) -> 32500000 | H9: =SUM(H5:H8) -> 1500000 | I9: =SUM(I5:I8) -> 1500000 | ... Y9: =SUM(Y5:Y8) -> 1500000

Sheet Cash Flow
A1: Consolidated Monthly Cash Flow Forecast
B3: 46113 | C3: 46143 | D3: 46174 | E3: 46204 | F3: 46235 | G3: 46266 | H3: 46296 | I3: 46327 | J3: 46357 | K3: 46388 | L3: 46419 | M3: 46447 | N3: 46478 | O3: 46508 | P3: 46539 | Q3: 46569 | R3: 46600 | S3: 46631 | T3: 46661 | U3: 46692 | V3: 46722 | W3: 46753 | X3: 46784 | Y3: 46813
A5: Opening Cash | B5: 150000000 | C5: =B27 -> 1.0616667e+08 | D5: =C27 -> 75000000 | E5: =D27 -> 75000000 | F5: =E27 -> 75000000 | G5: =F27 -> 75000000 | H5: =G27 -> 75000000 | I5: =H27 -> 75000000 | J5: =I27 -> 75000000 | ... Y5: =X27 -> 75000000
A6: Operating Cash Inflows
A7: Off-plan customer collections | B7: =Collections!B29 -> Handover 20% | C7: =Collections!C29 -> 0 | D7: =Collections!D29 -> 0 | E7: =Collections!E29 -> 0 | F7: =Collections!F29 -> 0 | G7: =Collections!G29 -> 0 | H7: =Collections!H29 -> 0 | I7: =Collections!I29 -> 0 | ... Y7: =Collections!Y29 -> 2.9510026e+08
A8: Rental income | B8: =22000000*(1+Assumptions!$E$11/12)^(COLUMN()-2)*'Scenario Toggle'!$E$14 -> 22000000 | C8: =22000000*(1+Assumptions!$E$11/12)^(COLUMN()-2)*'Scenario Toggle'!$E$14 -> 22000000 | D8: =22000000*(1+Assumptions!$E$11/12)^(COLUMN()-2)*'Scenario Toggle'!$E$14 -> 22000000 | E8: =22000000*(1+Assumptions!$E$11/12)^(COLUMN()-2)*'Scenario Toggle'!$E$14 -> 22000000 | F8: =22000000*(1+Assumptions!$E$11/12)^(COLUMN()-2)*'Scenario Toggle'!$E$14 -> 22000000 | G8: =22000000*(1+Assumptions!$E$11/12)^(COLUMN()-2)*'Scenario Toggle'!$E$14 -> 22000000 | H8: =22000000*(1+Assumptions!$E$11/12)^(COLUMN()-2)*'Scenario Toggle'!$E$14 -> 22000000 | I8: =22000000*(1+Assumptions!$E$11/12)^(COLUMN()-2)*'Scenario Toggle'!$E$14 -> 22000000 | ... Y8: =22000000*(1+Assumptions!$E$11/12)^(COLUMN()-2)*'Scenario Toggle'!$E$14 -> 22000000
A9: Hospitality revenue | B9: =15000000*(1+Assumptions!$E$12/12)^(COLUMN()-2)*'Scenario Toggle'!$E$14 -> 15000000 | C9: =15000000*(1+Assumptions!$E$12/12)^(COLUMN()-2)*'Scenario Toggle'!$E$14 -> 15000000 | D9: =15000000*(1+Assumptions!$E$12/12)^(COLUMN()-2)*'Scenario Toggle'!$E$14 -> 15000000 | E9: =15000000*(1+Assumptions!$E$12/12)^(COLUMN()-2)*'Scenario Toggle'!$E$14 -> 15000000 | F9: =15000000*(1+Assumptions!$E$12/12)^(COLUMN()-2)*'Scenario Toggle'!$E$14 -> 15000000 | G9: =15000000*(1+Assumptions!$E$12/12)^(COLUMN()-2)*'Scenario Toggle'!$E$14 -> 15000000 | H9: =15000000*(1+Assumptions!$E$12/12)^(COLUMN()-2)*'Scenario Toggle'!$E$14 -> 15000000 | I9: =15000000*(1+Assumptions!$E$12/12)^(COLUMN()-2)*'Scenario Toggle'!$E$14 -> 15000000 | ... Y9: =15000000*(1+Assumptions!$E$12/12)^(COLUMN()-2)*'Scenario Toggle'!$E$14 -> 15000000
A10: JV / other operating inflows | B10: =6000000 -> 6000000 | C10: =6000000 -> 6000000 | D10: =6000000 -> 6000000 | E10: =6000000 -> 6000000 | F10: =6000000 -> 6000000 | G10: =6000000 -> 6000000 | H10: =6000000 -> 6000000 | I10: =6000000 -> 6000000 | ... Y10: =6000000 -> 6000000
A11: Total Operating Inflows | B11: =SUM(B7:B10) -> 43000000 | C11: =SUM(C7:C10) -> 43000000 | D11: =SUM(D7:D10) -> 43000000 | E11: =SUM(E7:E10) -> 43000000 | F11: =SUM(F7:F10) -> 43000000 | G11: =SUM(G7:G10) -> 43000000 | H11: =SUM(H7:H10) -> 43000000 | I11: =SUM(I7:I10) -> 43000000 | ... Y11: =SUM(Y7:Y10) -> 3.3810026e+08
A12: Operating Cash Outflows
A13: Construction spend (net of escrow? gross shown below) | B13: ='Construction Costs'!D29 -> 50000000 | C13: ='Construction Costs'!E29 -> 82625000 | D13: ='Construction Costs'!F29 -> 1.2330775e+08 | E13: ='Construction Costs'!G29 -> 1.7599697e+08 | F13: ='Construction Costs'!H29 -> 1.7643697e+08 | G13: ='Construction Costs'!I29 -> 1.7687806e+08 | H13: ='Construction Costs'!J29 -> 1.7732025e+08 | I13: ='Construction Costs'!K29 -> 1.7776356e+08 | ... Y13: ='Construction Costs'!AA29 -> 55063145
A14: Sales commissions | B14: =Collections!B30 -> Total Customer Collections | C14: =Collections!C30 -> 0 | D14: =Collections!D30 -> 0 | E14: =Collections!E30 -> 13912080 | F14: =Collections!F30 -> 13967728 | G14: =Collections!G30 -> 14023599 | H14: =Collections!H30 -> 14079694 | I14: =Collections!I30 -> 14136012 | ... Y14: =Collections!Y30 -> 3.4422649e+08
A15: Corporate opex | B15: ='Corporate Opex'!B9 -> 0.03 | C15: ='Corporate Opex'!C9 -> 0.03 | D15: ='Corporate Opex'!D9 -> 0.03 | E15: ='Corporate Opex'!E9 -> 0.03 | F15: ='Corporate Opex'!F9 -> 0.03 | G15: ='Corporate Opex'!G9 -> 0.03 | H15: ='Corporate Opex'!H9 -> 0.03 | I15: ='Corporate Opex'!I9 -> 0.03 | ... Y15: ='Corporate Opex'!Y9 -> 0.03
A16: Net Operating Cash Flow | B16: =B11-SUM(B13:B15) -> -7000000 | C16: =C11-SUM(C13:C15) -> -39625000 | D16: =D11-SUM(D13:D15) -> -80307753 | E16: =E11-SUM(E13:E15) -> -1.4690905e+08 | F16: =F11-SUM(F13:F15) -> -1.474047e+08 | G16: =G11-SUM(G13:G15) -> -1.4790166e+08 | H16: =H11-SUM(H13:H15) -> -1.4839995e+08 | I16: =I11-SUM(I13:I15) -> -1.4889957e+08 | ... Y16: =Y11-SUM(Y13:Y15) -> -61189383
A17: Investing Cash Flow
A18: CapEx | B18: =CapEx!B9 -> 32500000 | C18: =CapEx!C9 -> 7500000 | D18: =CapEx!D9 -> 7500000 | E18: =CapEx!E9 -> 7500000 | F18: =CapEx!F9 -> 15500000 | G18: =CapEx!G9 -> 32500000 | H18: =CapEx!H9 -> 1500000 | I18: =CapEx!I9 -> 1500000 | ... Y18: =CapEx!Y9 -> 1500000
A19: Net Investing Cash Flow | B19: =-B18 -> -32500000 | C19: =-C18 -> -7500000 | D19: =-D18 -> -7500000 | E19: =-E18 -> -7500000 | F19: =-F18 -> -15500000 | G19: =-G18 -> -32500000 | H19: =-H18 -> -1500000 | I19: =-I18 -> -1500000 | ... Y19: =-Y18 -> -1500000
A20: Financing Cash Flow
A21: Project loan drawdowns | B21: ='Debt Model'!D5+'Debt Model'!D12+'Debt Model'!D19+'Debt Model'!D26 -> 0 | C21: ='Debt Model'!E5+'Debt Model'!E12+'Debt Model'!E19+'Debt Model'!E26 -> 0 | D21: ='Debt Model'!F5+'Debt Model'!F12+'Debt Model'!F19+'Debt Model'!F26 -> 0 | E21: ='Debt Model'!G5+'Debt Model'!G12+'Debt Model'!G19+'Debt Model'!G26 -> 0 | F21: ='Debt Model'!H5+'Debt Model'!H12+'Debt Model'!H19+'Debt Model'!H26 -> 0 | G21: ='Debt Model'!I5+'Debt Model'!I12+'Debt Model'!I19+'Debt Model'!I26 -> 0 | H21: ='Debt Model'!J5+'Debt Model'!J12+'Debt Model'!J19+'Debt Model'!J26 -> 27514887 | I21: ='Debt Model'!K5+'Debt Model'!K12+'Debt Model'!K19+'Debt Model'!K26 -> 15639413 | ... Y21: ='Debt Model'!AA5+'Debt Model'!AA12+'Debt Model'!AA19+'Debt Model'!AA26 -> 0
A22: Interest paid | B22: ='Debt Model'!D8+'Debt Model'!D15+'Debt Model'!D22+'Debt Model'!D29+'Debt Model'!D37 -> 4333333.3 | C22: ='Debt Model'!E8+'Debt Model'!E15+'Debt Model'!E22+'Debt Model'!E29+'Debt Model'!E37 -> 4333333.3 | D22: ='Debt Model'!F8+'Debt Model'!F15+'Debt Model'!F22+'Debt Model'!F29+'Debt Model'!F37 -> 4333333.3 | E22: ='Debt Model'!G8+'Debt Model'!G15+'Debt Model'!G22+'Debt Model'!G29+'Debt Model'!G37 -> 4333333.3 | F22: ='Debt Model'!H8+'Debt Model'!H15+'Debt Model'!H22+'Debt Model'!H29+'Debt Model'!H37 -> 4333333.3 | G22: ='Debt Model'!I8+'Debt Model'!I15+'Debt Model'!I22+'Debt Model'!I29+'Debt Model'!I37 -> 4333333.3 | H22: ='Debt Model'!J8+'Debt Model'!J15+'Debt Model'!J22+'Debt Model'!J29+'Debt Model'!J37 -> 4333333.3 | I22: ='Debt Model'!K8+'Debt Model'!K15+'Debt Model'!K22+'Debt Model'!K29+'Debt Model'!K37 -> 4482372.3 | ... Y22: ='Debt Model'!AA8+'Debt Model'!AA15+'Debt Model'!AA22+'Debt Model'!AA29+'Debt Model'!AA37 -> 4761453.6
A23: Principal repayments | B23: ='Debt Model'!D9+'Debt Model'!D16+'Debt Model'!D23+'Debt Model'!D30+'Debt Model'!D38 -> 0 | C23: ='Debt Model'!E9+'Debt Model'!E16+'Debt Model'!E23+'Debt Model'!E30+'Debt Model'!E38 -> 0 | D23: ='Debt Model'!F9+'Debt Model'!F16+'Debt Model'!F23+'Debt Model'!F30+'Debt Model'!F38 -> 0 | E23: ='Debt Model'!G9+'Debt Model'!G16+'Debt Model'!G23+'Debt Model'!G30+'Debt Model'!G38 -> 0 | F23: ='Debt Model'!H9+'Debt Model'!H16+'Debt Model'!H23+'Debt Model'!H30+'Debt Model'!H38 -> 0 | G23: ='Debt Model'!I9+'Debt Model'!I16+'Debt Model'!I23+'Debt Model'!I30+'Debt Model'!I38 -> 0 | H23: ='Debt Model'!J9+'Debt Model'!J16+'Debt Model'!J23+'Debt Model'!J30+'Debt Model'!J38 -> 0 | I23: ='Debt Model'!K9+'Debt Model'!K16+'Debt Model'!K23+'Debt Model'!K30+'Debt Model'!K38 -> 0 | ... Y23: ='Debt Model'!AA9+'Debt Model'!AA16+'Debt Model'!AA23+'Debt Model'!AA30+'Debt Model'!AA38 -> 48281194
A24: Equity / sponsor support | B24: =MAX(0,Assumptions!$E$9-(B5+B16+B19+B21-B22-B23)) -> 0 | C24: =MAX(0,Assumptions!$E$9-(C5+C16+C19+C21-C22-C23)) -> 20291667 | D24: =MAX(0,Assumptions!$E$9-(D5+D16+D19+D21-D22-D23)) -> 92141086 | E24: =MAX(0,Assumptions!$E$9-(E5+E16+E19+E21-E22-E23)) -> 1.5874239e+08 | F24: =MAX(0,Assumptions!$E$9-(F5+F16+F19+F21-F22-F23)) -> 1.6723803e+08 | G24: =MAX(0,Assumptions!$E$9-(G5+G16+G19+G21-G22-G23)) -> 1.8473499e+08 | H24: =MAX(0,Assumptions!$E$9-(H5+H16+H19+H21-H22-H23)) -> 1.2671839e+08 | I24: =MAX(0,Assumptions!$E$9-(I5+I16+I19+I21-I22-I23)) -> 1.3924253e+08 | ... Y24: =MAX(0,Assumptions!$E$9-(Y5+Y16+Y19+Y21-Y22-Y23)) -> 1.1573203e+08
A25: Net Financing Cash Flow | B25: =B21-B22-B23+B24 -> -4333333.3 | C25: =C21-C22-C23+C24 -> 15958333 | D25: =D21-D22-D23+D24 -> 87807753 | E25: =E21-E22-E23+E24 -> 1.5440905e+08 | F25: =F21-F22-F23+F24 -> 1.629047e+08 | G25: =G21-G22-G23+G24 -> 1.8040166e+08 | H25: =H21-H22-H23+H24 -> 1.4989995e+08 | I25: =I21-I22-I23+I24 -> 1.5039957e+08 | ... Y25: =Y21-Y22-Y23+Y24 -> 62689383
A26: Net Change in Cash | B26: =B16+B19+B25 -> -43833333 | C26: =C16+C19+C25 -> -31166667 | D26: =D16+D19+D25 -> 0 | E26: =E16+E19+E25 -> 0 | F26: =F16+F19+F25 -> 0 | G26: =G16+G19+G25 -> 0 | H26: =H16+H19+H25 -> 0 | I26: =I16+I19+I25 -> 0 | ... Y26: =Y16+Y19+Y25 -> 0
A27: Closing Cash | B27: =B5+B26 -> 1.0616667e+08 | C27: =C5+C26 -> 75000000 | D27: =D5+D26 -> 75000000 | E27: =E5+E26 -> 75000000 | F27: =F5+F26 -> 75000000 | G27: =G5+G26 -> 75000000 | H27: =H5+H26 -> 75000000 | I27: =I5+I26 -> 75000000 | ... Y27: =Y5+Y26 -> 75000000

Sheet Liquidity
A1: Liquidity Analysis
B3: 46113 | C3: 46143 | D3: 46174 | E3: 46204 | F3: 46235 | G3: 46266 | H3: 46296 | I3: 46327 | J3: 46357 | K3: 46388 | L3: 46419 | M3: 46447 | N3: 46478 | O3: 46508 | P3: 46539 | Q3: 46569 | R3: 46600 | S3: 46631 | T3: 46661 | U3: 46692 | V3: 46722 | W3: 46753 | X3: 46784 | Y3: 46813
A5: Closing Cash | B5: ='Cash Flow'!B27 -> 1.0616667e+08 | C5: ='Cash Flow'!C27 -> 75000000 | D5: ='Cash Flow'!D27 -> 75000000 | E5: ='Cash Flow'!E27 -> 75000000 | F5: ='Cash Flow'!F27 -> 75000000 | G5: ='Cash Flow'!G27 -> 75000000 | H5: ='Cash Flow'!H27 -> 75000000 | I5: ='Cash Flow'!I27 -> 75000000 | ... Y5: ='Cash Flow'!Y27 -> 75000000
A6: Undrawn Credit Facilities | B6: =Assumptions!$E$10 -> 250000000 | C6: =Assumptions!$E$10 -> 250000000 | D6: =Assumptions!$E$10 -> 250000000 | E6: =Assumptions!$E$10 -> 250000000 | F6: =Assumptions!$E$10 -> 250000000 | G6: =Assumptions!$E$10 -> 250000000 | H6: =Assumptions!$E$10 -> 250000000 | I6: =Assumptions!$E$10 -> 250000000 | ... Y6: =Assumptions!$E$10 -> 250000000
A7: Available Liquidity | B7: =B5+B6 -> 3.5616667e+08 | C7: =C5+C6 -> 325000000 | D7: =D5+D6 -> 325000000 | E7: =E5+E6 -> 325000000 | F7: =F5+F6 -> 325000000 | G7: =G5+G6 -> 325000000 | H7: =H5+H6 -> 325000000 | I7: =I5+I6 -> 325000000 | ... Y7: =Y5+Y6 -> 325000000
A8: Minimum Cash Threshold | B8: =Assumptions!$E$9 -> 75000000 | C8: =Assumptions!$E$9 -> 75000000 | D8: =Assumptions!$E$9 -> 75000000 | E8: =Assumptions!$E$9 -> 75000000 | F8: =Assumptions!$E$9 -> 75000000 | G8: =Assumptions!$E$9 -> 75000000 | H8: =Assumptions!$E$9 -> 75000000 | I8: =Assumptions!$E$9 -> 75000000 | ... Y8: =Assumptions!$E$9 -> 75000000
A9: Liquidity Surplus / (Gap) | B9: =B7-B8 -> 2.8116667e+08 | C9: =C7-C8 -> 250000000 | D9: =D7-D8 -> 250000000 | E9: =E7-E8 -> 250000000 | F9: =F7-F8 -> 250000000 | G9: =G7-G8 -> 250000000 | H9: =H7-H8 -> 250000000 | I9: =I7-I8 -> 250000000 | ... Y9: =Y7-Y8 -> 250000000
A10: Peak Funding Gap Flag | B10: =IF(B9<0,"Funding Gap","OK") -> OK | C10: =IF(C9<0,"Funding Gap","OK") -> OK | D10: =IF(D9<0,"Funding Gap","OK") -> OK | E10: =IF(E9<0,"Funding Gap","OK") -> OK | F10: =IF(F9<0,"Funding Gap","OK") -> OK | G10: =IF(G9<0,"Funding Gap","OK") -> OK | H10: =IF(H9<0,"Funding Gap","OK") -> OK | I10: =IF(I9<0,"Funding Gap","OK") -> OK | ... Y10: =IF(Y9<0,"Funding Gap","OK") -> OK
A12: Minimum Liquidity Surplus | B12: =MIN(B9:Y9) -> 250000000
A13: Peak Funding Gap | B13: =MIN(0,B12) -> 0

Sheet Sensitivity
A1: Sensitivity Analysis
A3: Ending Cash Sensitivity (AED mm)
B4: Sales Price \ Sales Velocity | C4: -0.1 | D4: -0.05 | E4: 0 | F4: 0.05 | G4: 0.1
B5: -0.1 | C5: =('Cash Flow'!Y27 + -0.1*0.6*'Sales Forecast'!Y30 + -0.1*0.5*'Sales Forecast'!Y30)/1000000 -> 57.520284 | D5: =('Cash Flow'!Y27 + -0.1*0.6*'Sales Forecast'!Y30 + -0.05*0.5*'Sales Forecast'!Y30)/1000000 -> 61.492947 | E5: =('Cash Flow'!Y27 + -0.1*0.6*'Sales Forecast'!Y30 + 0*0.5*'Sales Forecast'!Y30)/1000000 -> 65.465609 | F5: =('Cash Flow'!Y27 + -0.1*0.6*'Sales Forecast'!Y30 + 0.05*0.5*'Sales Forecast'!Y30)/1000000 -> 69.438272 | G5: =('Cash Flow'!Y27 + -0.1*0.6*'Sales Forecast'!Y30 + 0.1*0.5*'Sales Forecast'!Y30)/1000000 -> 73.410935
B6: -0.05 | C6: =('Cash Flow'!Y27 + -0.05*0.6*'Sales Forecast'!Y30 + -0.1*0.5*'Sales Forecast'!Y30)/1000000 -> 62.287479 | D6: =('Cash Flow'!Y27 + -0.05*0.6*'Sales Forecast'!Y30 + -0.05*0.5*'Sales Forecast'!Y30)/1000000 -> 66.260142 | E6: =('Cash Flow'!Y27 + -0.05*0.6*'Sales Forecast'!Y30 + 0*0.5*'Sales Forecast'!Y30)/1000000 -> 70.232805 | F6: =('Cash Flow'!Y27 + -0.05*0.6*'Sales Forecast'!Y30 + 0.05*0.5*'Sales Forecast'!Y30)/1000000 -> 74.205467 | G6: =('Cash Flow'!Y27 + -0.05*0.6*'Sales Forecast'!Y30 + 0.1*0.5*'Sales Forecast'!Y30)/1000000 -> 78.17813
B7: 0 | C7: =('Cash Flow'!Y27 + 0*0.6*'Sales Forecast'!Y30 + -0.1*0.5*'Sales Forecast'!Y30)/1000000 -> 67.054675 | D7: =('Cash Flow'!Y27 + 0*0.6*'Sales Forecast'!Y30 + -0.05*0.5*'Sales Forecast'!Y30)/1000000 -> 71.027337 | E7: =('Cash Flow'!Y27 + 0*0.6*'Sales Forecast'!Y30 + 0*0.5*'Sales Forecast'!Y30)/1000000 -> 75 | F7: =('Cash Flow'!Y27 + 0*0.6*'Sales Forecast'!Y30 + 0.05*0.5*'Sales Forecast'!Y30)/1000000 -> 78.972663 | G7: =('Cash Flow'!Y27 + 0*0.6*'Sales Forecast'!Y30 + 0.1*0.5*'Sales Forecast'!Y30)/1000000 -> 82.945325
B8: 0.05 | C8: =('Cash Flow'!Y27 + 0.05*0.6*'Sales Forecast'!Y30 + -0.1*0.5*'Sales Forecast'!Y30)/1000000 -> 71.82187 | D8: =('Cash Flow'!Y27 + 0.05*0.6*'Sales Forecast'!Y30 + -0.05*0.5*'Sales Forecast'!Y30)/1000000 -> 75.794533 | E8: =('Cash Flow'!Y27 + 0.05*0.6*'Sales Forecast'!Y30 + 0*0.5*'Sales Forecast'!Y30)/1000000 -> 79.767195 | F8: =('Cash Flow'!Y27 + 0.05*0.6*'Sales Forecast'!Y30 + 0.05*0.5*'Sales Forecast'!Y30)/1000000 -> 83.739858 | G8: =('Cash Flow'!Y27 + 0.05*0.6*'Sales Forecast'!Y30 + 0.1*0.5*'Sales Forecast'!Y30)/1000000 -> 87.712521
B9: 0.1 | C9: =('Cash Flow'!Y27 + 0.1*0.6*'Sales Forecast'!Y30 + -0.1*0.5*'Sales Forecast'!Y30)/1000000 -> 76.589065 | D9: =('Cash Flow'!Y27 + 0.1*0.6*'Sales Forecast'!Y30 + -0.05*0.5*'Sales Forecast'!Y30)/1000000 -> 80.561728 | E9: =('Cash Flow'!Y27 + 0.1*0.6*'Sales Forecast'!Y30 + 0*0.5*'Sales Forecast'!Y30)/1000000 -> 84.534391 | F9: =('Cash Flow'!Y27 + 0.1*0.6*'Sales Forecast'!Y30 + 0.05*0.5*'Sales Forecast'!Y30)/1000000 -> 88.507053 | G9: =('Cash Flow'!Y27 + 0.1*0.6*'Sales Forecast'!Y30 + 0.1*0.5*'Sales Forecast'!Y30)/1000000 -> 92.479716
A12: Funding Requirement Sensitivity (AED mm)
B13: Construction Cost \ Interest Rate | C13: -0.01 | D13: 0 | E13: 0.01 | F13: 0.02
B14: -0.05 | C14: =MAX(0,-(Liquidity!$B$13 + -0.05*0.4*SUM('Construction Costs'!D29:AA29) + -0.01*0.8*SUM('Debt Model'!D36:AA36))/1000000) -> 71.691692 | D14: =MAX(0,-(Liquidity!$B$13 + -0.05*0.4*SUM('Construction Costs'!D29:AA29) + 0*0.8*SUM('Debt Model'!D36:AA36))/1000000) -> 71.691692 | E14: =MAX(0,-(Liquidity!$B$13 + -0.05*0.4*SUM('Construction Costs'!D29:AA29) + 0.01*0.8*SUM('Debt Model'!D36:AA36))/1000000) -> 71.691692 | F14: =MAX(0,-(Liquidity!$B$13 + -0.05*0.4*SUM('Construction Costs'!D29:AA29) + 0.02*0.8*SUM('Debt Model'!D36:AA36))/1000000) -> 71.691692
B15: 0 | C15: =MAX(0,-(Liquidity!$B$13 + 0*0.4*SUM('Construction Costs'!D29:AA29) + -0.01*0.8*SUM('Debt Model'!D36:AA36))/1000000) -> 0 | D15: =MAX(0,-(Liquidity!$B$13 + 0*0.4*SUM('Construction Costs'!D29:AA29) + 0*0.8*SUM('Debt Model'!D36:AA36))/1000000) -> 0 | E15: =MAX(0,-(Liquidity!$B$13 + 0*0.4*SUM('Construction Costs'!D29:AA29) + 0.01*0.8*SUM('Debt Model'!D36:AA36))/1000000) -> 0 | F15: =MAX(0,-(Liquidity!$B$13 + 0*0.4*SUM('Construction Costs'!D29:AA29) + 0.02*0.8*SUM('Debt Model'!D36:AA36))/1000000) -> 0
B16: 0.05 | C16: =MAX(0,-(Liquidity!$B$13 + 0.05*0.4*SUM('Construction Costs'!D29:AA29) + -0.01*0.8*SUM('Debt Model'!D36:AA36))/1000000) -> 0 | D16: =MAX(0,-(Liquidity!$B$13 + 0.05*0.4*SUM('Construction Costs'!D29:AA29) + 0*0.8*SUM('Debt Model'!D36:AA36))/1000000) -> 0 | E16: =MAX(0,-(Liquidity!$B$13 + 0.05*0.4*SUM('Construction Costs'!D29:AA29) + 0.01*0.8*SUM('Debt Model'!D36:AA36))/1000000) -> 0 | F16: =MAX(0,-(Liquidity!$B$13 + 0.05*0.4*SUM('Construction Costs'!D29:AA29) + 0.02*0.8*SUM('Debt Model'!D36:AA36))/1000000) -> 0
B17: 0.1 | C17: =MAX(0,-(Liquidity!$B$13 + 0.1*0.4*SUM('Construction Costs'!D29:AA29) + -0.01*0.8*SUM('Debt Model'!D36:AA36))/1000000) -> 0 | D17: =MAX(0,-(Liquidity!$B$13 + 0.1*0.4*SUM('Construction Costs'!D29:AA29) + 0*0.8*SUM('Debt Model'!D36:AA36))/1000000) -> 0 | E17: =MAX(0,-(Liquidity!$B$13 + 0.1*0.4*SUM('Construction Costs'!D29:AA29) + 0.01*0.8*SUM('Debt Model'!D36:AA36))/1000000) -> 0 | F17: =MAX(0,-(Liquidity!$B$13 + 0.1*0.4*SUM('Construction Costs'!D29:AA29) + 0.02*0.8*SUM('Debt Model'!D36:AA36))/1000000) -> 0

Sheet Dashboard
A1: Management Dashboard
A3: Ending Cash | E3: Peak Funding Gap
A4: ='Cash Flow'!Y27 -> 75000000 | E4: =Liquidity!$B$13 -> 0
A6: Total Units Sold | E6: Total Sales Value
A7: =SUM('Sales Forecast'!C29:Y29) -> 571.144 | E7: =SUM('Sales Forecast'!C30:Y30) -> 9.0203746e+09
A9: Total Customer Collections | E9: Total Construction Spend
A10: =SUM(Collections!C29:Y29) -> 2.9510026e+08 | E10: =SUM('Construction Costs'!D29:AA29) -> 3.5845846e+09
A12: Total Project Drawdowns | E12: Sponsor Support / Equity
A13: =SUM('Cash Flow'!B21:Y21) -> 1.7900858e+08 | E13: =SUM('Cash Flow'!B24:Y24) -> 3.3958025e+09
A18: Month | B18: ='Cash Flow'!B3 -> 46113 | C18: ='Cash Flow'!C3 -> 46143 | D18: ='Cash Flow'!D3 -> 46174 | E18: ='Cash Flow'!E3 -> 46204 | F18: ='Cash Flow'!F3 -> 46235 | G18: ='Cash Flow'!G3 -> 46266 | H18: ='Cash Flow'!H3 -> 46296 | I18: ='Cash Flow'!I3 -> 46327 | ... Y18: ='Cash Flow'!Y3 -> 46813
A19: Closing Cash | B19: ='Cash Flow'!B27 -> 1.0616667e+08 | C19: ='Cash Flow'!C27 -> 75000000 | D19: ='Cash Flow'!D27 -> 75000000 | E19: ='Cash Flow'!E27 -> 75000000 | F19: ='Cash Flow'!F27 -> 75000000 | G19: ='Cash Flow'!G27 -> 75000000 | H19: ='Cash Flow'!H27 -> 75000000 | I19: ='Cash Flow'!I27 -> 75000000 | ... Y19: ='Cash Flow'!Y27 -> 75000000
A20: Collections | B20: ='Cash Flow'!B7 -> Handover 20% | C20: ='Cash Flow'!C7 -> 0 | D20: ='Cash Flow'!D7 -> 0 | E20: ='Cash Flow'!E7 -> 0 | F20: ='Cash Flow'!F7 -> 0 | G20: ='Cash Flow'!G7 -> 0 | H20: ='Cash Flow'!H7 -> 0 | I20: ='Cash Flow'!I7 -> 0 | ... Y20: ='Cash Flow'!Y7 -> 2.9510026e+08
A21: Construction Spend | B21: ='Cash Flow'!B13 -> 50000000 | C21: ='Cash Flow'!C13 -> 82625000 | D21: ='Cash Flow'!D13 -> 1.2330775e+08 | E21: ='Cash Flow'!E13 -> 1.7599697e+08 | F21: ='Cash Flow'!F13 -> 1.7643697e+08 | G21: ='Cash Flow'!G13 -> 1.7687806e+08 | H21: ='Cash Flow'!H13 -> 1.7732025e+08 | I21: ='Cash Flow'!I13 -> 1.7776356e+08 | ... Y21: ='Cash Flow'!Y13 -> 55063145
B56: ='Sales Forecast'!C3 -> 46113 | C56: ='Sales Forecast'!D3 -> 46143 | D56: ='Sales Forecast'!E3 -> 46174 | E56: ='Sales Forecast'!F3 -> 46204 | F56: ='Sales Forecast'!G3 -> 46235 | G56: ='Sales Forecast'!H3 -> 46266 | H56: ='Sales Forecast'!I3 -> 46296 | I56: ='Sales Forecast'!J3 -> 46327 | ... Y56: ='Sales Forecast'!Z3 -> 46813
B57: ='Sales Forecast'!C30 -> 156800000 | C57: ='Sales Forecast'!D30 -> 260621200 | D57: ='Sales Forecast'!E30 -> 3.3122408e+08 | E57: ='Sales Forecast'!F30 -> 4.5191298e+08 | F57: ='Sales Forecast'!G30 -> 4.5372063e+08 | G57: ='Sales Forecast'!H30 -> 4.5553552e+08 | H57: ='Sales Forecast'!I30 -> 4.5735766e+08 | I57: ='Sales Forecast'!J30 -> 4.5918709e+08 | ... Y57: ='Sales Forecast'!Z30 -> 1.2928485e+08
