Workbook

Sheet 01 Dashboard
A1: Budget Summary Dashboard
A2: Annual Operating Budget – Aurelia Developments LLC (FY2026) | Management summary
A4: Metric | B4: Budget (Annual) | C4: Comment | E4: Month | F4: Revenue | G4: Construction Spend | I4: Category | J4: Annual Budget
A5: Revenue | B5: ='03 Revenue Budget'!N11 -> 2073754.3 | C5: Total corporate revenue | E5: 46023 | F5: ='03 Revenue Budget'!B11 -> 128709.76 | G5: ='05 Construction Cost Budget'!B49 -> 82099.5 | I5: Construction | J5: ='05 Construction Cost Budget'!N49 -> 1172850
A6: Gross Profit | B6: ='14 Budget vs Forecast'!N6 -> 900904.32 | C6: Revenue less development cost budget | E6: 46054 | F6: ='03 Revenue Budget'!C11 -> 147558.05 | G6: ='05 Construction Cost Budget'!C49 -> 82099.5 | I6: Sales & Marketing | J6: ='06 Sales and Marketing Budget'!N10 -> 9500
A7: EBITDA | B7: ='14 Budget vs Forecast'!N7 -> 782741.72 | C7: Before financing and tax | E7: 46082 | F7: ='03 Revenue Budget'!D11 -> 166406.47 | G7: ='05 Construction Cost Budget'!D49 -> 93828 | I7: Corporate Opex | J7: ='07 Corporate Opex'!N15 -> 108662.6
A8: Operating Expenses | B8: ='14 Budget vs Forecast'!N8 -> 118162.6 | C8: Sales & marketing plus corporate opex | E8: 46113 | F8: ='03 Revenue Budget'!E11 -> 166445.06 | G8: ='05 Construction Cost Budget'!E49 -> 93828 | I8: CapEx | J8: ='09 CapEx Budget'!N10 -> 105400
A9: Net Profit | B9: ='14 Budget vs Forecast'!N9 -> 708365.85 | C9: After financing cost | E9: 46143 | F9: ='03 Revenue Budget'!F11 -> 185293.74 | G9: ='05 Construction Cost Budget'!F49 -> 105556.5 | I9: Financing Cost | J9: ='10 Financing Cost'!N64 -> 74375.869
A10: Total Development Spend | B10: ='05 Construction Cost Budget'!N49 -> 1172850 | C10: Annual construction budget | E10: 46174 | F10: ='03 Revenue Budget'!G11 -> 185332.59 | G10: ='05 Construction Cost Budget'!G49 -> 105556.5
A11: Capital Expenditure | B11: ='09 CapEx Budget'!N10 -> 105400 | C11: Corporate / strategic capex | E11: 46204 | F11: ='03 Revenue Budget'!H11 -> 204181.53 | G11: ='05 Construction Cost Budget'!H49 -> 105556.5
A12: Debt Outstanding | B12: =SUM('13 Debt Schedule'!S5:S10) -> 3173734.2 | C12: Opening debt plus annual movement | E12: 46235 | F12: ='03 Revenue Budget'!I11 -> 204220.63 | G12: ='05 Construction Cost Budget'!I49 -> 117285
E13: 46266 | F13: ='03 Revenue Budget'!J11 -> 185449.91 | G13: ='05 Construction Cost Budget'!J49 -> 117285
E14: 46296 | F14: ='03 Revenue Budget'!K11 -> 185489.28 | G14: ='05 Construction Cost Budget'!K49 -> 105556.5
E15: 46327 | F15: ='03 Revenue Budget'!L11 -> 166718.81 | G15: ='05 Construction Cost Budget'!L49 -> 93828
E16: 46357 | F16: ='03 Revenue Budget'!M11 -> 147948.49 | G16: ='05 Construction Cost Budget'!M49 -> 70371

Sheet 02 Budget Assumptions
A1: Budget Assumptions
A2: Aurelia Developments LLC | FY2026 annual operating budget | Amounts in AED'000 unless noted
A4: Core Budget Drivers
A5: Assumption | B5: Base Value | C5: Budget Value | D5: Units | E5: Comment
A6: Construction cost inflation | B6: 0.05 | C6: =B6 -> 0.05 | D6: % | E6: Applied to monthly construction spend
A7: Sales price growth vs FY2025 | B7: 0.04 | C7: =B7 -> 0.04 | D7: % | E7: Luxury residential pricing uplift
A8: Broker commission rate | B8: 0.03 | C8: =B8 -> 0.03 | D8: % | E8: Applied to property sales
A9: Customer deposit rate on off-plan sales | B9: 0.3 | C9: =B9 -> 0.3 | D9: % | E9: Collections to escrow
A10: Escrow release ratio | B10: 0.85 | C10: =B10 -> 0.85 | D10: % | E10: Eligible construction spend released
A11: Payroll growth | B11: 0.06 | C11: =B11 -> 0.06 | D11: % | E11: Applied to average salaries
A12: Office / admin inflation | B12: 0.04 | C12: =B12 -> 0.04 | D12: % | E12: Corporate overheads
A13: Corporate tax placeholder | B13: 0.09 | C13: =B13 -> 0.09 | D13: % | E13: Illustrative
A14: Accounts receivable days | B14: 30 | C14: =B14 -> 30 | D14: days | E14: Completed property / leasing
A15: Accounts payable days | B15: 45 | C15: =B15 -> 45 | D15: days | E15: Construction and consultants
A18: Recurring Revenue Assumptions
A19: Revenue Line | B19: Monthly Base | C19: Growth / Seasonality Driver | D19: Units | E19: Comment
A20: Rental income | B20: 7000 | C20: 3% annualized step-up | D20: AED'000 | E20: Stabilized leasing portfolio
A21: Hospitality revenue | B21: 4500 | C21: seasonality + 4% ADR growth | D21: AED'000 | E21: Branded hospitality operations
A22: Development management fees | B22: 3500 | C22: flat monthly retainer | D22: AED'000 | E22: Development and asset management
A23: Other income | B23: 850 | C23: flat monthly | D23: AED'000 | E23: Miscellaneous fees and recoveries
A26: Monthly Seasonality Factors
A27: Factor | B27: Jan | C27: Feb | D27: Mar | E27: Apr | F27: May | G27: Jun | H27: Jul | I27: Aug | J27: Sep | K27: Oct | L27: Nov | M27: Dec
A28: Sales seasonality | B28: 0.06 | C28: 0.07 | D28: 0.08 | E28: 0.08 | F28: 0.09 | G28: 0.09 | H28: 0.1 | I28: 0.1 | J28: 0.09 | K28: 0.09 | L28: 0.08 | M28: 0.07
A29: Construction seasonality | B29: 0.07 | C29: 0.07 | D29: 0.08 | E29: 0.08 | F29: 0.09 | G29: 0.09 | H29: 0.09 | I29: 0.1 | J29: 0.1 | K29: 0.09 | L29: 0.08 | M29: 0.06
A30: Marketing seasonality | B30: 0.07 | C30: 0.07 | D30: 0.08 | E30: 0.08 | F30: 0.09 | G30: 0.09 | H30: 0.1 | I30: 0.1 | J30: 0.09 | K30: 0.08 | L30: 0.08 | M30: 0.07
A33: Project-Level Sales Assumptions
A34: Project | B34: Location | C34: Units Planned | D34: Avg Selling Price / Unit | E34: Off-plan % | F34: Construction Budget | G34: Debt Rate | H34: Opening Debt | I34: Annual Sales Value
A35: Marina Residences Tower | B35: Dubai Marina | C35: 95 | D35: 6200 | E35: 0.7 | F35: 325000 | G35: 0.071 | H35: 180000 | I35: =C35*D35 -> 589000
A36: Palm Waterfront Villas | B36: Palm Jumeirah | C36: 18 | D36: 22000 | E36: 0.5 | F36: 228000 | G36: 0.068 | H36: 140000 | I36: =C36*D36 -> 396000
A37: Downtown Mixed-Use Development | B37: Downtown Dubai | C37: 75 | D37: 4950 | E37: 0.8 | F37: 246000 | G37: 0.0695 | H37: 125000 | I37: =C37*D37 -> 371250
A38: Jumeirah Branded Residences | B38: Jumeirah | C38: 52 | D38: 8700 | E38: 0.6 | F38: 318000 | G38: 0.0735 | H38: 165000 | I38: =C38*D38 -> 452400

Sheet 03 Revenue Budget
A1: Revenue Budget
A2: Monthly revenue forecast linked to project-level sales assumptions
A4: Revenue Line | B4: Jan | C4: Feb | D4: Mar | E4: Apr | F4: May | G4: Jun | H4: Jul | I4: Aug | J4: Sep | K4: Oct | L4: Nov | M4: Dec | N4: FY2026
A5: Off-plan property sales | B5: =99_Helper!B41 -> 73553.376 | C5: =99_Helper!C41 -> 85812.272 | D5: =99_Helper!D41 -> 98071.168 | E5: =99_Helper!E41 -> 98071.168 | F5: =99_Helper!F41 -> 110330.06 | G5: =99_Helper!G41 -> 110330.06 | H5: =99_Helper!H41 -> 122588.96 | I5: =99_Helper!I41 -> 122588.96 | ... M5: =99_Helper!M41 -> 85812.272 | N5: =SUM(B5:M5) -> 1225889.6
A6: Completed property sales | B6: =99_Helper!B42 -> 39306.384 | C6: =99_Helper!C42 -> 45857.448 | D6: =99_Helper!D42 -> 52408.512 | E6: =99_Helper!E42 -> 52408.512 | F6: =99_Helper!F42 -> 58959.576 | G6: =99_Helper!G42 -> 58959.576 | H6: =99_Helper!H42 -> 65510.64 | I6: =99_Helper!I42 -> 65510.64 | ... M6: =99_Helper!M42 -> 45857.448 | N6: =SUM(B6:M6) -> 655106.4
A7: Rental income | B7: ='02 Budget Assumptions'!$B$20*(1+'02 Budget Assumptions'!$C$12/12)^0 -> 7000 | C7: ='02 Budget Assumptions'!$B$20*(1+'02 Budget Assumptions'!$C$12/12)^1 -> 7023.3333 | D7: ='02 Budget Assumptions'!$B$20*(1+'02 Budget Assumptions'!$C$12/12)^2 -> 7046.7444 | E7: ='02 Budget Assumptions'!$B$20*(1+'02 Budget Assumptions'!$C$12/12)^3 -> 7070.2336 | F7: ='02 Budget Assumptions'!$B$20*(1+'02 Budget Assumptions'!$C$12/12)^4 -> 7093.801 | G7: ='02 Budget Assumptions'!$B$20*(1+'02 Budget Assumptions'!$C$12/12)^5 -> 7117.447 | H7: ='02 Budget Assumptions'!$B$20*(1+'02 Budget Assumptions'!$C$12/12)^6 -> 7141.1719 | I7: ='02 Budget Assumptions'!$B$20*(1+'02 Budget Assumptions'!$C$12/12)^7 -> 7164.9758 | J7: ='02 Budget Assumptions'!$B$20*(1+'02 Budget Assumptions'!$C$12/12)^8 -> 7188.859 | K7: ='02 Budget Assumptions'!$B$20*(1+'02 Budget Assumptions'!$C$12/12)^9 -> 7212.8219 | L7: ='02 Budget Assumptions'!$B$20*(1+'02 Budget Assumptions'!$C$12/12)^10 -> 7236.8646 | M7: ='02 Budget Assumptions'!$B$20*(1+'02 Budget Assumptions'!$C$12/12)^11 -> 7260.9875 | N7: =SUM(B7:M7) -> 85557.24
A8: Hospitality revenue | B8: ='02 Budget Assumptions'!$B$21*(1+'02 Budget Assumptions'!$C$7/12)^(0) -> 4500 | C8: ='02 Budget Assumptions'!$B$21*(1+'02 Budget Assumptions'!$C$7/12)^(1) -> 4515 | D8: ='02 Budget Assumptions'!$B$21*(1+'02 Budget Assumptions'!$C$7/12)^(2) -> 4530.05 | E8: ='02 Budget Assumptions'!$B$21*(1+'02 Budget Assumptions'!$C$7/12)^(3) -> 4545.1502 | F8: ='02 Budget Assumptions'!$B$21*(1+'02 Budget Assumptions'!$C$7/12)^(4) -> 4560.3007 | G8: ='02 Budget Assumptions'!$B$21*(1+'02 Budget Assumptions'!$C$7/12)^(5) -> 4575.5017 | H8: ='02 Budget Assumptions'!$B$21*(1+'02 Budget Assumptions'!$C$7/12)^(6) -> 4590.7533 | I8: ='02 Budget Assumptions'!$B$21*(1+'02 Budget Assumptions'!$C$7/12)^(7) -> 4606.0559 | J8: ='02 Budget Assumptions'!$B$21*(1+'02 Budget Assumptions'!$C$7/12)^(8) -> 4621.4094 | K8: ='02 Budget Assumptions'!$B$21*(1+'02 Budget Assumptions'!$C$7/12)^(9) -> 4636.8141 | L8: ='02 Budget Assumptions'!$B$21*(1+'02 Budget Assumptions'!$C$7/12)^(10) -> 4652.2701 | M8: ='02 Budget Assumptions'!$B$21*(1+'02 Budget Assumptions'!$C$7/12)^(11) -> 4667.7777 | N8: =SUM(B8:M8) -> 55001.083
A9: Development management fees | B9: ='02 Budget Assumptions'!$B$22 -> 3500 | C9: ='02 Budget Assumptions'!$B$22 -> 3500 | D9: ='02 Budget Assumptions'!$B$22 -> 3500 | E9: ='02 Budget Assumptions'!$B$22 -> 3500 | F9: ='02 Budget Assumptions'!$B$22 -> 3500 | G9: ='02 Budget Assumptions'!$B$22 -> 3500 | H9: ='02 Budget Assumptions'!$B$22 -> 3500 | I9: ='02 Budget Assumptions'!$B$22 -> 3500 | ... M9: ='02 Budget Assumptions'!$B$22 -> 3500 | N9: =SUM(B9:M9) -> 42000
A10: Other income | B10: ='02 Budget Assumptions'!$B$23 -> 850 | C10: ='02 Budget Assumptions'!$B$23 -> 850 | D10: ='02 Budget Assumptions'!$B$23 -> 850 | E10: ='02 Budget Assumptions'!$B$23 -> 850 | F10: ='02 Budget Assumptions'!$B$23 -> 850 | G10: ='02 Budget Assumptions'!$B$23 -> 850 | H10: ='02 Budget Assumptions'!$B$23 -> 850 | I10: ='02 Budget Assumptions'!$B$23 -> 850 | ... M10: ='02 Budget Assumptions'!$B$23 -> 850 | N10: =SUM(B10:M10) -> 10200
A11: Total Revenue | B11: =SUM(B5:B10) -> 128709.76 | C11: =SUM(C5:C10) -> 147558.05 | D11: =SUM(D5:D10) -> 166406.47 | E11: =SUM(E5:E10) -> 166445.06 | F11: =SUM(F5:F10) -> 185293.74 | G11: =SUM(G5:G10) -> 185332.59 | H11: =SUM(H5:H10) -> 204181.53 | I11: =SUM(I5:I10) -> 204220.63 | ... M11: =SUM(M5:M10) -> 147948.49 | N11: =SUM(B11:M11) -> 2073754.3

Sheet 04 Development Project Budget
A1: Development Project Budget
A2: Annual project budget summary and monthly sales planning
A4: Project | B4: Location | C4: Units Planned for Sale | D4: Average Selling Price | E4: Total Sales Value | F4: Budgeted Revenue | G4: Budgeted Construction Cost | H4: Gross Margin | I4: Gross Margin % | J4: Jan Units | K4: Feb Units | L4: Mar Units | M4: Apr Units | N4: May Units | O4: Jun Units | P4: Jul Units | Q4: Aug Units | R4: Sep Units | S4: Oct Units | T4: Nov Units | U4: Dec Units
A5: Marina Residences Tower | B5: Dubai Marina | C5: ='02 Budget Assumptions'!C35 -> 95 | D5: ='02 Budget Assumptions'!D35 -> 6200 | E5: ='02 Budget Assumptions'!I35 -> 589000 | F5: =SUM(99_Helper!B6:M6) -> 612560 | G5: ='02 Budget Assumptions'!F35 -> 325000 | H5: =F5-G5 -> 287560 | I5: =IFERROR(H5/F5,0) -> 0.46943973 | J5: =99_Helper!B5 -> 5.7 | K5: =99_Helper!C5 -> 6.65 | L5: =99_Helper!D5 -> 7.6 | M5: =99_Helper!E5 -> 7.6 | N5: =99_Helper!F5 -> 8.55 | O5: =99_Helper!G5 -> 8.55 | P5: =99_Helper!H5 -> 9.5 | Q5: =99_Helper!I5 -> 9.5 | ... U5: =99_Helper!M5 -> 6.65
A6: Palm Waterfront Villas | B6: Palm Jumeirah | C6: ='02 Budget Assumptions'!C36 -> 18 | D6: ='02 Budget Assumptions'!D36 -> 22000 | E6: ='02 Budget Assumptions'!I36 -> 396000 | F6: =SUM(99_Helper!B15:M15) -> 411840 | G6: ='02 Budget Assumptions'!F36 -> 228000 | H6: =F6-G6 -> 183840 | I6: =IFERROR(H6/F6,0) -> 0.44638695 | J6: =99_Helper!B14 -> 1.08 | K6: =99_Helper!C14 -> 1.26 | L6: =99_Helper!D14 -> 1.44 | M6: =99_Helper!E14 -> 1.44 | N6: =99_Helper!F14 -> 1.62 | O6: =99_Helper!G14 -> 1.62 | P6: =99_Helper!H14 -> 1.8 | Q6: =99_Helper!I14 -> 1.8 | ... U6: =99_Helper!M14 -> 1.26
A7: Downtown Mixed-Use Development | B7: Downtown Dubai | C7: ='02 Budget Assumptions'!C37 -> 75 | D7: ='02 Budget Assumptions'!D37 -> 4950 | E7: ='02 Budget Assumptions'!I37 -> 371250 | F7: =SUM(99_Helper!B24:M24) -> 386100 | G7: ='02 Budget Assumptions'!F37 -> 246000 | H7: =F7-G7 -> 140100 | I7: =IFERROR(H7/F7,0) -> 0.36285936 | J7: =99_Helper!B23 -> 4.5 | K7: =99_Helper!C23 -> 5.25 | L7: =99_Helper!D23 -> 6 | M7: =99_Helper!E23 -> 6 | N7: =99_Helper!F23 -> 6.75 | O7: =99_Helper!G23 -> 6.75 | P7: =99_Helper!H23 -> 7.5 | Q7: =99_Helper!I23 -> 7.5 | ... U7: =99_Helper!M23 -> 5.25
A8: Jumeirah Branded Residences | B8: Jumeirah | C8: ='02 Budget Assumptions'!C38 -> 52 | D8: ='02 Budget Assumptions'!D38 -> 8700 | E8: ='02 Budget Assumptions'!I38 -> 452400 | F8: =SUM(99_Helper!B33:M33) -> 470496 | G8: ='02 Budget Assumptions'!F38 -> 318000 | H8: =F8-G8 -> 152496 | I8: =IFERROR(H8/F8,0) -> 0.32411753 | J8: =99_Helper!B32 -> 3.12 | K8: =99_Helper!C32 -> 3.64 | L8: =99_Helper!D32 -> 4.16 | M8: =99_Helper!E32 -> 4.16 | N8: =99_Helper!F32 -> 4.68 | O8: =99_Helper!G32 -> 4.68 | P8: =99_Helper!H32 -> 5.2 | Q8: =99_Helper!I32 -> 5.2 | ... U8: =99_Helper!M32 -> 3.64
A9: Total | C9: =SUM(C5:C8) -> 240 | D9: =SUM(D5:D8) -> 41850 | E9: =SUM(E5:E8) -> 1808650 | F9: =SUM(F5:F8) -> 1880996 | G9: =SUM(G5:G8) -> 1117000 | H9: =SUM(H5:H8) -> 763996 | I9: =SUM(I5:I8) -> 1.6028036 | J9: =SUM(J5:J8) -> 14.4 | ... T9: =SUM(T5:T8) -> 19.2

Sheet 05 Construction Cost Budget
A1: Construction Cost Budget
A2: Detailed monthly construction budget by project and cost package
A4: Project / Cost Package | B4: Jan | C4: Feb | D4: Mar | E4: Apr | F4: May | G4: Jun | H4: Jul | I4: Aug | J4: Sep | K4: Oct | L4: Nov | M4: Dec | N4: FY2026
A5: Marina Residences Tower
A6: Main contractor payments | B6: =99_Helper!B11*0.34 -> 8121.75 | C6: =99_Helper!C11*0.34 -> 8121.75 | D6: =99_Helper!D11*0.34 -> 9282 | E6: =99_Helper!E11*0.34 -> 9282 | F6: =99_Helper!F11*0.34 -> 10442.25 | G6: =99_Helper!G11*0.34 -> 10442.25 | H6: =99_Helper!H11*0.34 -> 10442.25 | I6: =99_Helper!I11*0.34 -> 11602.5 | ... M6: =99_Helper!M11*0.34 -> 6961.5 | N6: =SUM(B6:M6) -> 116025
A7: Subcontractor packages | B7: =99_Helper!B11*0.15 -> 3583.125 | C7: =99_Helper!C11*0.15 -> 3583.125 | D7: =99_Helper!D11*0.15 -> 4095 | E7: =99_Helper!E11*0.15 -> 4095 | F7: =99_Helper!F11*0.15 -> 4606.875 | G7: =99_Helper!G11*0.15 -> 4606.875 | H7: =99_Helper!H11*0.15 -> 4606.875 | I7: =99_Helper!I11*0.15 -> 5118.75 | ... M7: =99_Helper!M11*0.15 -> 3071.25 | N7: =SUM(B7:M7) -> 51187.5
A8: MEP contractors | B8: =99_Helper!B11*0.14 -> 3344.25 | C8: =99_Helper!C11*0.14 -> 3344.25 | D8: =99_Helper!D11*0.14 -> 3822 | E8: =99_Helper!E11*0.14 -> 3822 | F8: =99_Helper!F11*0.14 -> 4299.75 | G8: =99_Helper!G11*0.14 -> 4299.75 | H8: =99_Helper!H11*0.14 -> 4299.75 | I8: =99_Helper!I11*0.14 -> 4777.5 | ... M8: =99_Helper!M11*0.14 -> 2866.5 | N8: =SUM(B8:M8) -> 47775
A9: Façade contractors | B9: =99_Helper!B11*0.1 -> 2388.75 | C9: =99_Helper!C11*0.1 -> 2388.75 | D9: =99_Helper!D11*0.1 -> 2730 | E9: =99_Helper!E11*0.1 -> 2730 | F9: =99_Helper!F11*0.1 -> 3071.25 | G9: =99_Helper!G11*0.1 -> 3071.25 | H9: =99_Helper!H11*0.1 -> 3071.25 | I9: =99_Helper!I11*0.1 -> 3412.5 | ... M9: =99_Helper!M11*0.1 -> 2047.5 | N9: =SUM(B9:M9) -> 34125
A10: Consultant and design fees | B10: =99_Helper!B11*0.09 -> 2149.875 | C10: =99_Helper!C11*0.09 -> 2149.875 | D10: =99_Helper!D11*0.09 -> 2457 | E10: =99_Helper!E11*0.09 -> 2457 | F10: =99_Helper!F11*0.09 -> 2764.125 | G10: =99_Helper!G11*0.09 -> 2764.125 | H10: =99_Helper!H11*0.09 -> 2764.125 | I10: =99_Helper!I11*0.09 -> 3071.25 | ... M10: =99_Helper!M11*0.09 -> 1842.75 | N10: =SUM(B10:M10) -> 30712.5
A11: Infrastructure costs | B11: =99_Helper!B11*0.08 -> 1911 | C11: =99_Helper!C11*0.08 -> 1911 | D11: =99_Helper!D11*0.08 -> 2184 | E11: =99_Helper!E11*0.08 -> 2184 | F11: =99_Helper!F11*0.08 -> 2457 | G11: =99_Helper!G11*0.08 -> 2457 | H11: =99_Helper!H11*0.08 -> 2457 | I11: =99_Helper!I11*0.08 -> 2730 | ... M11: =99_Helper!M11*0.08 -> 1638 | N11: =SUM(B11:M11) -> 27300
A12: Testing and commissioning | B12: =99_Helper!B11*0.04 -> 955.5 | C12: =99_Helper!C11*0.04 -> 955.5 | D12: =99_Helper!D11*0.04 -> 1092 | E12: =99_Helper!E11*0.04 -> 1092 | F12: =99_Helper!F11*0.04 -> 1228.5 | G12: =99_Helper!G11*0.04 -> 1228.5 | H12: =99_Helper!H11*0.04 -> 1228.5 | I12: =99_Helper!I11*0.04 -> 1365 | ... M12: =99_Helper!M11*0.04 -> 819 | N12: =SUM(B12:M12) -> 13650
A13: Contingency allowances | B13: =99_Helper!B11*0.06 -> 1433.25 | C13: =99_Helper!C11*0.06 -> 1433.25 | D13: =99_Helper!D11*0.06 -> 1638 | E13: =99_Helper!E11*0.06 -> 1638 | F13: =99_Helper!F11*0.06 -> 1842.75 | G13: =99_Helper!G11*0.06 -> 1842.75 | H13: =99_Helper!H11*0.06 -> 1842.75 | I13: =99_Helper!I11*0.06 -> 2047.5 | ... M13: =99_Helper!M11*0.06 -> 1228.5 | N13: =SUM(B13:M13) -> 20475
A14: Project Total | B14: =SUM(B6:B13) -> 23887.5 | C14: =SUM(C6:C13) -> 23887.5 | D14: =SUM(D6:D13) -> 27300 | E14: =SUM(E6:E13) -> 27300 | F14: =SUM(F6:F13) -> 30712.5 | G14: =SUM(G6:G13) -> 30712.5 | H14: =SUM(H6:H13) -> 30712.5 | I14: =SUM(I6:I13) -> 34125 | ... M14: =SUM(M6:M13) -> 20475 | N14: =SUM(B14:M14) -> 341250
A16: Palm Waterfront Villas
A17: Main contractor payments | B17: =99_Helper!B20*0.34 -> 5697.72 | C17: =99_Helper!C20*0.34 -> 5697.72 | D17: =99_Helper!D20*0.34 -> 6511.68 | E17: =99_Helper!E20*0.34 -> 6511.68 | F17: =99_Helper!F20*0.34 -> 7325.64 | G17: =99_Helper!G20*0.34 -> 7325.64 | H17: =99_Helper!H20*0.34 -> 7325.64 | I17: =99_Helper!I20*0.34 -> 8139.6 | ... M17: =99_Helper!M20*0.34 -> 4883.76 | N17: =SUM(B17:M17) -> 81396
A18: Subcontractor packages | B18: =99_Helper!B20*0.15 -> 2513.7 | C18: =99_Helper!C20*0.15 -> 2513.7 | D18: =99_Helper!D20*0.15 -> 2872.8 | E18: =99_Helper!E20*0.15 -> 2872.8 | F18: =99_Helper!F20*0.15 -> 3231.9 | G18: =99_Helper!G20*0.15 -> 3231.9 | H18: =99_Helper!H20*0.15 -> 3231.9 | I18: =99_Helper!I20*0.15 -> 3591 | ... M18: =99_Helper!M20*0.15 -> 2154.6 | N18: =SUM(B18:M18) -> 35910
A19: MEP contractors | B19: =99_Helper!B20*0.14 -> 2346.12 | C19: =99_Helper!C20*0.14 -> 2346.12 | D19: =99_Helper!D20*0.14 -> 2681.28 | E19: =99_Helper!E20*0.14 -> 2681.28 | F19: =99_Helper!F20*0.14 -> 3016.44 | G19: =99_Helper!G20*0.14 -> 3016.44 | H19: =99_Helper!H20*0.14 -> 3016.44 | I19: =99_Helper!I20*0.14 -> 3351.6 | ... M19: =99_Helper!M20*0.14 -> 2010.96 | N19: =SUM(B19:M19) -> 33516
A20: Façade contractors | B20: =99_Helper!B20*0.1 -> 1675.8 | C20: =99_Helper!C20*0.1 -> 1675.8 | D20: =99_Helper!D20*0.1 -> 1915.2 | E20: =99_Helper!E20*0.1 -> 1915.2 | F20: =99_Helper!F20*0.1 -> 2154.6 | G20: =99_Helper!G20*0.1 -> 2154.6 | H20: =99_Helper!H20*0.1 -> 2154.6 | I20: =99_Helper!I20*0.1 -> 2394 | ... M20: =99_Helper!M20*0.1 -> 1436.4 | N20: =SUM(B20:M20) -> 23940
A21: Consultant and design fees | B21: =99_Helper!B20*0.09 -> 1508.22 | C21: =99_Helper!C20*0.09 -> 1508.22 | D21: =99_Helper!D20*0.09 -> 1723.68 | E21: =99_Helper!E20*0.09 -> 1723.68 | F21: =99_Helper!F20*0.09 -> 1939.14 | G21: =99_Helper!G20*0.09 -> 1939.14 | H21: =99_Helper!H20*0.09 -> 1939.14 | I21: =99_Helper!I20*0.09 -> 2154.6 | ... M21: =99_Helper!M20*0.09 -> 1292.76 | N21: =SUM(B21:M21) -> 21546
A22: Infrastructure costs | B22: =99_Helper!B20*0.08 -> 1340.64 | C22: =99_Helper!C20*0.08 -> 1340.64 | D22: =99_Helper!D20*0.08 -> 1532.16 | E22: =99_Helper!E20*0.08 -> 1532.16 | F22: =99_Helper!F20*0.08 -> 1723.68 | G22: =99_Helper!G20*0.08 -> 1723.68 | H22: =99_Helper!H20*0.08 -> 1723.68 | I22: =99_Helper!I20*0.08 -> 1915.2 | ... M22: =99_Helper!M20*0.08 -> 1149.12 | N22: =SUM(B22:M22) -> 19152
A23: Testing and commissioning | B23: =99_Helper!B20*0.04 -> 670.32 | C23: =99_Helper!C20*0.04 -> 670.32 | D23: =99_Helper!D20*0.04 -> 766.08 | E23: =99_Helper!E20*0.04 -> 766.08 | F23: =99_Helper!F20*0.04 -> 861.84 | G23: =99_Helper!G20*0.04 -> 861.84 | H23: =99_Helper!H20*0.04 -> 861.84 | I23: =99_Helper!I20*0.04 -> 957.6 | ... M23: =99_Helper!M20*0.04 -> 574.56 | N23: =SUM(B23:M23) -> 9576
A24: Contingency allowances | B24: =99_Helper!B20*0.06 -> 1005.48 | C24: =99_Helper!C20*0.06 -> 1005.48 | D24: =99_Helper!D20*0.06 -> 1149.12 | E24: =99_Helper!E20*0.06 -> 1149.12 | F24: =99_Helper!F20*0.06 -> 1292.76 | G24: =99_Helper!G20*0.06 -> 1292.76 | H24: =99_Helper!H20*0.06 -> 1292.76 | I24: =99_Helper!I20*0.06 -> 1436.4 | ... M24: =99_Helper!M20*0.06 -> 861.84 | N24: =SUM(B24:M24) -> 14364
A25: Project Total | B25: =SUM(B17:B24) -> 16758 | C25: =SUM(C17:C24) -> 16758 | D25: =SUM(D17:D24) -> 19152 | E25: =SUM(E17:E24) -> 19152 | F25: =SUM(F17:F24) -> 21546 | G25: =SUM(G17:G24) -> 21546 | H25: =SUM(H17:H24) -> 21546 | I25: =SUM(I17:I24) -> 23940 | ... M25: =SUM(M17:M24) -> 14364 | N25: =SUM(B25:M25) -> 239400
A27: Downtown Mixed-Use Development
A28: Main contractor payments | B28: =99_Helper!B29*0.34 -> 6147.54 | C28: =99_Helper!C29*0.34 -> 6147.54 | D28: =99_Helper!D29*0.34 -> 7025.76 | E28: =99_Helper!E29*0.34 -> 7025.76 | F28: =99_Helper!F29*0.34 -> 7903.98 | G28: =99_Helper!G29*0.34 -> 7903.98 | H28: =99_Helper!H29*0.34 -> 7903.98 | I28: =99_Helper!I29*0.34 -> 8782.2 | ... M28: =99_Helper!M29*0.34 -> 5269.32 | N28: =SUM(B28:M28) -> 87822
A29: Subcontractor packages | B29: =99_Helper!B29*0.15 -> 2712.15 | C29: =99_Helper!C29*0.15 -> 2712.15 | D29: =99_Helper!D29*0.15 -> 3099.6 | E29: =99_Helper!E29*0.15 -> 3099.6 | F29: =99_Helper!F29*0.15 -> 3487.05 | G29: =99_Helper!G29*0.15 -> 3487.05 | H29: =99_Helper!H29*0.15 -> 3487.05 | I29: =99_Helper!I29*0.15 -> 3874.5 | ... M29: =99_Helper!M29*0.15 -> 2324.7 | N29: =SUM(B29:M29) -> 38745
A30: MEP contractors | B30: =99_Helper!B29*0.14 -> 2531.34 | C30: =99_Helper!C29*0.14 -> 2531.34 | D30: =99_Helper!D29*0.14 -> 2892.96 | E30: =99_Helper!E29*0.14 -> 2892.96 | F30: =99_Helper!F29*0.14 -> 3254.58 | G30: =99_Helper!G29*0.14 -> 3254.58 | H30: =99_Helper!H29*0.14 -> 3254.58 | I30: =99_Helper!I29*0.14 -> 3616.2 | ... M30: =99_Helper!M29*0.14 -> 2169.72 | N30: =SUM(B30:M30) -> 36162
A31: Façade contractors | B31: =99_Helper!B29*0.1 -> 1808.1 | C31: =99_Helper!C29*0.1 -> 1808.1 | D31: =99_Helper!D29*0.1 -> 2066.4 | E31: =99_Helper!E29*0.1 -> 2066.4 | F31: =99_Helper!F29*0.1 -> 2324.7 | G31: =99_Helper!G29*0.1 -> 2324.7 | H31: =99_Helper!H29*0.1 -> 2324.7 | I31: =99_Helper!I29*0.1 -> 2583 | ... M31: =99_Helper!M29*0.1 -> 1549.8 | N31: =SUM(B31:M31) -> 25830
A32: Consultant and design fees | B32: =99_Helper!B29*0.09 -> 1627.29 | C32: =99_Helper!C29*0.09 -> 1627.29 | D32: =99_Helper!D29*0.09 -> 1859.76 | E32: =99_Helper!E29*0.09 -> 1859.76 | F32: =99_Helper!F29*0.09 -> 2092.23 | G32: =99_Helper!G29*0.09 -> 2092.23 | H32: =99_Helper!H29*0.09 -> 2092.23 | I32: =99_Helper!I29*0.09 -> 2324.7 | ... M32: =99_Helper!M29*0.09 -> 1394.82 | N32: =SUM(B32:M32) -> 23247
A33: Infrastructure costs | B33: =99_Helper!B29*0.08 -> 1446.48 | C33: =99_Helper!C29*0.08 -> 1446.48 | D33: =99_Helper!D29*0.08 -> 1653.12 | E33: =99_Helper!E29*0.08 -> 1653.12 | F33: =99_Helper!F29*0.08 -> 1859.76 | G33: =99_Helper!G29*0.08 -> 1859.76 | H33: =99_Helper!H29*0.08 -> 1859.76 | I33: =99_Helper!I29*0.08 -> 2066.4 | ... M33: =99_Helper!M29*0.08 -> 1239.84 | N33: =SUM(B33:M33) -> 20664
A34: Testing and commissioning | B34: =99_Helper!B29*0.04 -> 723.24 | C34: =99_Helper!C29*0.04 -> 723.24 | D34: =99_Helper!D29*0.04 -> 826.56 | E34: =99_Helper!E29*0.04 -> 826.56 | F34: =99_Helper!F29*0.04 -> 929.88 | G34: =99_Helper!G29*0.04 -> 929.88 | H34: =99_Helper!H29*0.04 -> 929.88 | I34: =99_Helper!I29*0.04 -> 1033.2 | ... M34: =99_Helper!M29*0.04 -> 619.92 | N34: =SUM(B34:M34) -> 10332
A35: Contingency allowances | B35: =99_Helper!B29*0.06 -> 1084.86 | C35: =99_Helper!C29*0.06 -> 1084.86 | D35: =99_Helper!D29*0.06 -> 1239.84 | E35: =99_Helper!E29*0.06 -> 1239.84 | F35: =99_Helper!F29*0.06 -> 1394.82 | G35: =99_Helper!G29*0.06 -> 1394.82 | H35: =99_Helper!H29*0.06 -> 1394.82 | I35: =99_Helper!I29*0.06 -> 1549.8 | ... M35: =99_Helper!M29*0.06 -> 929.88 | N35: =SUM(B35:M35) -> 15498
A36: Project Total | B36: =SUM(B28:B35) -> 18081 | C36: =SUM(C28:C35) -> 18081 | D36: =SUM(D28:D35) -> 20664 | E36: =SUM(E28:E35) -> 20664 | F36: =SUM(F28:F35) -> 23247 | G36: =SUM(G28:G35) -> 23247 | H36: =SUM(H28:H35) -> 23247 | I36: =SUM(I28:I35) -> 25830 | ... M36: =SUM(M28:M35) -> 15498 | N36: =SUM(B36:M36) -> 258300
A38: Jumeirah Branded Residences
A39: Main contractor payments | B39: =99_Helper!B38*0.34 -> 7946.82 | C39: =99_Helper!C38*0.34 -> 7946.82 | D39: =99_Helper!D38*0.34 -> 9082.08 | E39: =99_Helper!E38*0.34 -> 9082.08 | F39: =99_Helper!F38*0.34 -> 10217.34 | G39: =99_Helper!G38*0.34 -> 10217.34 | H39: =99_Helper!H38*0.34 -> 10217.34 | I39: =99_Helper!I38*0.34 -> 11352.6 | ... M39: =99_Helper!M38*0.34 -> 6811.56 | N39: =SUM(B39:M39) -> 113526
A40: Subcontractor packages | B40: =99_Helper!B38*0.15 -> 3505.95 | C40: =99_Helper!C38*0.15 -> 3505.95 | D40: =99_Helper!D38*0.15 -> 4006.8 | E40: =99_Helper!E38*0.15 -> 4006.8 | F40: =99_Helper!F38*0.15 -> 4507.65 | G40: =99_Helper!G38*0.15 -> 4507.65 | H40: =99_Helper!H38*0.15 -> 4507.65 | I40: =99_Helper!I38*0.15 -> 5008.5 | ... M40: =99_Helper!M38*0.15 -> 3005.1 | N40: =SUM(B40:M40) -> 50085
A41: MEP contractors | B41: =99_Helper!B38*0.14 -> 3272.22 | C41: =99_Helper!C38*0.14 -> 3272.22 | D41: =99_Helper!D38*0.14 -> 3739.68 | E41: =99_Helper!E38*0.14 -> 3739.68 | F41: =99_Helper!F38*0.14 -> 4207.14 | G41: =99_Helper!G38*0.14 -> 4207.14 | H41: =99_Helper!H38*0.14 -> 4207.14 | I41: =99_Helper!I38*0.14 -> 4674.6 | ... M41: =99_Helper!M38*0.14 -> 2804.76 | N41: =SUM(B41:M41) -> 46746
A42: Façade contractors | B42: =99_Helper!B38*0.1 -> 2337.3 | C42: =99_Helper!C38*0.1 -> 2337.3 | D42: =99_Helper!D38*0.1 -> 2671.2 | E42: =99_Helper!E38*0.1 -> 2671.2 | F42: =99_Helper!F38*0.1 -> 3005.1 | G42: =99_Helper!G38*0.1 -> 3005.1 | H42: =99_Helper!H38*0.1 -> 3005.1 | I42: =99_Helper!I38*0.1 -> 3339 | ... M42: =99_Helper!M38*0.1 -> 2003.4 | N42: =SUM(B42:M42) -> 33390
A43: Consultant and design fees | B43: =99_Helper!B38*0.09 -> 2103.57 | C43: =99_Helper!C38*0.09 -> 2103.57 | D43: =99_Helper!D38*0.09 -> 2404.08 | E43: =99_Helper!E38*0.09 -> 2404.08 | F43: =99_Helper!F38*0.09 -> 2704.59 | G43: =99_Helper!G38*0.09 -> 2704.59 | H43: =99_Helper!H38*0.09 -> 2704.59 | I43: =99_Helper!I38*0.09 -> 3005.1 | ... M43: =99_Helper!M38*0.09 -> 1803.06 | N43: =SUM(B43:M43) -> 30051
A44: Infrastructure costs | B44: =99_Helper!B38*0.08 -> 1869.84 | C44: =99_Helper!C38*0.08 -> 1869.84 | D44: =99_Helper!D38*0.08 -> 2136.96 | E44: =99_Helper!E38*0.08 -> 2136.96 | F44: =99_Helper!F38*0.08 -> 2404.08 | G44: =99_Helper!G38*0.08 -> 2404.08 | H44: =99_Helper!H38*0.08 -> 2404.08 | I44: =99_Helper!I38*0.08 -> 2671.2 | ... M44: =99_Helper!M38*0.08 -> 1602.72 | N44: =SUM(B44:M44) -> 26712
A45: Testing and commissioning | B45: =99_Helper!B38*0.04 -> 934.92 | C45: =99_Helper!C38*0.04 -> 934.92 | D45: =99_Helper!D38*0.04 -> 1068.48 | E45: =99_Helper!E38*0.04 -> 1068.48 | F45: =99_Helper!F38*0.04 -> 1202.04 | G45: =99_Helper!G38*0.04 -> 1202.04 | H45: =99_Helper!H38*0.04 -> 1202.04 | I45: =99_Helper!I38*0.04 -> 1335.6 | ... M45: =99_Helper!M38*0.04 -> 801.36 | N45: =SUM(B45:M45) -> 13356
A46: Contingency allowances | B46: =99_Helper!B38*0.06 -> 1402.38 | C46: =99_Helper!C38*0.06 -> 1402.38 | D46: =99_Helper!D38*0.06 -> 1602.72 | E46: =99_Helper!E38*0.06 -> 1602.72 | F46: =99_Helper!F38*0.06 -> 1803.06 | G46: =99_Helper!G38*0.06 -> 1803.06 | H46: =99_Helper!H38*0.06 -> 1803.06 | I46: =99_Helper!I38*0.06 -> 2003.4 | ... M46: =99_Helper!M38*0.06 -> 1202.04 | N46: =SUM(B46:M46) -> 20034
A47: Project Total | B47: =SUM(B39:B46) -> 23373 | C47: =SUM(C39:C46) -> 23373 | D47: =SUM(D39:D46) -> 26712 | E47: =SUM(E39:E46) -> 26712 | F47: =SUM(F39:F46) -> 30051 | G47: =SUM(G39:G46) -> 30051 | H47: =SUM(H39:H46) -> 30051 | I47: =SUM(I39:I46) -> 33390 | ... M47: =SUM(M39:M46) -> 20034 | N47: =SUM(B47:M47) -> 333900
A49: Grand Total Development Spend | B49: =SUM(B14,B25,B36,B47) -> 82099.5 | C49: =SUM(C14,C25,C36,C47) -> 82099.5 | D49: =SUM(D14,D25,D36,D47) -> 93828 | E49: =SUM(E14,E25,E36,E47) -> 93828 | F49: =SUM(F14,F25,F36,F47) -> 105556.5 | G49: =SUM(G14,G25,G36,G47) -> 105556.5 | H49: =SUM(H14,H25,H36,H47) -> 105556.5 | I49: =SUM(I14,I25,I36,I47) -> 117285 | ... N49: =SUM(N14,N25,N36,N47) -> 1172850

Sheet 06 Sales and Marketing Budget
A1: Sales and Marketing Budget
A2: Monthly marketing and sales support spend
A4: Category | B4: Jan | C4: Feb | D4: Mar | E4: Apr | F4: May | G4: Jun | H4: Jul | I4: Aug | J4: Sep | K4: Oct | L4: Nov | M4: Dec | N4: FY2026
A5: Advertising campaigns | B5: =18000*'02 Budget Assumptions'!B$30 -> 1260 | C5: =18000*'02 Budget Assumptions'!C$30 -> 1260 | D5: =18000*'02 Budget Assumptions'!D$30 -> 1440 | E5: =18000*'02 Budget Assumptions'!E$30 -> 1440 | F5: =18000*'02 Budget Assumptions'!F$30 -> 1620 | G5: =18000*'02 Budget Assumptions'!G$30 -> 1620 | H5: =18000*'02 Budget Assumptions'!H$30 -> 1800 | I5: =18000*'02 Budget Assumptions'!I$30 -> 1800 | ... M5: =18000*'02 Budget Assumptions'!M$30 -> 1260 | N5: =SUM(B5:M5) -> 18000
A6: Digital marketing | B6: =14000*'02 Budget Assumptions'!B$30 -> 980 | C6: =14000*'02 Budget Assumptions'!C$30 -> 980 | D6: =14000*'02 Budget Assumptions'!D$30 -> 1120 | E6: =14000*'02 Budget Assumptions'!E$30 -> 1120 | F6: =14000*'02 Budget Assumptions'!F$30 -> 1260 | G6: =14000*'02 Budget Assumptions'!G$30 -> 1260 | H6: =14000*'02 Budget Assumptions'!H$30 -> 1400 | I6: =14000*'02 Budget Assumptions'!I$30 -> 1400 | ... M6: =14000*'02 Budget Assumptions'!M$30 -> 980 | N6: =SUM(B6:M6) -> 14000
A7: Broker commissions | B7: =('03 Revenue Budget'!B5+'03 Revenue Budget'!B6)*'02 Budget Assumptions'!$C$8 -> 3385.7928 | C7: =('03 Revenue Budget'!C5+'03 Revenue Budget'!C6)*'02 Budget Assumptions'!$C$8 -> 3950.0916 | D7: =('03 Revenue Budget'!D5+'03 Revenue Budget'!D6)*'02 Budget Assumptions'!$C$8 -> 4514.3904 | E7: =('03 Revenue Budget'!E5+'03 Revenue Budget'!E6)*'02 Budget Assumptions'!$C$8 -> 4514.3904 | F7: =('03 Revenue Budget'!F5+'03 Revenue Budget'!F6)*'02 Budget Assumptions'!$C$8 -> 5078.6892 | G7: =('03 Revenue Budget'!G5+'03 Revenue Budget'!G6)*'02 Budget Assumptions'!$C$8 -> 5078.6892 | H7: =('03 Revenue Budget'!H5+'03 Revenue Budget'!H6)*'02 Budget Assumptions'!$C$8 -> 5642.988 | I7: =('03 Revenue Budget'!I5+'03 Revenue Budget'!I6)*'02 Budget Assumptions'!$C$8 -> 5642.988 | ... M7: =('03 Revenue Budget'!M5+'03 Revenue Budget'!M6)*'02 Budget Assumptions'!$C$8 -> 3950.0916 | N7: =SUM(B7:M7) -> 56429.88
A8: Sales center operations | B8: =12000*'02 Budget Assumptions'!B$30 -> 840 | C8: =12000*'02 Budget Assumptions'!C$30 -> 840 | D8: =12000*'02 Budget Assumptions'!D$30 -> 960 | E8: =12000*'02 Budget Assumptions'!E$30 -> 960 | F8: =12000*'02 Budget Assumptions'!F$30 -> 1080 | G8: =12000*'02 Budget Assumptions'!G$30 -> 1080 | H8: =12000*'02 Budget Assumptions'!H$30 -> 1200 | I8: =12000*'02 Budget Assumptions'!I$30 -> 1200 | ... M8: =12000*'02 Budget Assumptions'!M$30 -> 840 | N8: =SUM(B8:M8) -> 12000
A9: Launch events | B9: 300 | C9: 600 | D9: 300 | E9: 300 | F9: 600 | G9: 300 | H9: 300 | I9: 600 | J9: 300 | K9: 300 | L9: 600 | M9: 300 | N9: =SUM(B9:M9) -> 4800
A10: PR and branding | B10: =9500*'02 Budget Assumptions'!B$30 -> 665 | C10: =9500*'02 Budget Assumptions'!C$30 -> 665 | D10: =9500*'02 Budget Assumptions'!D$30 -> 760 | E10: =9500*'02 Budget Assumptions'!E$30 -> 760 | F10: =9500*'02 Budget Assumptions'!F$30 -> 855 | G10: =9500*'02 Budget Assumptions'!G$30 -> 855 | H10: =9500*'02 Budget Assumptions'!H$30 -> 950 | I10: =9500*'02 Budget Assumptions'!I$30 -> 950 | ... M10: =9500*'02 Budget Assumptions'!M$30 -> 665 | N10: =SUM(B10:M10) -> 9500
A11: Total Sales & Marketing | B11: =SUM(B5:B10) -> 7430.7928 | C11: =SUM(C5:C10) -> 8295.0916 | D11: =SUM(D5:D10) -> 9094.3904 | E11: =SUM(E5:E10) -> 9094.3904 | F11: =SUM(F5:F10) -> 10493.689 | G11: =SUM(G5:G10) -> 10193.689 | H11: =SUM(H5:H10) -> 11292.988 | I11: =SUM(I5:I10) -> 11592.988 | ... N11: =SUM(N5:N10) -> 114729.88

Sheet 07 Corporate Opex
A1: Corporate Operating Expense Budget
A2: Detailed corporate cost budget linked to headcount and assumptions
A4: Category | B4: Jan | C4: Feb | D4: Mar | E4: Apr | F4: May | G4: Jun | H4: Jul | I4: Aug | J4: Sep | K4: Oct | L4: Nov | M4: Dec | N4: FY2026
A5: Executive salaries | B5: 2200 | C5: 2200 | D5: 2200 | E5: 2200 | F5: 2200 | G5: 2200 | H5: 2200 | I5: 2200 | J5: 2200 | K5: 2200 | L5: 2200 | M5: 2200 | N5: =SUM(B5:M5) -> 26400
A6: Employee payroll | B6: ='08 Headcount Budget'!H13 -> 4086.44 | C6: ='08 Headcount Budget'!H13 -> 4086.44 | D6: ='08 Headcount Budget'!H13 -> 4086.44 | E6: ='08 Headcount Budget'!H13 -> 4086.44 | F6: ='08 Headcount Budget'!H13 -> 4086.44 | G6: ='08 Headcount Budget'!H13 -> 4086.44 | H6: ='08 Headcount Budget'!H13 -> 4086.44 | I6: ='08 Headcount Budget'!H13 -> 4086.44 | J6: ='08 Headcount Budget'!H13 -> 4086.44 | K6: ='08 Headcount Budget'!H13 -> 4086.44 | L6: ='08 Headcount Budget'!H13 -> 4086.44 | M6: ='08 Headcount Budget'!H13 -> 4086.44 | N6: =SUM(B6:M6) -> 49037.28
A7: Bonuses | B7: 0 | C7: 0 | D7: 0 | E7: 0 | F7: 0 | G7: 0 | H7: 0 | I7: 0 | J7: 0 | K7: 0 | L7: 0 | M7: ='08 Headcount Budget'!F13 -> 4145.28 | N7: =SUM(B7:M7) -> 4145.28
A8: Office rent | B8: 950 | C8: 950 | D8: 950 | E8: 950 | F8: 950 | G8: 950 | H8: 950 | I8: 950 | J8: 950 | K8: 950 | L8: 950 | M8: 950 | N8: =SUM(B8:M8) -> 11400
A9: Utilities | B9: =180*(1+'02 Budget Assumptions'!$C$12/12)^(0) -> 180 | C9: =180*(1+'02 Budget Assumptions'!$C$12/12)^(1) -> 180.6 | D9: =180*(1+'02 Budget Assumptions'!$C$12/12)^(2) -> 181.202 | E9: =180*(1+'02 Budget Assumptions'!$C$12/12)^(3) -> 181.80601 | F9: =180*(1+'02 Budget Assumptions'!$C$12/12)^(4) -> 182.41203 | G9: =180*(1+'02 Budget Assumptions'!$C$12/12)^(5) -> 183.02007 | H9: =180*(1+'02 Budget Assumptions'!$C$12/12)^(6) -> 183.63013 | I9: =180*(1+'02 Budget Assumptions'!$C$12/12)^(7) -> 184.24223 | J9: =180*(1+'02 Budget Assumptions'!$C$12/12)^(8) -> 184.85637 | K9: =180*(1+'02 Budget Assumptions'!$C$12/12)^(9) -> 185.47256 | L9: =180*(1+'02 Budget Assumptions'!$C$12/12)^(10) -> 186.0908 | M9: =180*(1+'02 Budget Assumptions'!$C$12/12)^(11) -> 186.71111 | N9: =SUM(B9:M9) -> 2200.0433
A10: Insurance | B10: 220 | C10: 220 | D10: 220 | E10: 220 | F10: 220 | G10: 220 | H10: 220 | I10: 220 | J10: 220 | K10: 220 | L10: 220 | M10: 220 | N10: =SUM(B10:M10) -> 2640
A11: Legal fees | B11: 280 | C11: 280 | D11: 280 | E11: 280 | F11: 280 | G11: 280 | H11: 280 | I11: 280 | J11: 280 | K11: 280 | L11: 280 | M11: 280 | N11: =SUM(B11:M11) -> 3360
A12: Professional services | B12: 420 | C12: 420 | D12: 420 | E12: 420 | F12: 420 | G12: 420 | H12: 420 | I12: 420 | J12: 420 | K12: 420 | L12: 420 | M12: 420 | N12: =SUM(B12:M12) -> 5040
A13: IT and technology | B13: 210 | C13: 210 | D13: 210 | E13: 210 | F13: 210 | G13: 210 | H13: 210 | I13: 210 | J13: 210 | K13: 210 | L13: 210 | M13: 210 | N13: =SUM(B13:M13) -> 2520
A14: Travel and entertainment | B14: 160 | C14: 160 | D14: 160 | E14: 160 | F14: 160 | G14: 160 | H14: 160 | I14: 160 | J14: 160 | K14: 160 | L14: 160 | M14: 160 | N14: =SUM(B14:M14) -> 1920
A15: Total Corporate Opex | B15: =SUM(B5:B14) -> 8706.44 | C15: =SUM(C5:C14) -> 8707.04 | D15: =SUM(D5:D14) -> 8707.642 | E15: =SUM(E5:E14) -> 8708.246 | F15: =SUM(F5:F14) -> 8708.852 | G15: =SUM(G5:G14) -> 8709.4601 | H15: =SUM(H5:H14) -> 8710.0701 | I15: =SUM(I5:I14) -> 8710.6822 | ... M15: =SUM(M5:M14) -> 12858.431 | N15: =SUM(B15:M15) -> 108662.6

Sheet 08 Headcount Budget
A1: Headcount Budget
A2: Workforce planning and annual payroll budget
A4: Department | B4: Headcount | C4: Average Monthly Salary | D4: Annual Base Payroll | E4: Bonus % | F4: Annual Bonus | G4: Total Payroll | H4: Monthly Payroll | I4: Comment
A5: Development | B5: 12 | C5: 45 | D5: =B5*C5*12 -> 6480 | E5: 0.1 | F5: =D5*E5 -> 648 | G5: =D5+F5 -> 7128 | H5: =G5/12 -> 594 | I5: Annual merit and inflation incorporated in salary planning
A6: Construction | B6: 28 | C6: 38 | D6: =B6*C6*12 -> 12768 | E6: 0.1 | F6: =D6*E6 -> 1276.8 | G6: =D6+F6 -> 14044.8 | H6: =G6/12 -> 1170.4 | I6: Annual merit and inflation incorporated in salary planning
A7: Sales | B7: 22 | C7: 32 | D7: =B7*C7*12 -> 8448 | E7: 0.1 | F7: =D7*E7 -> 844.8 | G7: =D7+F7 -> 9292.8 | H7: =G7/12 -> 774.4 | I7: Annual merit and inflation incorporated in salary planning
A8: Marketing | B8: 10 | C8: 28 | D8: =B8*C8*12 -> 3360 | E8: 0.08 | F8: =D8*E8 -> 268.8 | G8: =D8+F8 -> 3628.8 | H8: =G8/12 -> 302.4 | I8: Annual merit and inflation incorporated in salary planning
A9: Finance | B9: 12 | C9: 30 | D9: =B9*C9*12 -> 4320 | E9: 0.08 | F9: =D9*E9 -> 345.6 | G9: =D9+F9 -> 4665.6 | H9: =G9/12 -> 388.8 | I9: Annual merit and inflation incorporated in salary planning
A10: Legal | B10: 5 | C10: 35 | D10: =B10*C10*12 -> 2100 | E10: 0.08 | F10: =D10*E10 -> 168 | G10: =D10+F10 -> 2268 | H10: =G10/12 -> 189 | I10: Annual merit and inflation incorporated in salary planning
A11: HR | B11: 6 | C11: 25 | D11: =B11*C11*12 -> 1800 | E11: 0.08 | F11: =D11*E11 -> 144 | G11: =D11+F11 -> 1944 | H11: =G11/12 -> 162 | I11: Annual merit and inflation incorporated in salary planning
A12: Operations | B12: 18 | C12: 26 | D12: =B12*C12*12 -> 5616 | E12: 0.08 | F12: =D12*E12 -> 449.28 | G12: =D12+F12 -> 6065.28 | H12: =G12/12 -> 505.44 | I12: Annual merit and inflation incorporated in salary planning
A13: Total | B13: =SUM(B5:B12) -> 113 | C13: =SUM(C5:C12) -> 259 | D13: =SUM(D5:D12) -> 44892 | E13: =SUM(E5:E12) -> 0.7 | F13: =SUM(F5:F12) -> 4145.28 | G13: =SUM(G5:G12) -> 49037.28 | H13: =SUM(H5:H12) -> 4086.44

Sheet 09 CapEx Budget
A1: Capital Expenditure Budget
A2: Monthly CapEx schedule for corporate and project support investments
A4: CapEx Category | B4: Jan | C4: Feb | D4: Mar | E4: Apr | F4: May | G4: Jun | H4: Jul | I4: Aug | J4: Sep | K4: Oct | L4: Nov | M4: Dec | N4: FY2026
A5: Land acquisitions | B5: 35000 | C5: 0 | D5: 0 | E5: 0 | F5: 0 | G5: 0 | H5: 0 | I5: 0 | J5: 0 | K5: 20000 | L5: 0 | M5: 0 | N5: =SUM(B5:M5) -> 55000
A6: Office expansions | B6: 0 | C6: 0 | D6: 3000 | E6: 0 | F6: 0 | G6: 3000 | H6: 0 | I6: 0 | J6: 3000 | K6: 0 | L6: 0 | M6: 3000 | N6: =SUM(B6:M6) -> 12000
A7: Sales center construction | B7: 4000 | C7: 5000 | D7: 4000 | E7: 2000 | F7: 0 | G7: 0 | H7: 0 | I7: 0 | J7: 0 | K7: 0 | L7: 0 | M7: 0 | N7: =SUM(B7:M7) -> 15000
A8: Technology investment | B8: 1200 | C8: 1200 | D8: 1200 | E8: 1200 | F8: 1200 | G8: 1200 | H8: 1200 | I8: 1200 | J8: 1200 | K8: 1200 | L8: 1200 | M8: 1200 | N8: =SUM(B8:M8) -> 14400
A9: Furniture and equipment | B9: 750 | C9: 750 | D9: 750 | E9: 750 | F9: 750 | G9: 750 | H9: 750 | I9: 750 | J9: 750 | K9: 750 | L9: 750 | M9: 750 | N9: =SUM(B9:M9) -> 9000
A10: Total Capital Expenditure | B10: =SUM(B5:B9) -> 40950 | C10: =SUM(C5:C9) -> 6950 | D10: =SUM(D5:D9) -> 8950 | E10: =SUM(E5:E9) -> 3950 | F10: =SUM(F5:F9) -> 1950 | G10: =SUM(G5:G9) -> 4950 | H10: =SUM(H5:H9) -> 1950 | I10: =SUM(I5:I9) -> 1950 | ... N10: =SUM(N5:N9) -> 105400

Sheet 10 Financing Cost
A1: Financing Cost Budget
A2: Monthly interest expense, fees and projected balances
A4: Facility / Cost Line | B4: Jan | C4: Feb | D4: Mar | E4: Apr | F4: May | G4: Jun | H4: Jul | I4: Aug | J4: Sep | K4: Oct | L4: Nov | M4: Dec | N4: FY2026
A5: Marina Residences Tower
A6: Opening Balance | B6: 180000 | C6: =B11 -> 185787.64 | D6: =C11 -> 190748.32 | E6: =D11 -> 196417.67 | F6: =E11 -> 202087.03 | G6: =F11 -> 208465.05 | H6: =G11 -> 214843.07 | I6: =H11 -> 220394.13 | J6: =I11 -> 227480.82 | ... M6: =L11 -> 239441.84 | N6: =SUM(B6:M6) -> 2538832.5
A7: Drawdown | B7: =MAX(0,99_Helper!B11-99_Helper!B10)*0.45 -> 5787.639 | C7: =MAX(0,99_Helper!C11-99_Helper!C10)*0.45 -> 4960.683 | D7: =MAX(0,99_Helper!D11-99_Helper!D10)*0.45 -> 5669.352 | E7: =MAX(0,99_Helper!E11-99_Helper!E10)*0.45 -> 5669.352 | F7: =MAX(0,99_Helper!F11-99_Helper!F10)*0.45 -> 6378.021 | G7: =MAX(0,99_Helper!G11-99_Helper!G10)*0.45 -> 6378.021 | H7: =MAX(0,99_Helper!H11-99_Helper!H10)*0.45 -> 5551.065 | I7: =MAX(0,99_Helper!I11-99_Helper!I10)*0.45 -> 7086.69 | ... M7: =MAX(0,99_Helper!M11-99_Helper!M10)*0.45 -> 3425.058 | N7: =SUM(B7:M7) -> 70866.9
A8: Interest Expense | B8: =B6*'02 Budget Assumptions'!$G$35 / 12 -> 1065 | C8: =C6*'02 Budget Assumptions'!$G$35 / 12 -> 1099.2435 | D8: =D6*'02 Budget Assumptions'!$G$35 / 12 -> 1128.5942 | E8: =E6*'02 Budget Assumptions'!$G$35 / 12 -> 1162.1379 | F8: =F6*'02 Budget Assumptions'!$G$35 / 12 -> 1195.6816 | G8: =G6*'02 Budget Assumptions'!$G$35 / 12 -> 1233.4182 | H8: =H6*'02 Budget Assumptions'!$G$35 / 12 -> 1271.1548 | I8: =I6*'02 Budget Assumptions'!$G$35 / 12 -> 1303.9986 | ... M8: =M6*'02 Budget Assumptions'!$G$35 / 12 -> 1416.6976 | N8: =SUM(B8:M8) -> 15021.426
A9: Interest Payment | B9: =B8 -> 1065 | C9: =C8 -> 1099.2435 | D9: =D8 -> 1128.5942 | E9: =E8 -> 1162.1379 | F9: =F8 -> 1195.6816 | G9: =G8 -> 1233.4182 | H9: =H8 -> 1271.1548 | I9: =I8 -> 1303.9986 | ... M9: =M8 -> 1416.6976 | N9: =SUM(B9:M9) -> 15021.426
A10: Principal Repayment | B10: 0 | C10: 0 | D10: 0 | E10: 0 | F10: 0 | G10: 0 | H10: 0 | I10: 0 | J10: 0 | K10: 4000 | L10: 4000 | M10: 4000 | N10: =SUM(B10:M10) -> 12000
A11: Closing Balance | B11: =B6+B7+B8-B9-B10 -> 185787.64 | C11: =C6+C7+C8-C9-C10 -> 190748.32 | D11: =D6+D7+D8-D9-D10 -> 196417.67 | E11: =E6+E7+E8-E9-E10 -> 202087.03 | F11: =F6+F7+F8-F9-F10 -> 208465.05 | G11: =G6+G7+G8-G9-G10 -> 214843.07 | H11: =H6+H7+H8-H9-H10 -> 220394.13 | I11: =I6+I7+I8-I9-I10 -> 227480.82 | ... M11: =M6+M7+M8-M9-M10 -> 238866.9 | N11: =SUM(B11:M11) -> 2597699.4
A14: Palm Waterfront Villas
A15: Opening Balance | B15: 140000 | C15: =B20 -> 144205.2 | D15: =C20 -> 147854.41 | E15: =D20 -> 152024.94 | F15: =E20 -> 156195.46 | G15: =F20 -> 160887.31 | H15: =G20 -> 165579.15 | I15: =H20 -> 169715.01 | J15: =I20 -> 174928.17 | ... M15: =L20 -> 181559.69 | N15: =SUM(B15:M15) -> 1955035.8
A16: Drawdown | B16: =MAX(0,99_Helper!B20-99_Helper!B19)*0.45 -> 4205.196 | C16: =MAX(0,99_Helper!C20-99_Helper!C19)*0.45 -> 3649.212 | D16: =MAX(0,99_Helper!D20-99_Helper!D19)*0.45 -> 4170.528 | E16: =MAX(0,99_Helper!E20-99_Helper!E19)*0.45 -> 4170.528 | F16: =MAX(0,99_Helper!F20-99_Helper!F19)*0.45 -> 4691.844 | G16: =MAX(0,99_Helper!G20-99_Helper!G19)*0.45 -> 4691.844 | H16: =MAX(0,99_Helper!H20-99_Helper!H19)*0.45 -> 4135.86 | I16: =MAX(0,99_Helper!I20-99_Helper!I19)*0.45 -> 5213.16 | ... M16: =MAX(0,99_Helper!M20-99_Helper!M19)*0.45 -> 2571.912 | N16: =SUM(B16:M16) -> 52131.6
A17: Interest Expense | B17: =B15*'02 Budget Assumptions'!$G$36 / 12 -> 793.33333 | C17: =C15*'02 Budget Assumptions'!$G$36 / 12 -> 817.16278 | D17: =D15*'02 Budget Assumptions'!$G$36 / 12 -> 837.84165 | E17: =E15*'02 Budget Assumptions'!$G$36 / 12 -> 861.47464 | F17: =F15*'02 Budget Assumptions'!$G$36 / 12 -> 885.10763 | G17: =G15*'02 Budget Assumptions'!$G$36 / 12 -> 911.69475 | H17: =H15*'02 Budget Assumptions'!$G$36 / 12 -> 938.28186 | I17: =I15*'02 Budget Assumptions'!$G$36 / 12 -> 961.7184 | ... M17: =M15*'02 Budget Assumptions'!$G$36 / 12 -> 1028.8382 | N17: =SUM(B17:M17) -> 11078.536
A18: Interest Payment | B18: =B17 -> 793.33333 | C18: =C17 -> 817.16278 | D18: =D17 -> 837.84165 | E18: =E17 -> 861.47464 | F18: =F17 -> 885.10763 | G18: =G17 -> 911.69475 | H18: =H17 -> 938.28186 | I18: =I17 -> 961.7184 | ... M18: =M17 -> 1028.8382 | N18: =SUM(B18:M18) -> 11078.536
A19: Principal Repayment | B19: 0 | C19: 0 | D19: 0 | E19: 0 | F19: 0 | G19: 0 | H19: 0 | I19: 0 | J19: 0 | K19: 4000 | L19: 4000 | M19: 4000 | N19: =SUM(B19:M19) -> 12000
A20: Closing Balance | B20: =B15+B16+B17-B18-B19 -> 144205.2 | C20: =C15+C16+C17-C18-C19 -> 147854.41 | D20: =D15+D16+D17-D18-D19 -> 152024.94 | E20: =E15+E16+E17-E18-E19 -> 156195.46 | F20: =F15+F16+F17-F18-F19 -> 160887.31 | G20: =G15+G16+G17-G18-G19 -> 165579.15 | H20: =H15+H16+H17-H18-H19 -> 169715.01 | I20: =I15+I16+I17-I18-I19 -> 174928.17 | ... M20: =M15+M16+M17-M18-M19 -> 180131.6 | N20: =SUM(B20:M20) -> 1995167.4
A23: Downtown Mixed-Use Development
A24: Opening Balance | B24: 125000 | C24: =B29 -> 130009.04 | D24: =C29 -> 134496.85 | E24: =D29 -> 139625.77 | F24: =E29 -> 144754.68 | G24: =F29 -> 150524.72 | H24: =G29 -> 156294.76 | I24: =H29 -> 161543.55 | J24: =I29 -> 167954.7 | ... M24: =L29 -> 177786.05 | N24: =SUM(B24:M24) -> 1839534.3
A25: Drawdown | B25: =MAX(0,99_Helper!B29-99_Helper!B28)*0.45 -> 5009.04 | C25: =MAX(0,99_Helper!C29-99_Helper!C28)*0.45 -> 4487.805 | D25: =MAX(0,99_Helper!D29-99_Helper!D28)*0.45 -> 5128.92 | E25: =MAX(0,99_Helper!E29-99_Helper!E28)*0.45 -> 5128.92 | F25: =MAX(0,99_Helper!F29-99_Helper!F28)*0.45 -> 5770.035 | G25: =MAX(0,99_Helper!G29-99_Helper!G28)*0.45 -> 5770.035 | H25: =MAX(0,99_Helper!H29-99_Helper!H28)*0.45 -> 5248.8 | I25: =MAX(0,99_Helper!I29-99_Helper!I28)*0.45 -> 6411.15 | ... M25: =MAX(0,99_Helper!M29-99_Helper!M28)*0.45 -> 3325.455 | N25: =SUM(B25:M25) -> 64111.5
A26: Interest Expense | B26: =B24*'02 Budget Assumptions'!$G$37 / 12 -> 723.95833 | C26: =C24*'02 Budget Assumptions'!$G$37 / 12 -> 752.96902 | D26: =D24*'02 Budget Assumptions'!$G$37 / 12 -> 778.96089 | E26: =E24*'02 Budget Assumptions'!$G$37 / 12 -> 808.66589 | F26: =F24*'02 Budget Assumptions'!$G$37 / 12 -> 838.37088 | G26: =G24*'02 Budget Assumptions'!$G$37 / 12 -> 871.789 | H26: =H24*'02 Budget Assumptions'!$G$37 / 12 -> 905.20712 | I26: =I24*'02 Budget Assumptions'!$G$37 / 12 -> 935.60642 | ... M26: =M24*'02 Budget Assumptions'!$G$37 / 12 -> 1029.6775 | N26: =SUM(B26:M26) -> 10653.97
A27: Interest Payment | B27: =B26 -> 723.95833 | C27: =C26 -> 752.96902 | D27: =D26 -> 778.96089 | E27: =E26 -> 808.66589 | F27: =F26 -> 838.37088 | G27: =G26 -> 871.789 | H27: =H26 -> 905.20712 | I27: =I26 -> 935.60642 | ... M27: =M26 -> 1029.6775 | N27: =SUM(B27:M27) -> 10653.97
A28: Principal Repayment | B28: 0 | C28: 0 | D28: 0 | E28: 0 | F28: 0 | G28: 0 | H28: 0 | I28: 0 | J28: 0 | K28: 4000 | L28: 4000 | M28: 4000 | N28: =SUM(B28:M28) -> 12000
A29: Closing Balance | B29: =B24+B25+B26-B27-B28 -> 130009.04 | C29: =C24+C25+C26-C27-C28 -> 134496.85 | D29: =D24+D25+D26-D27-D28 -> 139625.77 | E29: =E24+E25+E26-E27-E28 -> 144754.68 | F29: =F24+F25+F26-F27-F28 -> 150524.72 | G29: =G24+G25+G26-G27-G28 -> 156294.76 | H29: =H24+H25+H26-H27-H28 -> 161543.55 | I29: =I24+I25+I26-I27-I28 -> 167954.7 | ... M29: =M24+M25+M26-M27-M28 -> 177111.5 | N29: =SUM(B29:M29) -> 1891645.8
A32: Jumeirah Branded Residences
A33: Opening Balance | B33: 165000 | C33: =B38 -> 171706.83 | D33: =C38 -> 177778.5 | E33: =D38 -> 184717.54 | F33: =E38 -> 191656.58 | G33: =F38 -> 199463.01 | H33: =G38 -> 207269.43 | I33: =H38 -> 214440.68 | J33: =I38 -> 223114.49 | ... M33: =L38 -> 239168.93 | N33: =SUM(B33:M33) -> 2442969.3
A34: Drawdown | B34: =MAX(0,99_Helper!B38-99_Helper!B37)*0.45 -> 6706.8324 | C34: =MAX(0,99_Helper!C38-99_Helper!C37)*0.45 -> 6071.6628 | D34: =MAX(0,99_Helper!D38-99_Helper!D37)*0.45 -> 6939.0432 | E34: =MAX(0,99_Helper!E38-99_Helper!E37)*0.45 -> 6939.0432 | F34: =MAX(0,99_Helper!F38-99_Helper!F37)*0.45 -> 7806.4236 | G34: =MAX(0,99_Helper!G38-99_Helper!G37)*0.45 -> 7806.4236 | H34: =MAX(0,99_Helper!H38-99_Helper!H37)*0.45 -> 7171.254 | I34: =MAX(0,99_Helper!I38-99_Helper!I37)*0.45 -> 8673.804 | ... M34: =MAX(0,99_Helper!M38-99_Helper!M37)*0.45 -> 4569.1128 | N34: =SUM(B34:M34) -> 86738.04
A35: Interest Expense | B35: =B33*'02 Budget Assumptions'!$G$38 / 12 -> 1010.625 | C35: =C33*'02 Budget Assumptions'!$G$38 / 12 -> 1051.7043 | D35: =D33*'02 Budget Assumptions'!$G$38 / 12 -> 1088.8933 | E35: =E33*'02 Budget Assumptions'!$G$38 / 12 -> 1131.3949 | F35: =F33*'02 Budget Assumptions'!$G$38 / 12 -> 1173.8966 | G35: =G33*'02 Budget Assumptions'!$G$38 / 12 -> 1221.7109 | H35: =H33*'02 Budget Assumptions'!$G$38 / 12 -> 1269.5253 | I35: =I33*'02 Budget Assumptions'!$G$38 / 12 -> 1313.4492 | ... M35: =M33*'02 Budget Assumptions'!$G$38 / 12 -> 1464.9097 | N35: =SUM(B35:M35) -> 14963.187
A36: Interest Payment | B36: =B35 -> 1010.625 | C36: =C35 -> 1051.7043 | D36: =D35 -> 1088.8933 | E36: =E35 -> 1131.3949 | F36: =F35 -> 1173.8966 | G36: =G35 -> 1221.7109 | H36: =H35 -> 1269.5253 | I36: =I35 -> 1313.4492 | ... M36: =M35 -> 1464.9097 | N36: =SUM(B36:M36) -> 14963.187
A37: Principal Repayment | B37: 0 | C37: 0 | D37: 0 | E37: 0 | F37: 0 | G37: 0 | H37: 0 | I37: 0 | J37: 0 | K37: 4000 | L37: 4000 | M37: 4000 | N37: =SUM(B37:M37) -> 12000
A38: Closing Balance | B38: =B33+B34+B35-B36-B37 -> 171706.83 | C38: =C33+C34+C35-C36-C37 -> 177778.5 | D38: =D33+D34+D35-D36-D37 -> 184717.54 | E38: =E33+E34+E35-E36-E37 -> 191656.58 | F38: =F33+F34+F35-F36-F37 -> 199463.01 | G38: =G33+G34+G35-G36-G37 -> 207269.43 | H38: =H33+H34+H35-H36-H37 -> 214440.68 | I38: =I33+I34+I35-I36-I37 -> 223114.49 | ... M38: =M33+M34+M35-M36-M37 -> 239738.04 | N38: =SUM(B38:M38) -> 2517707.4
A41: Corporate Revolving Facility
A42: Opening Balance | B42: 60000 | C42: =B47 -> 60000 | D42: =C47 -> 60000 | E42: =D47 -> 70000 | F42: =E47 -> 85000 | G42: =F47 -> 95000 | H42: =G47 -> 90000 | I42: =H47 -> 80000 | J42: =I47 -> 85000 | ... M42: =L47 -> 65000 | N42: =SUM(B42:M42) -> 900000
A43: Drawdown | B43: 0 | C43: 0 | D43: 10000 | E43: 15000 | F43: 10000 | G43: 0 | H43: 0 | I43: 5000 | J43: 0 | K43: 0 | L43: 0 | M43: 0 | N43: =SUM(B43:M43) -> 40000
A44: Interest Expense | B44: =B42*0.0775/12 -> 387.5 | C44: =C42*0.0775/12 -> 387.5 | D44: =D42*0.0775/12 -> 387.5 | E44: =E42*0.0775/12 -> 452.08333 | F44: =F42*0.0775/12 -> 548.95833 | G44: =G42*0.0775/12 -> 613.54167 | H44: =H42*0.0775/12 -> 581.25 | I44: =I42*0.0775/12 -> 516.66667 | ... M44: =M42*0.0775/12 -> 419.79167 | N44: =SUM(B44:M44) -> 5812.5
A45: Interest Payment | B45: =B44 -> 387.5 | C45: =C44 -> 387.5 | D45: =D44 -> 387.5 | E45: =E44 -> 452.08333 | F45: =F44 -> 548.95833 | G45: =G44 -> 613.54167 | H45: =H44 -> 581.25 | I45: =I44 -> 516.66667 | ... M45: =M44 -> 419.79167 | N45: =SUM(B45:M45) -> 5812.5
A46: Principal Repayment | B46: 0 | C46: 0 | D46: 0 | E46: 0 | F46: 0 | G46: 5000 | H46: 10000 | I46: 0 | J46: 5000 | K46: 10000 | L46: 5000 | M46: 5000 | N46: =SUM(B46:M46) -> 40000
A47: Closing Balance | B47: =B42+B43+B44-B45-B46 -> 60000 | C47: =C42+C43+C44-C45-C46 -> 60000 | D47: =D42+D43+D44-D45-D46 -> 70000 | E47: =E42+E43+E44-E45-E46 -> 85000 | F47: =F42+F43+F44-F45-F46 -> 95000 | G47: =G42+G43+G44-G45-G46 -> 90000 | H47: =H42+H43+H44-H45-H46 -> 80000 | I47: =I42+I43+I44-I45-I46 -> 85000 | ... M47: =M42+M43+M44-M45-M46 -> 60000 | N47: =SUM(B47:M47) -> 900000
A50: Shareholder Loan
A51: Opening Balance | B51: 85000 | C51: =B56 -> 90000 | D51: =C56 -> 95000 | E51: =D56 -> 95000 | F51: =E56 -> 95000 | G51: =F56 -> 95000 | H51: =G56 -> 95000 | I51: =H56 -> 95000 | J51: =I56 -> 95000 | ... M51: =L56 -> 95000 | N51: =SUM(B51:M51) -> 1125000
A52: Drawdown | B52: 5000 | C52: 5000 | D52: 0 | E52: 0 | F52: 0 | G52: 0 | H52: 0 | I52: 0 | J52: 0 | K52: 0 | L52: 0 | M52: 0 | N52: =SUM(B52:M52) -> 10000
A53: Interest Expense | B53: =B51*0.095/12 -> 672.91667 | C53: =C51*0.095/12 -> 712.5 | D53: =D51*0.095/12 -> 752.08333 | E53: =E51*0.095/12 -> 752.08333 | F53: =F51*0.095/12 -> 752.08333 | G53: =G51*0.095/12 -> 752.08333 | H53: =H51*0.095/12 -> 752.08333 | I53: =I51*0.095/12 -> 752.08333 | ... M53: =M51*0.095/12 -> 752.08333 | N53: =SUM(B53:M53) -> 8906.25
A54: Interest Payment | B54: =B53 -> 672.91667 | C54: =C53 -> 712.5 | D54: =D53 -> 752.08333 | E54: =E53 -> 752.08333 | F54: =F53 -> 752.08333 | G54: =G53 -> 752.08333 | H54: =H53 -> 752.08333 | I54: =I53 -> 752.08333 | ... M54: =M53 -> 752.08333 | N54: =SUM(B54:M54) -> 8906.25
A55: Principal Repayment | B55: 0 | C55: 0 | D55: 0 | E55: 0 | F55: 0 | G55: 0 | H55: 0 | I55: 0 | J55: 0 | K55: 0 | L55: 0 | M55: 0 | N55: =SUM(B55:M55) -> 0
A56: Closing Balance | B56: =B51+B52+B53-B54-B55 -> 90000 | C56: =C51+C52+C53-C54-C55 -> 95000 | D56: =D51+D52+D53-D54-D55 -> 95000 | E56: =E51+E52+E53-E54-E55 -> 95000 | F56: =F51+F52+F53-F54-F55 -> 95000 | G56: =G51+G52+G53-G54-G55 -> 95000 | H56: =H51+H52+H53-H54-H55 -> 95000 | I56: =I51+I52+I53-I54-I55 -> 95000 | ... M56: =M51+M52+M53-M54-M55 -> 95000 | N56: =SUM(B56:M56) -> 1135000
A59: Other Financing Costs
A60: Loan commitment fees | B60: 180 | C60: 180 | D60: 180 | E60: 180 | F60: 180 | G60: 180 | H60: 180 | I60: 180 | J60: 180 | K60: 180 | L60: 180 | M60: 180 | N60: =SUM(B60:M60) -> 2160
A61: Arrangement fees | B61: 2500 | C61: 0 | D61: 0 | E61: 0 | F61: 0 | G61: 2500 | H61: 0 | I61: 0 | J61: 0 | K61: 0 | L61: 0 | M61: 0 | N61: =SUM(B61:M61) -> 5000
A62: Bank charges | B62: 65 | C62: 65 | D62: 65 | E62: 65 | F62: 65 | G62: 65 | H62: 65 | I62: 65 | J62: 65 | K62: 65 | L62: 65 | M62: 65 | N62: =SUM(B62:M62) -> 780
A63: Total Financing Cost
A64: Total Interest / Fees | B64: =SUM(B9,B18,B27,B36,B45,B54,B60,B61,B62) -> 7398.3333 | C64: =SUM(C9,C18,C27,C36,C45,C54,C60,C61,C62) -> 5066.0797 | D64: =SUM(D9,D18,D27,D36,D45,D54,D60,D61,D62) -> 5218.8734 | E64: =SUM(E9,E18,E27,E36,E45,E54,E60,E61,E62) -> 5412.84 | F64: =SUM(F9,F18,F27,F36,F45,F54,F60,F61,F62) -> 5639.0983 | G64: =SUM(G9,G18,G27,G36,G45,G54,G60,G61,G62) -> 8349.2379 | H64: =SUM(H9,H18,H27,H36,H45,H54,H60,H61,H62) -> 5962.5024 | I64: =SUM(I9,I18,I27,I36,I45,I54,I60,I61,I62) -> 6028.5226 | ... M64: =SUM(M9,M18,M27,M36,M45,M54,M60,M61,M62) -> 6356.998 | N64: =SUM(B64:M64) -> 74375.869

Sheet 11 Cash Flow Budget
A1: Cash Flow Budget
A2: Monthly budgeted cash flow statement
A4: Cash Flow Category | B4: Jan | C4: Feb | D4: Mar | E4: Apr | F4: May | G4: Jun | H4: Jul | I4: Aug | J4: Sep | K4: Oct | L4: Nov | M4: Dec | N4: FY2026
A5: Opening Cash | B5: 95000 | C5: =B28 -> 133345.65 | D5: =C28 -> 157655.39 | E5: =D28 -> 199103.53 | F5: =E28 -> 238699.61 | G5: =F28 -> 289304.61 | H5: =G28 -> 307541.78 | I5: =H28 -> 335123.45 | J5: =I28 -> 382988.16 | ... M5: =L28 -> 361304.31 | N5: =SUM(B5:M5) -> 3265048.9
A6: Operating Cash Inflows | N6: =SUM(B6:M6) -> 0
A7: Customer deposits from off-plan sales | B7: =99_Helper!B43 -> 33857.928 | C7: =99_Helper!C43 -> 39500.916 | D7: =99_Helper!D43 -> 45143.904 | E7: =99_Helper!E43 -> 45143.904 | F7: =99_Helper!F43 -> 50786.892 | G7: =99_Helper!G43 -> 50786.892 | H7: =99_Helper!H43 -> 56429.88 | I7: =99_Helper!I43 -> 56429.88 | ... M7: =99_Helper!M43 -> 39500.916 | N7: =SUM(B7:M7) -> 564298.8
A8: Completed property cash collections | B8: ='03 Revenue Budget'!B6*0.9 -> 35375.746 | C8: ='03 Revenue Budget'!C6*0.9 -> 41271.703 | D8: ='03 Revenue Budget'!D6*0.9 -> 47167.661 | E8: ='03 Revenue Budget'!E6*0.9 -> 47167.661 | F8: ='03 Revenue Budget'!F6*0.9 -> 53063.618 | G8: ='03 Revenue Budget'!G6*0.9 -> 53063.618 | H8: ='03 Revenue Budget'!H6*0.9 -> 58959.576 | I8: ='03 Revenue Budget'!I6*0.9 -> 58959.576 | ... M8: ='03 Revenue Budget'!M6*0.9 -> 41271.703 | N8: =SUM(B8:M8) -> 589595.76
A9: Rental income | B9: ='03 Revenue Budget'!B7 -> 7000 | C9: ='03 Revenue Budget'!C7 -> 7023.3333 | D9: ='03 Revenue Budget'!D7 -> 7046.7444 | E9: ='03 Revenue Budget'!E7 -> 7070.2336 | F9: ='03 Revenue Budget'!F7 -> 7093.801 | G9: ='03 Revenue Budget'!G7 -> 7117.447 | H9: ='03 Revenue Budget'!H7 -> 7141.1719 | I9: ='03 Revenue Budget'!I7 -> 7164.9758 | ... M9: ='03 Revenue Budget'!M7 -> 7260.9875 | N9: =SUM(B9:M9) -> 85557.24
A10: Hospitality / mgmt / other | B10: ='03 Revenue Budget'!B8+'03 Revenue Budget'!B9+'03 Revenue Budget'!B10 -> 8850 | C10: ='03 Revenue Budget'!C8+'03 Revenue Budget'!C9+'03 Revenue Budget'!C10 -> 8865 | D10: ='03 Revenue Budget'!D8+'03 Revenue Budget'!D9+'03 Revenue Budget'!D10 -> 8880.05 | E10: ='03 Revenue Budget'!E8+'03 Revenue Budget'!E9+'03 Revenue Budget'!E10 -> 8895.1502 | F10: ='03 Revenue Budget'!F8+'03 Revenue Budget'!F9+'03 Revenue Budget'!F10 -> 8910.3007 | G10: ='03 Revenue Budget'!G8+'03 Revenue Budget'!G9+'03 Revenue Budget'!G10 -> 8925.5017 | H10: ='03 Revenue Budget'!H8+'03 Revenue Budget'!H9+'03 Revenue Budget'!H10 -> 8940.7533 | I10: ='03 Revenue Budget'!I8+'03 Revenue Budget'!I9+'03 Revenue Budget'!I10 -> 8956.0559 | ... M10: ='03 Revenue Budget'!M8+'03 Revenue Budget'!M9+'03 Revenue Budget'!M10 -> 9017.7777 | N10: =SUM(B10:M10) -> 107201.08
A11: Total Operating Inflows | B11: =SUM(B7:B10) -> 85083.674 | C11: =SUM(C7:C10) -> 96660.953 | D11: =SUM(D7:D10) -> 108238.36 | E11: =SUM(E7:E10) -> 108276.95 | F11: =SUM(F7:F10) -> 119854.61 | G11: =SUM(G7:G10) -> 119893.46 | H11: =SUM(H7:H10) -> 131471.38 | I11: =SUM(I7:I10) -> 131510.49 | ... M11: =SUM(M7:M10) -> 97051.384 | N11: =SUM(B11:M11) -> 1346652.9
A12: Operating Cash Outflows | N12: =SUM(B12:M12) -> 0
A13: Construction spend net of escrow releases | B13: =99_Helper!B45-99_Helper!B44 -> 48241.572 | C13: =99_Helper!C45-99_Helper!C44 -> 42598.584 | D13: =99_Helper!D45-99_Helper!D44 -> 48684.096 | E13: =99_Helper!E45-99_Helper!E44 -> 48684.096 | F13: =99_Helper!F45-99_Helper!F44 -> 54769.608 | G13: =99_Helper!G45-99_Helper!G44 -> 54769.608 | H13: =99_Helper!H45-99_Helper!H44 -> 49126.62 | I13: =99_Helper!I45-99_Helper!I44 -> 60855.12 | ... M13: =99_Helper!M45-99_Helper!M44 -> 30870.084 | N13: =SUM(B13:M13) -> 608551.2
A14: Sales & marketing spend | B14: ='06 Sales and Marketing Budget'!B10 -> 665 | C14: ='06 Sales and Marketing Budget'!C10 -> 665 | D14: ='06 Sales and Marketing Budget'!D10 -> 760 | E14: ='06 Sales and Marketing Budget'!E10 -> 760 | F14: ='06 Sales and Marketing Budget'!F10 -> 855 | G14: ='06 Sales and Marketing Budget'!G10 -> 855 | H14: ='06 Sales and Marketing Budget'!H10 -> 950 | I14: ='06 Sales and Marketing Budget'!I10 -> 950 | ... M14: ='06 Sales and Marketing Budget'!M10 -> 665 | N14: =SUM(B14:M14) -> 9500
A15: Corporate operating expense | B15: ='07 Corporate Opex'!B15 -> 8706.44 | C15: ='07 Corporate Opex'!C15 -> 8707.04 | D15: ='07 Corporate Opex'!D15 -> 8707.642 | E15: ='07 Corporate Opex'!E15 -> 8708.246 | F15: ='07 Corporate Opex'!F15 -> 8708.852 | G15: ='07 Corporate Opex'!G15 -> 8709.4601 | H15: ='07 Corporate Opex'!H15 -> 8710.0701 | I15: ='07 Corporate Opex'!I15 -> 8710.6822 | ... M15: ='07 Corporate Opex'!M15 -> 12858.431 | N15: =SUM(B15:M15) -> 108662.6
A16: Working capital movement | B16: =(99_Helper!B48-28000)+(99_Helper!B49-60000)-(99_Helper!B50-40000)-(99_Helper!B51-15000) -> -32514.613 | C16: =(99_Helper!C48-99_Helper!B48)+(99_Helper!C49-99_Helper!B49)-(99_Helper!C50-99_Helper!B50)-(99_Helper!C51-99_Helper!B51) -> 32533.873 | D16: =(99_Helper!D48-99_Helper!C48)+(99_Helper!D49-99_Helper!C49)-(99_Helper!D50-99_Helper!C50)-(99_Helper!D51-99_Helper!C51) -> 26377.449 | E16: =(99_Helper!E48-99_Helper!D48)+(99_Helper!E49-99_Helper!D49)-(99_Helper!E50-99_Helper!D50)-(99_Helper!E51-99_Helper!D51) -> 38073.529 | F16: =(99_Helper!F48-99_Helper!E48)+(99_Helper!F49-99_Helper!E49)-(99_Helper!F50-99_Helper!E50)-(99_Helper!F51-99_Helper!E51) -> 31973.379 | G16: =(99_Helper!G48-99_Helper!F48)+(99_Helper!G49-99_Helper!F49)-(99_Helper!G50-99_Helper!F50)-(99_Helper!G51-99_Helper!F51) -> 43669.303 | H16: =(99_Helper!H48-99_Helper!G48)+(99_Helper!H49-99_Helper!G49)-(99_Helper!H50-99_Helper!G50)-(99_Helper!H51-99_Helper!G51) -> 49297.496 | I16: =(99_Helper!I48-99_Helper!H48)+(99_Helper!I49-99_Helper!H49)-(99_Helper!I50-99_Helper!H50)-(99_Helper!I51-99_Helper!H51) -> 37536.261 | J16: =(99_Helper!J48-99_Helper!I48)+(99_Helper!J49-99_Helper!I49)-(99_Helper!J50-99_Helper!I50)-(99_Helper!J51-99_Helper!I51) -> 43588.96 | ... M16: =(99_Helper!M48-99_Helper!L48)+(99_Helper!M49-99_Helper!L49)-(99_Helper!M50-99_Helper!L50)-(99_Helper!M51-99_Helper!L51) -> 53615.214 | N16: =SUM(B16:M16) -> 429079.74
A17: Total Operating Outflows | B17: =SUM(B13:B16) -> 25098.399 | C17: =SUM(C13:C16) -> 84504.497 | D17: =SUM(D13:D16) -> 84529.187 | E17: =SUM(E13:E16) -> 96225.871 | F17: =SUM(F13:F16) -> 96306.839 | G17: =SUM(G13:G16) -> 108003.37 | H17: =SUM(H13:H16) -> 108084.19 | I17: =SUM(I13:I16) -> 108052.06 | ... M17: =SUM(M13:M16) -> 98008.729 | N17: =SUM(B17:M17) -> 1155793.5
A18: Net Operating Cash Flow | B18: =B11-B17 -> 59985.274 | C18: =C11-C17 -> 12156.456 | D18: =D11-D17 -> 23709.172 | E18: =E11-E17 -> 12051.077 | F18: =F11-F17 -> 23547.773 | G18: =G11-G17 -> 11890.088 | H18: =H11-H17 -> 23387.195 | I18: =I11-I17 -> 23458.424 | ... M18: =M11-M17 -> -957.34459 | N18: =SUM(B18:M18) -> 190859.34
A19: Investing Cash Flow | N19: =SUM(B19:M19) -> 0
A20: Capital expenditure | B20: ='09 CapEx Budget'!B10 -> 40950 | C20: ='09 CapEx Budget'!C10 -> 6950 | D20: ='09 CapEx Budget'!D10 -> 8950 | E20: ='09 CapEx Budget'!E10 -> 3950 | F20: ='09 CapEx Budget'!F10 -> 1950 | G20: ='09 CapEx Budget'!G10 -> 4950 | H20: ='09 CapEx Budget'!H10 -> 1950 | I20: ='09 CapEx Budget'!I10 -> 1950 | ... M20: ='09 CapEx Budget'!M10 -> 4950 | N20: =SUM(B20:M20) -> 105400
A21: Net Investing Cash Flow | B21: =-B20 -> -40950 | C21: =-C20 -> -6950 | D21: =-D20 -> -8950 | E21: =-E20 -> -3950 | F21: =-F20 -> -1950 | G21: =-G20 -> -4950 | H21: =-H20 -> -1950 | I21: =-I20 -> -1950 | ... M21: =-M20 -> -4950 | N21: =SUM(B21:M21) -> -105400
A22: Financing Cash Flow | N22: =SUM(B22:M22) -> 0
A23: Debt drawdowns | B23: =SUM('10 Financing Cost'!B7,'10 Financing Cost'!B16,'10 Financing Cost'!B25,'10 Financing Cost'!B34,'10 Financing Cost'!B43,'10 Financing Cost'!B52) -> 26708.707 | C23: =SUM('10 Financing Cost'!C7,'10 Financing Cost'!C16,'10 Financing Cost'!C25,'10 Financing Cost'!C34,'10 Financing Cost'!C43,'10 Financing Cost'!C52) -> 24169.363 | D23: =SUM('10 Financing Cost'!D7,'10 Financing Cost'!D16,'10 Financing Cost'!D25,'10 Financing Cost'!D34,'10 Financing Cost'!D43,'10 Financing Cost'!D52) -> 31907.843 | E23: =SUM('10 Financing Cost'!E7,'10 Financing Cost'!E16,'10 Financing Cost'!E25,'10 Financing Cost'!E34,'10 Financing Cost'!E43,'10 Financing Cost'!E52) -> 36907.843 | F23: =SUM('10 Financing Cost'!F7,'10 Financing Cost'!F16,'10 Financing Cost'!F25,'10 Financing Cost'!F34,'10 Financing Cost'!F43,'10 Financing Cost'!F52) -> 34646.324 | G23: =SUM('10 Financing Cost'!G7,'10 Financing Cost'!G16,'10 Financing Cost'!G25,'10 Financing Cost'!G34,'10 Financing Cost'!G43,'10 Financing Cost'!G52) -> 24646.324 | H23: =SUM('10 Financing Cost'!H7,'10 Financing Cost'!H16,'10 Financing Cost'!H25,'10 Financing Cost'!H34,'10 Financing Cost'!H43,'10 Financing Cost'!H52) -> 22106.979 | I23: =SUM('10 Financing Cost'!I7,'10 Financing Cost'!I16,'10 Financing Cost'!I25,'10 Financing Cost'!I34,'10 Financing Cost'!I43,'10 Financing Cost'!I52) -> 32384.804 | ... M23: =SUM('10 Financing Cost'!M7,'10 Financing Cost'!M16,'10 Financing Cost'!M25,'10 Financing Cost'!M34,'10 Financing Cost'!M43,'10 Financing Cost'!M52) -> 13891.538 | N23: =SUM(B23:M23) -> 323848.04
A24: Interest payments / fees | B24: =SUM('10 Financing Cost'!B9,'10 Financing Cost'!B18,'10 Financing Cost'!B27,'10 Financing Cost'!B36,'10 Financing Cost'!B45,'10 Financing Cost'!B54,'10 Financing Cost'!B60,'10 Financing Cost'!B61,'10 Financing Cost'!B62) -> 7398.3333 | C24: =SUM('10 Financing Cost'!C9,'10 Financing Cost'!C18,'10 Financing Cost'!C27,'10 Financing Cost'!C36,'10 Financing Cost'!C45,'10 Financing Cost'!C54,'10 Financing Cost'!C60,'10 Financing Cost'!C61,'10 Financing Cost'!C62) -> 5066.0797 | D24: =SUM('10 Financing Cost'!D9,'10 Financing Cost'!D18,'10 Financing Cost'!D27,'10 Financing Cost'!D36,'10 Financing Cost'!D45,'10 Financing Cost'!D54,'10 Financing Cost'!D60,'10 Financing Cost'!D61,'10 Financing Cost'!D62) -> 5218.8734 | E24: =SUM('10 Financing Cost'!E9,'10 Financing Cost'!E18,'10 Financing Cost'!E27,'10 Financing Cost'!E36,'10 Financing Cost'!E45,'10 Financing Cost'!E54,'10 Financing Cost'!E60,'10 Financing Cost'!E61,'10 Financing Cost'!E62) -> 5412.84 | F24: =SUM('10 Financing Cost'!F9,'10 Financing Cost'!F18,'10 Financing Cost'!F27,'10 Financing Cost'!F36,'10 Financing Cost'!F45,'10 Financing Cost'!F54,'10 Financing Cost'!F60,'10 Financing Cost'!F61,'10 Financing Cost'!F62) -> 5639.0983 | G24: =SUM('10 Financing Cost'!G9,'10 Financing Cost'!G18,'10 Financing Cost'!G27,'10 Financing Cost'!G36,'10 Financing Cost'!G45,'10 Financing Cost'!G54,'10 Financing Cost'!G60,'10 Financing Cost'!G61,'10 Financing Cost'!G62) -> 8349.2379 | H24: =SUM('10 Financing Cost'!H9,'10 Financing Cost'!H18,'10 Financing Cost'!H27,'10 Financing Cost'!H36,'10 Financing Cost'!H45,'10 Financing Cost'!H54,'10 Financing Cost'!H60,'10 Financing Cost'!H61,'10 Financing Cost'!H62) -> 5962.5024 | I24: =SUM('10 Financing Cost'!I9,'10 Financing Cost'!I18,'10 Financing Cost'!I27,'10 Financing Cost'!I36,'10 Financing Cost'!I45,'10 Financing Cost'!I54,'10 Financing Cost'!I60,'10 Financing Cost'!I61,'10 Financing Cost'!I62) -> 6028.5226 | ... M24: =SUM('10 Financing Cost'!M9,'10 Financing Cost'!M18,'10 Financing Cost'!M27,'10 Financing Cost'!M36,'10 Financing Cost'!M45,'10 Financing Cost'!M54,'10 Financing Cost'!M60,'10 Financing Cost'!M61,'10 Financing Cost'!M62) -> 6356.998 | N24: =SUM(B24:M24) -> 74375.869
A25: Principal repayments | B25: =SUM('10 Financing Cost'!B10,'10 Financing Cost'!B19,'10 Financing Cost'!B28,'10 Financing Cost'!B37,'10 Financing Cost'!B46,'10 Financing Cost'!B55) -> 0 | C25: =SUM('10 Financing Cost'!C10,'10 Financing Cost'!C19,'10 Financing Cost'!C28,'10 Financing Cost'!C37,'10 Financing Cost'!C46,'10 Financing Cost'!C55) -> 0 | D25: =SUM('10 Financing Cost'!D10,'10 Financing Cost'!D19,'10 Financing Cost'!D28,'10 Financing Cost'!D37,'10 Financing Cost'!D46,'10 Financing Cost'!D55) -> 0 | E25: =SUM('10 Financing Cost'!E10,'10 Financing Cost'!E19,'10 Financing Cost'!E28,'10 Financing Cost'!E37,'10 Financing Cost'!E46,'10 Financing Cost'!E55) -> 0 | F25: =SUM('10 Financing Cost'!F10,'10 Financing Cost'!F19,'10 Financing Cost'!F28,'10 Financing Cost'!F37,'10 Financing Cost'!F46,'10 Financing Cost'!F55) -> 0 | G25: =SUM('10 Financing Cost'!G10,'10 Financing Cost'!G19,'10 Financing Cost'!G28,'10 Financing Cost'!G37,'10 Financing Cost'!G46,'10 Financing Cost'!G55) -> 5000 | H25: =SUM('10 Financing Cost'!H10,'10 Financing Cost'!H19,'10 Financing Cost'!H28,'10 Financing Cost'!H37,'10 Financing Cost'!H46,'10 Financing Cost'!H55) -> 10000 | I25: =SUM('10 Financing Cost'!I10,'10 Financing Cost'!I19,'10 Financing Cost'!I28,'10 Financing Cost'!I37,'10 Financing Cost'!I46,'10 Financing Cost'!I55) -> 0 | ... M25: =SUM('10 Financing Cost'!M10,'10 Financing Cost'!M19,'10 Financing Cost'!M28,'10 Financing Cost'!M37,'10 Financing Cost'!M46,'10 Financing Cost'!M55) -> 21000 | N25: =SUM(B25:M25) -> 88000
A26: Net Financing Cash Flow | B26: =B23-B24-B25 -> 19310.374 | C26: =C23-C24-C25 -> 19103.283 | D26: =D23-D24-D25 -> 26688.97 | E26: =E23-E24-E25 -> 31495.003 | F26: =F23-F24-F25 -> 29007.225 | G26: =G23-G24-G25 -> 11297.086 | H26: =H23-H24-H25 -> 6144.4766 | I26: =I23-I24-I25 -> 26356.281 | ... M26: =M23-M24-M25 -> -13465.46 | N26: =SUM(B26:M26) -> 161472.17
A27: Net Change in Cash | B27: =B18+B21+B26 -> 38345.648 | C27: =C18+C21+C26 -> 24309.739 | D27: =D18+D21+D26 -> 41448.142 | E27: =E18+E21+E26 -> 39596.08 | F27: =F18+F21+F26 -> 50604.998 | G27: =G18+G21+G26 -> 18237.174 | H27: =H18+H21+H26 -> 27581.672 | I27: =I18+I21+I26 -> 47864.705 | ... M27: =M18+M21+M26 -> -19372.805 | N27: =SUM(B27:M27) -> 246931.51
A28: Closing Cash | B28: =B5+B27 -> 133345.65 | C28: =C5+C27 -> 157655.39 | D28: =D5+D27 -> 199103.53 | E28: =E5+E27 -> 238699.61 | F28: =F5+F27 -> 289304.61 | G28: =G5+G27 -> 307541.78 | H28: =H5+H27 -> 335123.45 | I28: =I5+I27 -> 382988.16 | ... M28: =M5+M27 -> 341931.51 | N28: =SUM(B28:M28) -> 3511980.4

Sheet 12 Working Capital
A1: Working Capital Budget
A2: Projected working capital balances and monthly movements
A4: Metric | B4: Jan | C4: Feb | D4: Mar | E4: Apr | F4: May | G4: Jun | H4: Jul | I4: Aug | J4: Sep | K4: Oct | L4: Nov | M4: Dec | N4: FY2026 Avg
A5: Accounts receivable | B5: =99_Helper!B48 -> 412.67928 | C5: =99_Helper!C48 -> 469.26916 | D5: =99_Helper!D48 -> 525.85957 | E5: =99_Helper!E48 -> 526.02064 | F5: =99_Helper!F48 -> 582.61213 | G5: =99_Helper!G48 -> 582.77427 | H5: =99_Helper!H48 -> 639.36684 | I5: =99_Helper!I48 -> 639.53006 | ... M5: =99_Helper!M48 -> 470.89879 | N5: =AVERAGE(B5:M5) -> 545.23885
A6: Customer deposits | B6: =99_Helper!B49 -> 86857.928 | C6: =99_Helper!C49 -> 119335.51 | D6: =99_Helper!D49 -> 157432.67 | E6: =99_Helper!E49 -> 195506.34 | F6: =99_Helper!F49 -> 239199.43 | G6: =99_Helper!G49 -> 282868.88 | H6: =99_Helper!H49 -> 332157.58 | I6: =99_Helper!I49 -> 381422.49 | ... M6: =99_Helper!M49 -> 538741.56 | N6: =AVERAGE(B6:M6) -> 311136.59
A7: Accounts payable | B7: =99_Helper!B50 -> 82099.5 | C7: =99_Helper!C50 -> 82099.5 | D7: =99_Helper!D50 -> 93828 | E7: =99_Helper!E50 -> 93828 | F7: =99_Helper!F50 -> 105556.5 | G7: =99_Helper!G50 -> 105556.5 | H7: =99_Helper!H50 -> 105556.5 | I7: =99_Helper!I50 -> 117285 | ... M7: =99_Helper!M50 -> 70371 | N7: =AVERAGE(B7:M7) -> 97737.5
A8: Accrued expenses | B8: =99_Helper!B51 -> 4685.72 | C8: =99_Helper!C51 -> 4686.02 | D8: =99_Helper!D51 -> 4733.821 | E8: =99_Helper!E51 -> 4734.123 | F8: =99_Helper!F51 -> 4781.926 | G8: =99_Helper!G51 -> 4782.23 | H8: =99_Helper!H51 -> 4830.0351 | I8: =99_Helper!I51 -> 4830.3411 | ... M8: =99_Helper!M51 -> 6761.7156 | N8: =AVERAGE(B8:M8) -> 4923.4418
A9: Net working capital | B9: =B5-B6-B7-B8 -> -173230.47 | C9: =C5-C6-C7-C8 -> -205651.76 | D9: =D5-D6-D7-D8 -> -255468.63 | E9: =E5-E6-E7-E8 -> -293542.44 | F9: =F5-F6-F7-F8 -> -348955.25 | G9: =G5-G6-G7-G8 -> -392624.83 | H9: =H5-H6-H7-H8 -> -441904.75 | I9: =I5-I6-I7-I8 -> -502898.3 | ... M9: =M5-M6-M7-M8 -> -615403.38 | N9: =AVERAGE(B9:M9) -> -413252.3

Sheet 13 Debt Schedule
A1: Debt and Financing Schedule
A2: Debt obligations and key terms at FY2026 budget start
A4: Lender | B4: Facility / Loan Type | C4: Project / Purpose | D4: Interest Rate | E4: Outstanding Balance | F4: Facility Limit | G4: Maturity Date | H4: Jan Close | I4: Feb Close | J4: Mar Close | K4: Apr Close | L4: May Close | M4: Jun Close | N4: Jul Close | O4: Aug Close | P4: Sep Close | Q4: Oct Close | R4: Nov Close | S4: Dec Close
A5: Emirates NBD | B5: Project Finance Facility | C5: Marina Residences Tower | D5: 0.071 | E5: 180000 | F5: 244000 | G5: 30-Jun-2028 | H5: =E5+'10 Financing Cost'!B6-'10 Financing Cost'!B9 -> 358935 | I5: =H5+'10 Financing Cost'!C6-'10 Financing Cost'!C9 -> 543623.4 | J5: =I5+'10 Financing Cost'!D6-'10 Financing Cost'!D9 -> 733243.12 | K5: =J5+'10 Financing Cost'!E6-'10 Financing Cost'!E9 -> 928498.66 | L5: =K5+'10 Financing Cost'!F6-'10 Financing Cost'!F9 -> 1129390 | M5: =L5+'10 Financing Cost'!G6-'10 Financing Cost'!G9 -> 1336621.6 | N5: =M5+'10 Financing Cost'!H6-'10 Financing Cost'!H9 -> 1550193.5 | O5: =N5+'10 Financing Cost'!I6-'10 Financing Cost'!I9 -> 1769283.7 | P5: =O5+'10 Financing Cost'!J6-'10 Financing Cost'!J9 -> 1995418.6 | ... S5: =R5+'10 Financing Cost'!M6-'10 Financing Cost'!M9 -> 2703811.1
A6: First Abu Dhabi Bank | B6: Project Finance Facility | C6: Palm Waterfront Villas | D6: 0.068 | E6: 140000 | F6: 171000 | G6: 31-Dec-2027 | H6: =E6+'10 Financing Cost'!B12-'10 Financing Cost'!B15 -> 0 | I6: =H6+'10 Financing Cost'!C12-'10 Financing Cost'!C15 -> -144205.2 | J6: =I6+'10 Financing Cost'!D12-'10 Financing Cost'!D15 -> -292059.6 | K6: =J6+'10 Financing Cost'!E12-'10 Financing Cost'!E15 -> -444084.54 | L6: =K6+'10 Financing Cost'!F12-'10 Financing Cost'!F15 -> -600280 | M6: =L6+'10 Financing Cost'!G12-'10 Financing Cost'!G15 -> -761167.31 | N6: =M6+'10 Financing Cost'!H12-'10 Financing Cost'!H15 -> -926746.46 | O6: =N6+'10 Financing Cost'!I12-'10 Financing Cost'!I15 -> -1096461.5 | P6: =O6+'10 Financing Cost'!J12-'10 Financing Cost'!J15 -> -1271389.6 | ... S6: =R6+'10 Financing Cost'!M12-'10 Financing Cost'!M15 -> -1815035.8
A7: ADCB | B7: Project Finance Facility | C7: Downtown Mixed-Use Development | D7: 0.0695 | E7: 125000 | F7: 184000 | G7: 30-Sep-2028 | H7: =E7+'10 Financing Cost'!B18-'10 Financing Cost'!B21 -> 125793.33 | I7: =H7+'10 Financing Cost'!C18-'10 Financing Cost'!C21 -> 126610.5 | J7: =I7+'10 Financing Cost'!D18-'10 Financing Cost'!D21 -> 127448.34 | K7: =J7+'10 Financing Cost'!E18-'10 Financing Cost'!E21 -> 128309.81 | L7: =K7+'10 Financing Cost'!F18-'10 Financing Cost'!F21 -> 129194.92 | M7: =L7+'10 Financing Cost'!G18-'10 Financing Cost'!G21 -> 130106.61 | N7: =M7+'10 Financing Cost'!H18-'10 Financing Cost'!H21 -> 131044.9 | O7: =N7+'10 Financing Cost'!I18-'10 Financing Cost'!I21 -> 132006.62 | P7: =O7+'10 Financing Cost'!J18-'10 Financing Cost'!J21 -> 132997.87 | ... S7: =R7+'10 Financing Cost'!M18-'10 Financing Cost'!M21 -> 136078.54
A8: Mashreq | B8: Project Finance Facility | C8: Jumeirah Branded Residences | D8: 0.0735 | E8: 165000 | F8: 238000 | G8: 31-Mar-2029 | H8: =E8+'10 Financing Cost'!B24-'10 Financing Cost'!B27 -> 289276.04 | I8: =H8+'10 Financing Cost'!C24-'10 Financing Cost'!C27 -> 418532.11 | J8: =I8+'10 Financing Cost'!D24-'10 Financing Cost'!D27 -> 552250 | K8: =J8+'10 Financing Cost'!E24-'10 Financing Cost'!E27 -> 691067.1 | L8: =K8+'10 Financing Cost'!F24-'10 Financing Cost'!F27 -> 834983.41 | M8: =L8+'10 Financing Cost'!G24-'10 Financing Cost'!G27 -> 984636.34 | N8: =M8+'10 Financing Cost'!H24-'10 Financing Cost'!H27 -> 1140025.9 | O8: =N8+'10 Financing Cost'!I24-'10 Financing Cost'!I27 -> 1300633.8 | P8: =O8+'10 Financing Cost'!J24-'10 Financing Cost'!J27 -> 1467615.8 | ... S8: =R8+'10 Financing Cost'!M24-'10 Financing Cost'!M27 -> 1993880.4
A9: Mashreq | B9: Corporate RCF | C9: Corporate Revolving Facility | D9: 0.0775 | E9: 60000 | F9: 180000 | G9: 31-Dec-2026 | H9: =E9+'10 Financing Cost'!B43-'10 Financing Cost'!B46 -> 60000 | I9: =H9+'10 Financing Cost'!C43-'10 Financing Cost'!C46 -> 60000 | J9: =I9+'10 Financing Cost'!D43-'10 Financing Cost'!D46 -> 70000 | K9: =J9+'10 Financing Cost'!E43-'10 Financing Cost'!E46 -> 85000 | L9: =K9+'10 Financing Cost'!F43-'10 Financing Cost'!F46 -> 95000 | M9: =L9+'10 Financing Cost'!G43-'10 Financing Cost'!G46 -> 90000 | N9: =M9+'10 Financing Cost'!H43-'10 Financing Cost'!H46 -> 80000 | O9: =N9+'10 Financing Cost'!I43-'10 Financing Cost'!I46 -> 85000 | P9: =O9+'10 Financing Cost'!J43-'10 Financing Cost'!J46 -> 80000 | ... S9: =R9+'10 Financing Cost'!M43-'10 Financing Cost'!M46 -> 60000
A10: Aurelia Holdings | B10: Shareholder Loan | C10: Shareholder Loan | D10: 0.095 | E10: 85000 | F10: 150000 | G10: 31-Dec-2028 | H10: =E10+'10 Financing Cost'!B52-'10 Financing Cost'!B55 -> 90000 | I10: =H10+'10 Financing Cost'!C52-'10 Financing Cost'!C55 -> 95000 | J10: =I10+'10 Financing Cost'!D52-'10 Financing Cost'!D55 -> 95000 | K10: =J10+'10 Financing Cost'!E52-'10 Financing Cost'!E55 -> 95000 | L10: =K10+'10 Financing Cost'!F52-'10 Financing Cost'!F55 -> 95000 | M10: =L10+'10 Financing Cost'!G52-'10 Financing Cost'!G55 -> 95000 | N10: =M10+'10 Financing Cost'!H52-'10 Financing Cost'!H55 -> 95000 | O10: =N10+'10 Financing Cost'!I52-'10 Financing Cost'!I55 -> 95000 | P10: =O10+'10 Financing Cost'!J52-'10 Financing Cost'!J55 -> 95000 | ... S10: =R10+'10 Financing Cost'!M52-'10 Financing Cost'!M55 -> 95000
A12: Note | B12: Monthly closing balances support financing cost and lender reporting.

Sheet 14 Budget vs Forecast
A1: Budget vs Forecast Structure
A2: Template for future budget vs actual tracking
A4: Financial Metric | B4: Jan Budget | C4: Feb Budget | D4: Mar Budget | E4: Apr Budget | F4: May Budget | G4: Jun Budget | H4: Jul Budget | I4: Aug Budget | J4: Sep Budget | K4: Oct Budget | L4: Nov Budget | M4: Dec Budget | N4: FY Budget | O4: Actual | P4: Variance
A5: Revenue | B5: ='03 Revenue Budget'!B11 -> 128709.76 | C5: ='03 Revenue Budget'!C11 -> 147558.05 | D5: ='03 Revenue Budget'!D11 -> 166406.47 | E5: ='03 Revenue Budget'!E11 -> 166445.06 | F5: ='03 Revenue Budget'!F11 -> 185293.74 | G5: ='03 Revenue Budget'!G11 -> 185332.59 | H5: ='03 Revenue Budget'!H11 -> 204181.53 | I5: ='03 Revenue Budget'!I11 -> 204220.63 | ... M5: ='03 Revenue Budget'!M11 -> 147948.49 | N5: =SUM(B5:M5) -> 2073754.3 | P5: =O5-N5 -> -2073754.3
A6: Gross Profit | B6: ='03 Revenue Budget'!B11-'05 Construction Cost Budget'!B49 -> 46610.26 | C6: ='03 Revenue Budget'!C11-'05 Construction Cost Budget'!C49 -> 65458.553 | D6: ='03 Revenue Budget'!D11-'05 Construction Cost Budget'!D49 -> 72578.474 | E6: ='03 Revenue Budget'!E11-'05 Construction Cost Budget'!E49 -> 72617.064 | F6: ='03 Revenue Budget'!F11-'05 Construction Cost Budget'!F49 -> 79737.242 | G6: ='03 Revenue Budget'!G11-'05 Construction Cost Budget'!G49 -> 79776.089 | H6: ='03 Revenue Budget'!H11-'05 Construction Cost Budget'!H49 -> 98625.025 | I6: ='03 Revenue Budget'!I11-'05 Construction Cost Budget'!I49 -> 86935.632 | ... M6: ='03 Revenue Budget'!M11-'05 Construction Cost Budget'!M49 -> 77577.485 | N6: =SUM(B6:M6) -> 900904.32 | P6: =O6-N6 -> -900904.32
A7: EBITDA | B7: ='03 Revenue Budget'!B11-'05 Construction Cost Budget'!B49-'06 Sales and Marketing Budget'!B10-'07 Corporate Opex'!B15 -> 37238.82 | C7: ='03 Revenue Budget'!C11-'05 Construction Cost Budget'!C49-'06 Sales and Marketing Budget'!C10-'07 Corporate Opex'!C15 -> 56086.513 | D7: ='03 Revenue Budget'!D11-'05 Construction Cost Budget'!D49-'06 Sales and Marketing Budget'!D10-'07 Corporate Opex'!D15 -> 63110.832 | E7: ='03 Revenue Budget'!E11-'05 Construction Cost Budget'!E49-'06 Sales and Marketing Budget'!E10-'07 Corporate Opex'!E15 -> 63148.818 | F7: ='03 Revenue Budget'!F11-'05 Construction Cost Budget'!F49-'06 Sales and Marketing Budget'!F10-'07 Corporate Opex'!F15 -> 70173.39 | G7: ='03 Revenue Budget'!G11-'05 Construction Cost Budget'!G49-'06 Sales and Marketing Budget'!G10-'07 Corporate Opex'!G15 -> 70211.629 | H7: ='03 Revenue Budget'!H11-'05 Construction Cost Budget'!H49-'06 Sales and Marketing Budget'!H10-'07 Corporate Opex'!H15 -> 88964.955 | I7: ='03 Revenue Budget'!I11-'05 Construction Cost Budget'!I49-'06 Sales and Marketing Budget'!I10-'07 Corporate Opex'!I15 -> 77274.949 | ... M7: ='03 Revenue Budget'!M11-'05 Construction Cost Budget'!M49-'06 Sales and Marketing Budget'!M10-'07 Corporate Opex'!M15 -> 64054.054 | N7: =SUM(B7:M7) -> 782741.72 | P7: =O7-N7 -> -782741.72
A8: Operating Expenses | B8: ='06 Sales and Marketing Budget'!B10+'07 Corporate Opex'!B15 -> 9371.44 | C8: ='06 Sales and Marketing Budget'!C10+'07 Corporate Opex'!C15 -> 9372.04 | D8: ='06 Sales and Marketing Budget'!D10+'07 Corporate Opex'!D15 -> 9467.642 | E8: ='06 Sales and Marketing Budget'!E10+'07 Corporate Opex'!E15 -> 9468.246 | F8: ='06 Sales and Marketing Budget'!F10+'07 Corporate Opex'!F15 -> 9563.852 | G8: ='06 Sales and Marketing Budget'!G10+'07 Corporate Opex'!G15 -> 9564.4601 | H8: ='06 Sales and Marketing Budget'!H10+'07 Corporate Opex'!H15 -> 9660.0701 | I8: ='06 Sales and Marketing Budget'!I10+'07 Corporate Opex'!I15 -> 9660.6822 | ... M8: ='06 Sales and Marketing Budget'!M10+'07 Corporate Opex'!M15 -> 13523.431 | N8: =SUM(B8:M8) -> 118162.6 | P8: =O8-N8 -> -118162.6
A9: Net Profit | B9: ='03 Revenue Budget'!B11-'05 Construction Cost Budget'!B49-'06 Sales and Marketing Budget'!B10-'07 Corporate Opex'!B15-'10 Financing Cost'!B64 -> 29840.487 | C9: ='03 Revenue Budget'!C11-'05 Construction Cost Budget'!C49-'06 Sales and Marketing Budget'!C10-'07 Corporate Opex'!C15-'10 Financing Cost'!C64 -> 51020.434 | D9: ='03 Revenue Budget'!D11-'05 Construction Cost Budget'!D49-'06 Sales and Marketing Budget'!D10-'07 Corporate Opex'!D15-'10 Financing Cost'!D64 -> 57891.959 | E9: ='03 Revenue Budget'!E11-'05 Construction Cost Budget'!E49-'06 Sales and Marketing Budget'!E10-'07 Corporate Opex'!E15-'10 Financing Cost'!E64 -> 57735.978 | F9: ='03 Revenue Budget'!F11-'05 Construction Cost Budget'!F49-'06 Sales and Marketing Budget'!F10-'07 Corporate Opex'!F15-'10 Financing Cost'!F64 -> 64534.291 | G9: ='03 Revenue Budget'!G11-'05 Construction Cost Budget'!G49-'06 Sales and Marketing Budget'!G10-'07 Corporate Opex'!G15-'10 Financing Cost'!G64 -> 61862.391 | H9: ='03 Revenue Budget'!H11-'05 Construction Cost Budget'!H49-'06 Sales and Marketing Budget'!H10-'07 Corporate Opex'!H15-'10 Financing Cost'!H64 -> 83002.453 | I9: ='03 Revenue Budget'!I11-'05 Construction Cost Budget'!I49-'06 Sales and Marketing Budget'!I10-'07 Corporate Opex'!I15-'10 Financing Cost'!I64 -> 71246.427 | ... M9: ='03 Revenue Budget'!M11-'05 Construction Cost Budget'!M49-'06 Sales and Marketing Budget'!M10-'07 Corporate Opex'!M15-'10 Financing Cost'!M64 -> 57697.056 | N9: =SUM(B9:M9) -> 708365.85 | P9: =O9-N9 -> -708365.85
A10: Closing Cash | B10: ='11 Cash Flow Budget'!B28 -> 133345.65 | C10: ='11 Cash Flow Budget'!C28 -> 157655.39 | D10: ='11 Cash Flow Budget'!D28 -> 199103.53 | E10: ='11 Cash Flow Budget'!E28 -> 238699.61 | F10: ='11 Cash Flow Budget'!F28 -> 289304.61 | G10: ='11 Cash Flow Budget'!G28 -> 307541.78 | H10: ='11 Cash Flow Budget'!H28 -> 335123.45 | I10: ='11 Cash Flow Budget'!I28 -> 382988.16 | ... M10: ='11 Cash Flow Budget'!M28 -> 341931.51 | N10: =M5 -> 147948.49 | P10: =O10-N10 -> -147948.49

Sheet 15 Sensitivity
A1: Sensitivity Analysis
A2: Impact on EBITDA and closing cash from key budget sensitivities
A4: Closing Cash Sensitivity: Sales Price vs Construction Cost
B5: -10% | C5: -5% | D5: Base | E5: +5% | F5: +10%
A6: -0.1 | B6: ='11 Cash Flow Budget'!N28*0.975 -> 3424180.9 | C6: ='11 Cash Flow Budget'!N28*0.9275 -> 3257361.9 | D6: ='11 Cash Flow Budget'!N28*0.88 -> 3090542.8 | E6: ='11 Cash Flow Budget'!N28*0.8325 -> 2923723.7 | F6: ='11 Cash Flow Budget'!N28*0.785 -> 2756904.6
A7: -0.05 | B7: ='11 Cash Flow Budget'!N28*1.035 -> 3634899.8 | C7: ='11 Cash Flow Budget'!N28*0.9875 -> 3468080.7 | D7: ='11 Cash Flow Budget'!N28*0.94 -> 3301261.6 | E7: ='11 Cash Flow Budget'!N28*0.8925 -> 3134442.5 | F7: ='11 Cash Flow Budget'!N28*0.845 -> 2967623.5
A8: 0 | B8: ='11 Cash Flow Budget'!N28*1.095 -> 3845618.6 | C8: ='11 Cash Flow Budget'!N28*1.0475 -> 3678799.5 | D8: ='11 Cash Flow Budget'!N28*1 -> 3511980.4 | E8: ='11 Cash Flow Budget'!N28*0.9525 -> 3345161.4 | F8: ='11 Cash Flow Budget'!N28*0.905 -> 3178342.3
A9: 0.05 | B9: ='11 Cash Flow Budget'!N28*1.155 -> 4056337.4 | C9: ='11 Cash Flow Budget'!N28*1.1075 -> 3889518.3 | D9: ='11 Cash Flow Budget'!N28*1.06 -> 3722699.3 | E9: ='11 Cash Flow Budget'!N28*1.0125 -> 3555880.2 | F9: ='11 Cash Flow Budget'!N28*0.965 -> 3389061.1
A10: 0.1 | B10: ='11 Cash Flow Budget'!N28*1.215 -> 4267056.2 | C10: ='11 Cash Flow Budget'!N28*1.1675 -> 4100237.2 | D10: ='11 Cash Flow Budget'!N28*1.12 -> 3933418.1 | E10: ='11 Cash Flow Budget'!N28*1.0725 -> 3766599 | F10: ='11 Cash Flow Budget'!N28*1.025 -> 3599780
A12: EBITDA Sensitivity: Sales Velocity vs Interest Rate
B13: -100bps | C13: -50bps | D13: Base | E13: +50bps | F13: +100bps
A14: -0.1 | B14: ='14 Budget vs Forecast'!N7*0.935 -> 731863.51 | C14: ='14 Budget vs Forecast'!N7*0.925 -> 724036.09 | D14: ='14 Budget vs Forecast'!N7*0.915 -> 716208.67 | E14: ='14 Budget vs Forecast'!N7*0.905 -> 708381.26 | F14: ='14 Budget vs Forecast'!N7*0.895 -> 700553.84
A15: -0.05 | B15: ='14 Budget vs Forecast'!N7*0.9775 -> 765130.03 | C15: ='14 Budget vs Forecast'!N7*0.9675 -> 757302.61 | D15: ='14 Budget vs Forecast'!N7*0.9575 -> 749475.2 | E15: ='14 Budget vs Forecast'!N7*0.9475 -> 741647.78 | F15: ='14 Budget vs Forecast'!N7*0.9375 -> 733820.36
A16: 0 | B16: ='14 Budget vs Forecast'!N7*1.02 -> 798396.55 | C16: ='14 Budget vs Forecast'!N7*1.01 -> 790569.14 | D16: ='14 Budget vs Forecast'!N7*1 -> 782741.72 | E16: ='14 Budget vs Forecast'!N7*0.99 -> 774914.3 | F16: ='14 Budget vs Forecast'!N7*0.98 -> 767086.89
A17: 0.05 | B17: ='14 Budget vs Forecast'!N7*1.0625 -> 831663.08 | C17: ='14 Budget vs Forecast'!N7*1.0525 -> 823835.66 | D17: ='14 Budget vs Forecast'!N7*1.0425 -> 816008.24 | E17: ='14 Budget vs Forecast'!N7*1.0325 -> 808180.83 | F17: ='14 Budget vs Forecast'!N7*1.0225 -> 800353.41
A18: 0.1 | B18: ='14 Budget vs Forecast'!N7*1.105 -> 864929.6 | C18: ='14 Budget vs Forecast'!N7*1.095 -> 857102.18 | D18: ='14 Budget vs Forecast'!N7*1.085 -> 849274.77 | E18: ='14 Budget vs Forecast'!N7*1.075 -> 841447.35 | F18: ='14 Budget vs Forecast'!N7*1.065 -> 833619.93

Sheet 16 Risk Commentary
A1: Risk Commentary
A2: Qualitative budget narrative for management, board and investor review
A4: Key Budget Assumptions
A5: The FY2026 budget assumes continued resilience in Dubai luxury residential demand, modest selling price appreciation of approximately 4%, and steady project execution across the four core developments. Off-plan collections are modeled using a 30% in-year customer deposit profile, with escrow releases capped at 85% of eligible construction spend.
A8: Construction budgets assume 5% cost inflation versus the prior planning cycle and continued pressure on façade, MEP and specialist subcontractor packages. The budget also assumes no major scope changes or regulatory delays beyond ordinary permitting and handover coordination.
A11: Major financial risks include slower off-plan absorption, handover timing slippage, contractor claims, higher-than-budgeted interest costs, and tighter escrow release mechanics. These risks would primarily pressure EBITDA conversion, working capital, and closing cash.
A14: Market demand assumptions reflect luxury waterfront and branded residence pricing strength, continued broker channel support, and stable international buyer activity. Downside exposure remains concentrated in larger-ticket villa inventory and branded residence sell-through if macro liquidity tightens.
A17: Construction Risk Factors
A18: • | B18: Main contractor cash flow and subcontractor coordination across active sites
A19: • | B19: Façade lead times and imported material cost volatility
A20: • | B20: MEP procurement timing and commissioning readiness
A21: • | B21: Infrastructure interfaces with utilities and external authorities
A23: Management Actions
A24: • | B24: Maintain monthly cost-to-complete reviews and contractor claim registers.
A25: • | B25: Reforecast project collections and escrow releases alongside monthly sales performance.
A26: • | B26: Preserve corporate liquidity headroom through staged CapEx and controlled discretionary spend.
A27: • | B27: Update lender reporting packs monthly and monitor covenant headroom on all facilities.

Sheet 99_Helper
A1: Helper Calculations
A3: Metric | B3: Jan | C3: Feb | D3: Mar | E3: Apr | F3: May | G3: Jun | H3: Jul | I3: Aug | J3: Sep | K3: Oct | L3: Nov | M3: Dec
A4: Marina Residences Tower
A5: Units Sold | B5: ='02 Budget Assumptions'!$C$35*'02 Budget Assumptions'!B$28 -> 5.7 | C5: ='02 Budget Assumptions'!$C$35*'02 Budget Assumptions'!C$28 -> 6.65 | D5: ='02 Budget Assumptions'!$C$35*'02 Budget Assumptions'!D$28 -> 7.6 | E5: ='02 Budget Assumptions'!$C$35*'02 Budget Assumptions'!E$28 -> 7.6 | F5: ='02 Budget Assumptions'!$C$35*'02 Budget Assumptions'!F$28 -> 8.55 | G5: ='02 Budget Assumptions'!$C$35*'02 Budget Assumptions'!G$28 -> 8.55 | H5: ='02 Budget Assumptions'!$C$35*'02 Budget Assumptions'!H$28 -> 9.5 | I5: ='02 Budget Assumptions'!$C$35*'02 Budget Assumptions'!I$28 -> 9.5 | ... M5: ='02 Budget Assumptions'!$C$35*'02 Budget Assumptions'!M$28 -> 6.65
A6: Sales Value | B6: =B5*'02 Budget Assumptions'!$D$35*(1+'02 Budget Assumptions'!$C$7) -> 36753.6 | C6: =C5*'02 Budget Assumptions'!$D$35*(1+'02 Budget Assumptions'!$C$7) -> 42879.2 | D6: =D5*'02 Budget Assumptions'!$D$35*(1+'02 Budget Assumptions'!$C$7) -> 49004.8 | E6: =E5*'02 Budget Assumptions'!$D$35*(1+'02 Budget Assumptions'!$C$7) -> 49004.8 | F6: =F5*'02 Budget Assumptions'!$D$35*(1+'02 Budget Assumptions'!$C$7) -> 55130.4 | G6: =G5*'02 Budget Assumptions'!$D$35*(1+'02 Budget Assumptions'!$C$7) -> 55130.4 | H6: =H5*'02 Budget Assumptions'!$D$35*(1+'02 Budget Assumptions'!$C$7) -> 61256 | I6: =I5*'02 Budget Assumptions'!$D$35*(1+'02 Budget Assumptions'!$C$7) -> 61256 | ... M6: =M5*'02 Budget Assumptions'!$D$35*(1+'02 Budget Assumptions'!$C$7) -> 42879.2
A7: Off-plan Revenue | B7: =B6*'02 Budget Assumptions'!$E$35 -> 25727.52 | C7: =C6*'02 Budget Assumptions'!$E$35 -> 30015.44 | D7: =D6*'02 Budget Assumptions'!$E$35 -> 34303.36 | E7: =E6*'02 Budget Assumptions'!$E$35 -> 34303.36 | F7: =F6*'02 Budget Assumptions'!$E$35 -> 38591.28 | G7: =G6*'02 Budget Assumptions'!$E$35 -> 38591.28 | H7: =H6*'02 Budget Assumptions'!$E$35 -> 42879.2 | I7: =I6*'02 Budget Assumptions'!$E$35 -> 42879.2 | ... M7: =M6*'02 Budget Assumptions'!$E$35 -> 30015.44
A8: Completed Revenue | B8: =B6*(1-'02 Budget Assumptions'!$E$35) -> 11026.08 | C8: =C6*(1-'02 Budget Assumptions'!$E$35) -> 12863.76 | D8: =D6*(1-'02 Budget Assumptions'!$E$35) -> 14701.44 | E8: =E6*(1-'02 Budget Assumptions'!$E$35) -> 14701.44 | F8: =F6*(1-'02 Budget Assumptions'!$E$35) -> 16539.12 | G8: =G6*(1-'02 Budget Assumptions'!$E$35) -> 16539.12 | H8: =H6*(1-'02 Budget Assumptions'!$E$35) -> 18376.8 | I8: =I6*(1-'02 Budget Assumptions'!$E$35) -> 18376.8 | ... M8: =M6*(1-'02 Budget Assumptions'!$E$35) -> 12863.76
A9: Customer Deposits | B9: =B6*'02 Budget Assumptions'!$C$9 -> 11026.08 | C9: =C6*'02 Budget Assumptions'!$C$9 -> 12863.76 | D9: =D6*'02 Budget Assumptions'!$C$9 -> 14701.44 | E9: =E6*'02 Budget Assumptions'!$C$9 -> 14701.44 | F9: =F6*'02 Budget Assumptions'!$C$9 -> 16539.12 | G9: =G6*'02 Budget Assumptions'!$C$9 -> 16539.12 | H9: =H6*'02 Budget Assumptions'!$C$9 -> 18376.8 | I9: =I6*'02 Budget Assumptions'!$C$9 -> 18376.8 | ... M9: =M6*'02 Budget Assumptions'!$C$9 -> 12863.76
A10: Escrow Release | B10: =MIN(B9,B11*'02 Budget Assumptions'!$C$10) -> 11026.08 | C10: =MIN(C9,C11*'02 Budget Assumptions'!$C$10) -> 12863.76 | D10: =MIN(D9,D11*'02 Budget Assumptions'!$C$10) -> 14701.44 | E10: =MIN(E9,E11*'02 Budget Assumptions'!$C$10) -> 14701.44 | F10: =MIN(F9,F11*'02 Budget Assumptions'!$C$10) -> 16539.12 | G10: =MIN(G9,G11*'02 Budget Assumptions'!$C$10) -> 16539.12 | H10: =MIN(H9,H11*'02 Budget Assumptions'!$C$10) -> 18376.8 | I10: =MIN(I9,I11*'02 Budget Assumptions'!$C$10) -> 18376.8 | ... M10: =MIN(M9,M11*'02 Budget Assumptions'!$C$10) -> 12863.76
A11: Construction Spend | B11: ='02 Budget Assumptions'!$F$35*'02 Budget Assumptions'!B$29*(1+'02 Budget Assumptions'!$C$6) -> 23887.5 | C11: ='02 Budget Assumptions'!$F$35*'02 Budget Assumptions'!C$29*(1+'02 Budget Assumptions'!$C$6) -> 23887.5 | D11: ='02 Budget Assumptions'!$F$35*'02 Budget Assumptions'!D$29*(1+'02 Budget Assumptions'!$C$6) -> 27300 | E11: ='02 Budget Assumptions'!$F$35*'02 Budget Assumptions'!E$29*(1+'02 Budget Assumptions'!$C$6) -> 27300 | F11: ='02 Budget Assumptions'!$F$35*'02 Budget Assumptions'!F$29*(1+'02 Budget Assumptions'!$C$6) -> 30712.5 | G11: ='02 Budget Assumptions'!$F$35*'02 Budget Assumptions'!G$29*(1+'02 Budget Assumptions'!$C$6) -> 30712.5 | H11: ='02 Budget Assumptions'!$F$35*'02 Budget Assumptions'!H$29*(1+'02 Budget Assumptions'!$C$6) -> 30712.5 | I11: ='02 Budget Assumptions'!$F$35*'02 Budget Assumptions'!I$29*(1+'02 Budget Assumptions'!$C$6) -> 34125 | ... M11: ='02 Budget Assumptions'!$F$35*'02 Budget Assumptions'!M$29*(1+'02 Budget Assumptions'!$C$6) -> 20475
A13: Palm Waterfront Villas
A14: Units Sold | B14: ='02 Budget Assumptions'!$C$36*'02 Budget Assumptions'!B$28 -> 1.08 | C14: ='02 Budget Assumptions'!$C$36*'02 Budget Assumptions'!C$28 -> 1.26 | D14: ='02 Budget Assumptions'!$C$36*'02 Budget Assumptions'!D$28 -> 1.44 | E14: ='02 Budget Assumptions'!$C$36*'02 Budget Assumptions'!E$28 -> 1.44 | F14: ='02 Budget Assumptions'!$C$36*'02 Budget Assumptions'!F$28 -> 1.62 | G14: ='02 Budget Assumptions'!$C$36*'02 Budget Assumptions'!G$28 -> 1.62 | H14: ='02 Budget Assumptions'!$C$36*'02 Budget Assumptions'!H$28 -> 1.8 | I14: ='02 Budget Assumptions'!$C$36*'02 Budget Assumptions'!I$28 -> 1.8 | ... M14: ='02 Budget Assumptions'!$C$36*'02 Budget Assumptions'!M$28 -> 1.26
A15: Sales Value | B15: =B14*'02 Budget Assumptions'!$D$36*(1+'02 Budget Assumptions'!$C$7) -> 24710.4 | C15: =C14*'02 Budget Assumptions'!$D$36*(1+'02 Budget Assumptions'!$C$7) -> 28828.8 | D15: =D14*'02 Budget Assumptions'!$D$36*(1+'02 Budget Assumptions'!$C$7) -> 32947.2 | E15: =E14*'02 Budget Assumptions'!$D$36*(1+'02 Budget Assumptions'!$C$7) -> 32947.2 | F15: =F14*'02 Budget Assumptions'!$D$36*(1+'02 Budget Assumptions'!$C$7) -> 37065.6 | G15: =G14*'02 Budget Assumptions'!$D$36*(1+'02 Budget Assumptions'!$C$7) -> 37065.6 | H15: =H14*'02 Budget Assumptions'!$D$36*(1+'02 Budget Assumptions'!$C$7) -> 41184 | I15: =I14*'02 Budget Assumptions'!$D$36*(1+'02 Budget Assumptions'!$C$7) -> 41184 | ... M15: =M14*'02 Budget Assumptions'!$D$36*(1+'02 Budget Assumptions'!$C$7) -> 28828.8
A16: Off-plan Revenue | B16: =B15*'02 Budget Assumptions'!$E$36 -> 12355.2 | C16: =C15*'02 Budget Assumptions'!$E$36 -> 14414.4 | D16: =D15*'02 Budget Assumptions'!$E$36 -> 16473.6 | E16: =E15*'02 Budget Assumptions'!$E$36 -> 16473.6 | F16: =F15*'02 Budget Assumptions'!$E$36 -> 18532.8 | G16: =G15*'02 Budget Assumptions'!$E$36 -> 18532.8 | H16: =H15*'02 Budget Assumptions'!$E$36 -> 20592 | I16: =I15*'02 Budget Assumptions'!$E$36 -> 20592 | ... M16: =M15*'02 Budget Assumptions'!$E$36 -> 14414.4
A17: Completed Revenue | B17: =B15*(1-'02 Budget Assumptions'!$E$36) -> 12355.2 | C17: =C15*(1-'02 Budget Assumptions'!$E$36) -> 14414.4 | D17: =D15*(1-'02 Budget Assumptions'!$E$36) -> 16473.6 | E17: =E15*(1-'02 Budget Assumptions'!$E$36) -> 16473.6 | F17: =F15*(1-'02 Budget Assumptions'!$E$36) -> 18532.8 | G17: =G15*(1-'02 Budget Assumptions'!$E$36) -> 18532.8 | H17: =H15*(1-'02 Budget Assumptions'!$E$36) -> 20592 | I17: =I15*(1-'02 Budget Assumptions'!$E$36) -> 20592 | ... M17: =M15*(1-'02 Budget Assumptions'!$E$36) -> 14414.4
A18: Customer Deposits | B18: =B15*'02 Budget Assumptions'!$C$9 -> 7413.12 | C18: =C15*'02 Budget Assumptions'!$C$9 -> 8648.64 | D18: =D15*'02 Budget Assumptions'!$C$9 -> 9884.16 | E18: =E15*'02 Budget Assumptions'!$C$9 -> 9884.16 | F18: =F15*'02 Budget Assumptions'!$C$9 -> 11119.68 | G18: =G15*'02 Budget Assumptions'!$C$9 -> 11119.68 | H18: =H15*'02 Budget Assumptions'!$C$9 -> 12355.2 | I18: =I15*'02 Budget Assumptions'!$C$9 -> 12355.2 | ... M18: =M15*'02 Budget Assumptions'!$C$9 -> 8648.64
A19: Escrow Release | B19: =MIN(B18,B20*'02 Budget Assumptions'!$C$10) -> 7413.12 | C19: =MIN(C18,C20*'02 Budget Assumptions'!$C$10) -> 8648.64 | D19: =MIN(D18,D20*'02 Budget Assumptions'!$C$10) -> 9884.16 | E19: =MIN(E18,E20*'02 Budget Assumptions'!$C$10) -> 9884.16 | F19: =MIN(F18,F20*'02 Budget Assumptions'!$C$10) -> 11119.68 | G19: =MIN(G18,G20*'02 Budget Assumptions'!$C$10) -> 11119.68 | H19: =MIN(H18,H20*'02 Budget Assumptions'!$C$10) -> 12355.2 | I19: =MIN(I18,I20*'02 Budget Assumptions'!$C$10) -> 12355.2 | ... M19: =MIN(M18,M20*'02 Budget Assumptions'!$C$10) -> 8648.64
A20: Construction Spend | B20: ='02 Budget Assumptions'!$F$36*'02 Budget Assumptions'!B$29*(1+'02 Budget Assumptions'!$C$6) -> 16758 | C20: ='02 Budget Assumptions'!$F$36*'02 Budget Assumptions'!C$29*(1+'02 Budget Assumptions'!$C$6) -> 16758 | D20: ='02 Budget Assumptions'!$F$36*'02 Budget Assumptions'!D$29*(1+'02 Budget Assumptions'!$C$6) -> 19152 | E20: ='02 Budget Assumptions'!$F$36*'02 Budget Assumptions'!E$29*(1+'02 Budget Assumptions'!$C$6) -> 19152 | F20: ='02 Budget Assumptions'!$F$36*'02 Budget Assumptions'!F$29*(1+'02 Budget Assumptions'!$C$6) -> 21546 | G20: ='02 Budget Assumptions'!$F$36*'02 Budget Assumptions'!G$29*(1+'02 Budget Assumptions'!$C$6) -> 21546 | H20: ='02 Budget Assumptions'!$F$36*'02 Budget Assumptions'!H$29*(1+'02 Budget Assumptions'!$C$6) -> 21546 | I20: ='02 Budget Assumptions'!$F$36*'02 Budget Assumptions'!I$29*(1+'02 Budget Assumptions'!$C$6) -> 23940 | ... M20: ='02 Budget Assumptions'!$F$36*'02 Budget Assumptions'!M$29*(1+'02 Budget Assumptions'!$C$6) -> 14364
A22: Downtown Mixed-Use Development
A23: Units Sold | B23: ='02 Budget Assumptions'!$C$37*'02 Budget Assumptions'!B$28 -> 4.5 | C23: ='02 Budget Assumptions'!$C$37*'02 Budget Assumptions'!C$28 -> 5.25 | D23: ='02 Budget Assumptions'!$C$37*'02 Budget Assumptions'!D$28 -> 6 | E23: ='02 Budget Assumptions'!$C$37*'02 Budget Assumptions'!E$28 -> 6 | F23: ='02 Budget Assumptions'!$C$37*'02 Budget Assumptions'!F$28 -> 6.75 | G23: ='02 Budget Assumptions'!$C$37*'02 Budget Assumptions'!G$28 -> 6.75 | H23: ='02 Budget Assumptions'!$C$37*'02 Budget Assumptions'!H$28 -> 7.5 | I23: ='02 Budget Assumptions'!$C$37*'02 Budget Assumptions'!I$28 -> 7.5 | ... M23: ='02 Budget Assumptions'!$C$37*'02 Budget Assumptions'!M$28 -> 5.25
A24: Sales Value | B24: =B23*'02 Budget Assumptions'!$D$37*(1+'02 Budget Assumptions'!$C$7) -> 23166 | C24: =C23*'02 Budget Assumptions'!$D$37*(1+'02 Budget Assumptions'!$C$7) -> 27027 | D24: =D23*'02 Budget Assumptions'!$D$37*(1+'02 Budget Assumptions'!$C$7) -> 30888 | E24: =E23*'02 Budget Assumptions'!$D$37*(1+'02 Budget Assumptions'!$C$7) -> 30888 | F24: =F23*'02 Budget Assumptions'!$D$37*(1+'02 Budget Assumptions'!$C$7) -> 34749 | G24: =G23*'02 Budget Assumptions'!$D$37*(1+'02 Budget Assumptions'!$C$7) -> 34749 | H24: =H23*'02 Budget Assumptions'!$D$37*(1+'02 Budget Assumptions'!$C$7) -> 38610 | I24: =I23*'02 Budget Assumptions'!$D$37*(1+'02 Budget Assumptions'!$C$7) -> 38610 | ... M24: =M23*'02 Budget Assumptions'!$D$37*(1+'02 Budget Assumptions'!$C$7) -> 27027
A25: Off-plan Revenue | B25: =B24*'02 Budget Assumptions'!$E$37 -> 18532.8 | C25: =C24*'02 Budget Assumptions'!$E$37 -> 21621.6 | D25: =D24*'02 Budget Assumptions'!$E$37 -> 24710.4 | E25: =E24*'02 Budget Assumptions'!$E$37 -> 24710.4 | F25: =F24*'02 Budget Assumptions'!$E$37 -> 27799.2 | G25: =G24*'02 Budget Assumptions'!$E$37 -> 27799.2 | H25: =H24*'02 Budget Assumptions'!$E$37 -> 30888 | I25: =I24*'02 Budget Assumptions'!$E$37 -> 30888 | ... M25: =M24*'02 Budget Assumptions'!$E$37 -> 21621.6
A26: Completed Revenue | B26: =B24*(1-'02 Budget Assumptions'!$E$37) -> 4633.2 | C26: =C24*(1-'02 Budget Assumptions'!$E$37) -> 5405.4 | D26: =D24*(1-'02 Budget Assumptions'!$E$37) -> 6177.6 | E26: =E24*(1-'02 Budget Assumptions'!$E$37) -> 6177.6 | F26: =F24*(1-'02 Budget Assumptions'!$E$37) -> 6949.8 | G26: =G24*(1-'02 Budget Assumptions'!$E$37) -> 6949.8 | H26: =H24*(1-'02 Budget Assumptions'!$E$37) -> 7722 | I26: =I24*(1-'02 Budget Assumptions'!$E$37) -> 7722 | ... M26: =M24*(1-'02 Budget Assumptions'!$E$37) -> 5405.4
A27: Customer Deposits | B27: =B24*'02 Budget Assumptions'!$C$9 -> 6949.8 | C27: =C24*'02 Budget Assumptions'!$C$9 -> 8108.1 | D27: =D24*'02 Budget Assumptions'!$C$9 -> 9266.4 | E27: =E24*'02 Budget Assumptions'!$C$9 -> 9266.4 | F27: =F24*'02 Budget Assumptions'!$C$9 -> 10424.7 | G27: =G24*'02 Budget Assumptions'!$C$9 -> 10424.7 | H27: =H24*'02 Budget Assumptions'!$C$9 -> 11583 | I27: =I24*'02 Budget Assumptions'!$C$9 -> 11583 | ... M27: =M24*'02 Budget Assumptions'!$C$9 -> 8108.1
A28: Escrow Release | B28: =MIN(B27,B29*'02 Budget Assumptions'!$C$10) -> 6949.8 | C28: =MIN(C27,C29*'02 Budget Assumptions'!$C$10) -> 8108.1 | D28: =MIN(D27,D29*'02 Budget Assumptions'!$C$10) -> 9266.4 | E28: =MIN(E27,E29*'02 Budget Assumptions'!$C$10) -> 9266.4 | F28: =MIN(F27,F29*'02 Budget Assumptions'!$C$10) -> 10424.7 | G28: =MIN(G27,G29*'02 Budget Assumptions'!$C$10) -> 10424.7 | H28: =MIN(H27,H29*'02 Budget Assumptions'!$C$10) -> 11583 | I28: =MIN(I27,I29*'02 Budget Assumptions'!$C$10) -> 11583 | ... M28: =MIN(M27,M29*'02 Budget Assumptions'!$C$10) -> 8108.1
A29: Construction Spend | B29: ='02 Budget Assumptions'!$F$37*'02 Budget Assumptions'!B$29*(1+'02 Budget Assumptions'!$C$6) -> 18081 | C29: ='02 Budget Assumptions'!$F$37*'02 Budget Assumptions'!C$29*(1+'02 Budget Assumptions'!$C$6) -> 18081 | D29: ='02 Budget Assumptions'!$F$37*'02 Budget Assumptions'!D$29*(1+'02 Budget Assumptions'!$C$6) -> 20664 | E29: ='02 Budget Assumptions'!$F$37*'02 Budget Assumptions'!E$29*(1+'02 Budget Assumptions'!$C$6) -> 20664 | F29: ='02 Budget Assumptions'!$F$37*'02 Budget Assumptions'!F$29*(1+'02 Budget Assumptions'!$C$6) -> 23247 | G29: ='02 Budget Assumptions'!$F$37*'02 Budget Assumptions'!G$29*(1+'02 Budget Assumptions'!$C$6) -> 23247 | H29: ='02 Budget Assumptions'!$F$37*'02 Budget Assumptions'!H$29*(1+'02 Budget Assumptions'!$C$6) -> 23247 | I29: ='02 Budget Assumptions'!$F$37*'02 Budget Assumptions'!I$29*(1+'02 Budget Assumptions'!$C$6) -> 25830 | ... M29: ='02 Budget Assumptions'!$F$37*'02 Budget Assumptions'!M$29*(1+'02 Budget Assumptions'!$C$6) -> 15498
A31: Jumeirah Branded Residences
A32: Units Sold | B32: ='02 Budget Assumptions'!$C$38*'02 Budget Assumptions'!B$28 -> 3.12 | C32: ='02 Budget Assumptions'!$C$38*'02 Budget Assumptions'!C$28 -> 3.64 | D32: ='02 Budget Assumptions'!$C$38*'02 Budget Assumptions'!D$28 -> 4.16 | E32: ='02 Budget Assumptions'!$C$38*'02 Budget Assumptions'!E$28 -> 4.16 | F32: ='02 Budget Assumptions'!$C$38*'02 Budget Assumptions'!F$28 -> 4.68 | G32: ='02 Budget Assumptions'!$C$38*'02 Budget Assumptions'!G$28 -> 4.68 | H32: ='02 Budget Assumptions'!$C$38*'02 Budget Assumptions'!H$28 -> 5.2 | I32: ='02 Budget Assumptions'!$C$38*'02 Budget Assumptions'!I$28 -> 5.2 | ... M32: ='02 Budget Assumptions'!$C$38*'02 Budget Assumptions'!M$28 -> 3.64
A33: Sales Value | B33: =B32*'02 Budget Assumptions'!$D$38*(1+'02 Budget Assumptions'!$C$7) -> 28229.76 | C33: =C32*'02 Budget Assumptions'!$D$38*(1+'02 Budget Assumptions'!$C$7) -> 32934.72 | D33: =D32*'02 Budget Assumptions'!$D$38*(1+'02 Budget Assumptions'!$C$7) -> 37639.68 | E33: =E32*'02 Budget Assumptions'!$D$38*(1+'02 Budget Assumptions'!$C$7) -> 37639.68 | F33: =F32*'02 Budget Assumptions'!$D$38*(1+'02 Budget Assumptions'!$C$7) -> 42344.64 | G33: =G32*'02 Budget Assumptions'!$D$38*(1+'02 Budget Assumptions'!$C$7) -> 42344.64 | H33: =H32*'02 Budget Assumptions'!$D$38*(1+'02 Budget Assumptions'!$C$7) -> 47049.6 | I33: =I32*'02 Budget Assumptions'!$D$38*(1+'02 Budget Assumptions'!$C$7) -> 47049.6 | ... M33: =M32*'02 Budget Assumptions'!$D$38*(1+'02 Budget Assumptions'!$C$7) -> 32934.72
A34: Off-plan Revenue | B34: =B33*'02 Budget Assumptions'!$E$38 -> 16937.856 | C34: =C33*'02 Budget Assumptions'!$E$38 -> 19760.832 | D34: =D33*'02 Budget Assumptions'!$E$38 -> 22583.808 | E34: =E33*'02 Budget Assumptions'!$E$38 -> 22583.808 | F34: =F33*'02 Budget Assumptions'!$E$38 -> 25406.784 | G34: =G33*'02 Budget Assumptions'!$E$38 -> 25406.784 | H34: =H33*'02 Budget Assumptions'!$E$38 -> 28229.76 | I34: =I33*'02 Budget Assumptions'!$E$38 -> 28229.76 | ... M34: =M33*'02 Budget Assumptions'!$E$38 -> 19760.832
A35: Completed Revenue | B35: =B33*(1-'02 Budget Assumptions'!$E$38) -> 11291.904 | C35: =C33*(1-'02 Budget Assumptions'!$E$38) -> 13173.888 | D35: =D33*(1-'02 Budget Assumptions'!$E$38) -> 15055.872 | E35: =E33*(1-'02 Budget Assumptions'!$E$38) -> 15055.872 | F35: =F33*(1-'02 Budget Assumptions'!$E$38) -> 16937.856 | G35: =G33*(1-'02 Budget Assumptions'!$E$38) -> 16937.856 | H35: =H33*(1-'02 Budget Assumptions'!$E$38) -> 18819.84 | I35: =I33*(1-'02 Budget Assumptions'!$E$38) -> 18819.84 | ... M35: =M33*(1-'02 Budget Assumptions'!$E$38) -> 13173.888
A36: Customer Deposits | B36: =B33*'02 Budget Assumptions'!$C$9 -> 8468.928 | C36: =C33*'02 Budget Assumptions'!$C$9 -> 9880.416 | D36: =D33*'02 Budget Assumptions'!$C$9 -> 11291.904 | E36: =E33*'02 Budget Assumptions'!$C$9 -> 11291.904 | F36: =F33*'02 Budget Assumptions'!$C$9 -> 12703.392 | G36: =G33*'02 Budget Assumptions'!$C$9 -> 12703.392 | H36: =H33*'02 Budget Assumptions'!$C$9 -> 14114.88 | I36: =I33*'02 Budget Assumptions'!$C$9 -> 14114.88 | ... M36: =M33*'02 Budget Assumptions'!$C$9 -> 9880.416
A37: Escrow Release | B37: =MIN(B36,B38*'02 Budget Assumptions'!$C$10) -> 8468.928 | C37: =MIN(C36,C38*'02 Budget Assumptions'!$C$10) -> 9880.416 | D37: =MIN(D36,D38*'02 Budget Assumptions'!$C$10) -> 11291.904 | E37: =MIN(E36,E38*'02 Budget Assumptions'!$C$10) -> 11291.904 | F37: =MIN(F36,F38*'02 Budget Assumptions'!$C$10) -> 12703.392 | G37: =MIN(G36,G38*'02 Budget Assumptions'!$C$10) -> 12703.392 | H37: =MIN(H36,H38*'02 Budget Assumptions'!$C$10) -> 14114.88 | I37: =MIN(I36,I38*'02 Budget Assumptions'!$C$10) -> 14114.88 | ... M37: =MIN(M36,M38*'02 Budget Assumptions'!$C$10) -> 9880.416
A38: Construction Spend | B38: ='02 Budget Assumptions'!$F$38*'02 Budget Assumptions'!B$29*(1+'02 Budget Assumptions'!$C$6) -> 23373 | C38: ='02 Budget Assumptions'!$F$38*'02 Budget Assumptions'!C$29*(1+'02 Budget Assumptions'!$C$6) -> 23373 | D38: ='02 Budget Assumptions'!$F$38*'02 Budget Assumptions'!D$29*(1+'02 Budget Assumptions'!$C$6) -> 26712 | E38: ='02 Budget Assumptions'!$F$38*'02 Budget Assumptions'!E$29*(1+'02 Budget Assumptions'!$C$6) -> 26712 | F38: ='02 Budget Assumptions'!$F$38*'02 Budget Assumptions'!F$29*(1+'02 Budget Assumptions'!$C$6) -> 30051 | G38: ='02 Budget Assumptions'!$F$38*'02 Budget Assumptions'!G$29*(1+'02 Budget Assumptions'!$C$6) -> 30051 | H38: ='02 Budget Assumptions'!$F$38*'02 Budget Assumptions'!H$29*(1+'02 Budget Assumptions'!$C$6) -> 30051 | I38: ='02 Budget Assumptions'!$F$38*'02 Budget Assumptions'!I$29*(1+'02 Budget Assumptions'!$C$6) -> 33390 | ... M38: ='02 Budget Assumptions'!$F$38*'02 Budget Assumptions'!M$29*(1+'02 Budget Assumptions'!$C$6) -> 20034
A40: Aggregates
A41: Total Off-plan Revenue | B41: =SUM(B7,B16,B25,B34) -> 73553.376 | C41: =SUM(C7,C16,C25,C34) -> 85812.272 | D41: =SUM(D7,D16,D25,D34) -> 98071.168 | E41: =SUM(E7,E16,E25,E34) -> 98071.168 | F41: =SUM(F7,F16,F25,F34) -> 110330.06 | G41: =SUM(G7,G16,G25,G34) -> 110330.06 | H41: =SUM(H7,H16,H25,H34) -> 122588.96 | I41: =SUM(I7,I16,I25,I34) -> 122588.96 | ... M41: =SUM(M7,M16,M25,M34) -> 85812.272
A42: Total Completed Revenue | B42: =SUM(B8,B17,B26,B35) -> 39306.384 | C42: =SUM(C8,C17,C26,C35) -> 45857.448 | D42: =SUM(D8,D17,D26,D35) -> 52408.512 | E42: =SUM(E8,E17,E26,E35) -> 52408.512 | F42: =SUM(F8,F17,F26,F35) -> 58959.576 | G42: =SUM(G8,G17,G26,G35) -> 58959.576 | H42: =SUM(H8,H17,H26,H35) -> 65510.64 | I42: =SUM(I8,I17,I26,I35) -> 65510.64 | ... M42: =SUM(M8,M17,M26,M35) -> 45857.448
A43: Total Customer Deposits | B43: =SUM(B9,B18,B27,B36) -> 33857.928 | C43: =SUM(C9,C18,C27,C36) -> 39500.916 | D43: =SUM(D9,D18,D27,D36) -> 45143.904 | E43: =SUM(E9,E18,E27,E36) -> 45143.904 | F43: =SUM(F9,F18,F27,F36) -> 50786.892 | G43: =SUM(G9,G18,G27,G36) -> 50786.892 | H43: =SUM(H9,H18,H27,H36) -> 56429.88 | I43: =SUM(I9,I18,I27,I36) -> 56429.88 | ... M43: =SUM(M9,M18,M27,M36) -> 39500.916
A44: Total Escrow Release | B44: =SUM(B10,B19,B28,B37) -> 33857.928 | C44: =SUM(C10,C19,C28,C37) -> 39500.916 | D44: =SUM(D10,D19,D28,D37) -> 45143.904 | E44: =SUM(E10,E19,E28,E37) -> 45143.904 | F44: =SUM(F10,F19,F28,F37) -> 50786.892 | G44: =SUM(G10,G19,G28,G37) -> 50786.892 | H44: =SUM(H10,H19,H28,H37) -> 56429.88 | I44: =SUM(I10,I19,I28,I37) -> 56429.88 | ... M44: =SUM(M10,M19,M28,M37) -> 39500.916
A45: Total Construction Spend | B45: =SUM(B11,B20,B29,B38) -> 82099.5 | C45: =SUM(C11,C20,C29,C38) -> 82099.5 | D45: =SUM(D11,D20,D29,D38) -> 93828 | E45: =SUM(E11,E20,E29,E38) -> 93828 | F45: =SUM(F11,F20,F29,F38) -> 105556.5 | G45: =SUM(G11,G20,G29,G38) -> 105556.5 | H45: =SUM(H11,H20,H29,H38) -> 105556.5 | I45: =SUM(I11,I20,I29,I38) -> 117285 | ... M45: =SUM(M11,M20,M29,M38) -> 70371
A46: Total Sales Value | B46: =SUM(B6,B15,B24,B33) -> 112859.76 | C46: =SUM(C6,C15,C24,C33) -> 131669.72 | D46: =SUM(D6,D15,D24,D33) -> 150479.68 | E46: =SUM(E6,E15,E24,E33) -> 150479.68 | F46: =SUM(F6,F15,F24,F33) -> 169289.64 | G46: =SUM(G6,G15,G24,G33) -> 169289.64 | H46: =SUM(H6,H15,H24,H33) -> 188099.6 | I46: =SUM(I6,I15,I24,I33) -> 188099.6 | ... M46: =SUM(M6,M15,M24,M33) -> 131669.72
A47: Working Capital Drivers
A48: Closing AR | B48: =('03 Revenue Budget'!B8+'03 Revenue Budget'!B9+'03 Revenue Budget'!B10+'03 Revenue Budget'!B11)*('02 Budget Assumptions'!$C$13/30) -> 412.67928 | C48: =('03 Revenue Budget'!C8+'03 Revenue Budget'!C9+'03 Revenue Budget'!C10+'03 Revenue Budget'!C11)*('02 Budget Assumptions'!$C$13/30) -> 469.26916 | D48: =('03 Revenue Budget'!D8+'03 Revenue Budget'!D9+'03 Revenue Budget'!D10+'03 Revenue Budget'!D11)*('02 Budget Assumptions'!$C$13/30) -> 525.85957 | E48: =('03 Revenue Budget'!E8+'03 Revenue Budget'!E9+'03 Revenue Budget'!E10+'03 Revenue Budget'!E11)*('02 Budget Assumptions'!$C$13/30) -> 526.02064 | F48: =('03 Revenue Budget'!F8+'03 Revenue Budget'!F9+'03 Revenue Budget'!F10+'03 Revenue Budget'!F11)*('02 Budget Assumptions'!$C$13/30) -> 582.61213 | G48: =('03 Revenue Budget'!G8+'03 Revenue Budget'!G9+'03 Revenue Budget'!G10+'03 Revenue Budget'!G11)*('02 Budget Assumptions'!$C$13/30) -> 582.77427 | H48: =('03 Revenue Budget'!H8+'03 Revenue Budget'!H9+'03 Revenue Budget'!H10+'03 Revenue Budget'!H11)*('02 Budget Assumptions'!$C$13/30) -> 639.36684 | I48: =('03 Revenue Budget'!I8+'03 Revenue Budget'!I9+'03 Revenue Budget'!I10+'03 Revenue Budget'!I11)*('02 Budget Assumptions'!$C$13/30) -> 639.53006 | ... M48: =('03 Revenue Budget'!M8+'03 Revenue Budget'!M9+'03 Revenue Budget'!M10+'03 Revenue Budget'!M11)*('02 Budget Assumptions'!$C$13/30) -> 470.89879
A49: Closing Customer Deposits | B49: =60000+B43-'03 Revenue Budget'!B7 -> 86857.928 | C49: =B49+C43-'03 Revenue Budget'!C7 -> 119335.51 | D49: =C49+D43-'03 Revenue Budget'!D7 -> 157432.67 | E49: =D49+E43-'03 Revenue Budget'!E7 -> 195506.34 | F49: =E49+F43-'03 Revenue Budget'!F7 -> 239199.43 | G49: =F49+G43-'03 Revenue Budget'!G7 -> 282868.88 | H49: =G49+H43-'03 Revenue Budget'!H7 -> 332157.58 | I49: =H49+I43-'03 Revenue Budget'!I7 -> 381422.49 | J49: =I49+J43-'03 Revenue Budget'!J7 -> 425020.52 | ... M49: =L49+M43-'03 Revenue Budget'!M7 -> 538741.56
A50: Closing AP | B50: =B45*('02 Budget Assumptions'!$C$14/30) -> 82099.5 | C50: =C45*('02 Budget Assumptions'!$C$14/30) -> 82099.5 | D50: =D45*('02 Budget Assumptions'!$C$14/30) -> 93828 | E50: =E45*('02 Budget Assumptions'!$C$14/30) -> 93828 | F50: =F45*('02 Budget Assumptions'!$C$14/30) -> 105556.5 | G50: =G45*('02 Budget Assumptions'!$C$14/30) -> 105556.5 | H50: =H45*('02 Budget Assumptions'!$C$14/30) -> 105556.5 | I50: =I45*('02 Budget Assumptions'!$C$14/30) -> 117285 | ... M50: =M45*('02 Budget Assumptions'!$C$14/30) -> 70371
A51: Closing Accrued Expenses | B51: =('07 Corporate Opex'!B15+'06 Sales and Marketing Budget'!B10)*0.5 -> 4685.72 | C51: =('07 Corporate Opex'!C15+'06 Sales and Marketing Budget'!C10)*0.5 -> 4686.02 | D51: =('07 Corporate Opex'!D15+'06 Sales and Marketing Budget'!D10)*0.5 -> 4733.821 | E51: =('07 Corporate Opex'!E15+'06 Sales and Marketing Budget'!E10)*0.5 -> 4734.123 | F51: =('07 Corporate Opex'!F15+'06 Sales and Marketing Budget'!F10)*0.5 -> 4781.926 | G51: =('07 Corporate Opex'!G15+'06 Sales and Marketing Budget'!G10)*0.5 -> 4782.23 | H51: =('07 Corporate Opex'!H15+'06 Sales and Marketing Budget'!H10)*0.5 -> 4830.0351 | I51: =('07 Corporate Opex'!I15+'06 Sales and Marketing Budget'!I10)*0.5 -> 4830.3411 | ... M51: =('07 Corporate Opex'!M15+'06 Sales and Marketing Budget'!M10)*0.5 -> 6761.7156
