Workbook

Sheet 1 Revenue Streams Summary
A1: Revenue Streams Summary
A2: Aurelia Developments LLC | Illustrative support schedules | Amounts in AED'000 unless stated
A4: Revenue Type | B4: Applicable Standard | C4: Recognition Method | D4: Timing of Recognition | E4: Typical Balance Sheet Impact | F4: Key Judgments
A5: Off-plan property sales | B5: IFRS 15 | C5: Point in time by default; over-time only if IFRS 15.35(c) is demonstrably met | D5: Generally at handover / transfer of control | E5: Contract liabilities before handover; receivable at transfer | F5: Enforceable right to payment; no alternative use; control transfer
A6: Completed property sales | B6: IFRS 15 | C6: Point in time | D6: At legal / practical transfer of control | E6: Receivable or cash; derecognition of inventory | F6: Handover documentation; possession; title / registration steps
A7: Development management fees | B7: IFRS 15 | C7: Over time | D7: As services are rendered | E7: Contract asset or receivable | F7: Measure of progress; variable consideration constraint
A8: Joint venture development fees | B8: IFRS 15 / IFRS 11 / IAS 28 | C8: Depends on substance; service fees under IFRS 15, equity returns outside revenue | D8: Over time or at milestone depending service | E8: Receivable or contract asset | F8: Whether fee is substantive service income or equity return
A9: Commercial leasing income | B9: IFRS 16 / IAS 40 | C9: Straight-line for operating lease income | D9: Over lease term | E9: Lease receivable / deferred straight-line balance | F9: Lease incentives; rent-free periods; variable rent
A10: Hospitality partnership income | B10: IFRS 15 or IFRS 16 depending arrangement | C10: Service-based over time or principal/agent assessment | D10: As services rendered or lease term | E10: Receivable / accrued income | F10: Principal vs agent; variable consideration

Sheet 2 Off-Plan Sales
A1: Off-Plan Sales Revenue Schedule
A2: Illustrative contract activity and deferred revenue rollforward
A4: Project | B4: Units Sold | C4: Average Price / Unit | D4: Contract Value | E4: Customer Deposits | F4: Units Handed Over | G4: Revenue Recognized | H4: Deferred Revenue | I4: Recognition Basis | J4: Comments
A5: Marina Residences Tower | B5: 84 | C5: 6200 | D5: =B5*C5 | E5: =D5*0.3 | F5: 18 | G5: =C5*F5 | H5: =D5-G5 | I5: Point in time | J5: Standard SPA; point-in-time recognition at handover
A6: Palm Waterfront Villas | B6: 16 | C6: 22000 | D6: =B6*C6 | E6: =D6*0.25 | F6: 7 | G6: =C6*F6 | H6: =D6-G6 | I6: Point in time | J6: Selective handovers in year
A7: Downtown Mixed-Use Development | B7: 68 | C7: 4950 | D7: =B7*C7 | E7: =D7*0.35 | F7: 15 | G7: =C7*F7 | H7: =D7-G7 | I7: Point in time | J7: Majority remains pre-handover
A8: Jumeirah Branded Residences | B8: 44 | C8: 8700 | D8: =B8*C8 | E8: =D8*0.28 | F8: 12 | G8: =C8*F8 | H8: =D8-G8 | I8: Point in time | J8: Branded product with staged collections
A9: Total | B9: =SUM(B5:B8) | D9: =SUM(D5:D8) | E9: =SUM(E5:E8) | F9: =SUM(F5:F8) | G9: =SUM(G5:G8) | H9: =SUM(H5:H8)

Sheet 3 Contract Liabilities
A1: Contract Liabilities Schedule
A2: Illustrative customer deposits and deferred revenue rollforward
A4: Project | B4: Opening Customer Deposits | C4: Current-Year Deposits | D4: Revenue Recognized | E4: Refunds / Cancellations | F4: Remaining Liability | G4: Escrow Balance Proxy | H4: Notes
A5: Marina Residences Tower | B5: 52000 | C5: ='2 Off-Plan Sales'!E5 | D5: ='2 Off-Plan Sales'!G5 | E5: 2500 | F5: =B5+C5-D5-E5 | G5: =MAX(0,C5*0.85) | H5: Contract liability until transfer of control
A6: Palm Waterfront Villas | B6: 64000 | C6: ='2 Off-Plan Sales'!E6 | D6: ='2 Off-Plan Sales'!G6 | E6: 1200 | F6: =B6+C6-D6-E6 | G6: =MAX(0,C6*0.85) | H6: Contract liability until transfer of control
A7: Downtown Mixed-Use Development | B7: 48000 | C7: ='2 Off-Plan Sales'!E7 | D7: ='2 Off-Plan Sales'!G7 | E7: 1800 | F7: =B7+C7-D7-E7 | G7: =MAX(0,C7*0.85) | H7: Contract liability until transfer of control
A8: Jumeirah Branded Residences | B8: 71000 | C8: ='2 Off-Plan Sales'!E8 | D8: ='2 Off-Plan Sales'!G8 | E8: 2200 | F8: =B8+C8-D8-E8 | G8: =MAX(0,C8*0.85) | H8: Contract liability until transfer of control
A9: Total | B9: =SUM(B5:B8) | C9: =SUM(C5:C8) | D9: =SUM(D5:D8) | E9: =SUM(E5:E8) | F9: =SUM(F5:F8) | G9: =SUM(G5:G8)

Sheet 4 Leasing Revenue
A1: Leasing Revenue Schedule
A2: Illustrative operating lease income recognized on a straight-line basis
A4: Property | B4: Lease Term | C4: Annual Rent | D4: Free Rent Months | E4: Straight-Line Annual Revenue | F4: Monthly Recognized Revenue | G4: Cash Rent in Year | H4: Recognition Method | I4: Comments
A5: Marina Retail Podium | B5: 5 years | C5: 18500 | D5: 2 | E5: =C5 | F5: =E5/12 | G5: =C5*(12-D5)/12 | H5: Straight-line | I5: Lease income outside IFRS 15; recognized over lease term
A6: Palm Clubhouse Retail | B6: 3 years | C6: 9200 | D6: 1 | E6: =C6 | F6: =E6/12 | G6: =C6*(12-D6)/12 | H6: Straight-line | I6: Lease income outside IFRS 15; recognized over lease term
A7: Downtown F&B Boulevard | B7: 7 years | C7: 14200 | D7: 3 | E7: =C7 | F7: =E7/12 | G7: =C7*(12-D7)/12 | H7: Straight-line | I7: Lease income outside IFRS 15; recognized over lease term
A8: Jumeirah Hospitality Arcade | B8: 4 years | C8: 11600 | D8: 2 | E8: =C8 | F8: =E8/12 | G8: =C8*(12-D8)/12 | H8: Straight-line | I8: Lease income outside IFRS 15; recognized over lease term
A9: Total | C9: =SUM(C5:C8) | E9: =SUM(E5:E8) | F9: =SUM(F5:F8) | G9: =SUM(G5:G8)
